Workbook

Sheet 入力 Inputs
A1: =IF('入力 Inputs'!$F$1="English","PPVA MASTER TOOL — ALL INPUTS",IF('入力 Inputs'!$F$1="日本語","PPVAマスターツール — 全入力項目","PPVAマスターツール — 全入力項目 / PPVA MASTER TOOL — ALL INPUTS")) -> PPVA MASTER TOOL — ALL INPUTS | F1: English
A2: =IF('入力 Inputs'!$F$1="English","Blue = adjustable inputs | Black = auto-calculated | Change inputs here to update",IF('入力 Inputs'!$F$1="日本語","青 = 変更可能な入力 | 黒 = 自動計算 | ここで入力を変更して計算シートを更新","青 = 変更可能な入力 | 黒 = 自動計算 | ここで入力を変更して計算シートを更新 / Blue = adjustable inputs | Black = auto-calculated | Change inputs here to update")) -> Blue = adjustable inputs | Black = auto-calculated | Change inputs here to update
A4: =IF('入力 Inputs'!$F$1="English","POLICY DETAILS",IF('入力 Inputs'!$F$1="日本語","証券詳細","証券詳細 / POLICY DETAILS")) -> POLICY DETAILS
A5: =IF('入力 Inputs'!$F$1="English","Policy Owner",IF('入力 Inputs'!$F$1="日本語","契約者","契約者 / Policy Owner")) -> Policy Owner | B5: Creating Yourself LLC
A6: =IF('入力 Inputs'!$F$1="English","Policy Issue Date",IF('入力 Inputs'!$F$1="日本語","証券発行日","証券発行日 / Policy Issue Date")) -> Policy Issue Date | B6: 46087
A7: =IF('入力 Inputs'!$F$1="English","Total Deposit",IF('入力 Inputs'!$F$1="日本語","預入総額","預入総額 / Total Deposit")) -> Total Deposit | B7: 13000000
A8: =IF('入力 Inputs'!$F$1="English","Policy Type",IF('入力 Inputs'!$F$1="日本語","保険種類","保険種類 / Policy Type")) -> Policy Type | B8: Variable Annuity (PPVA)
A10: =IF('入力 Inputs'!$F$1="English","PREMIUM LOAD (Step 1)",IF('入力 Inputs'!$F$1="日本語","プレミアムロード（ステップ1）","プレミアムロード（ステップ1） / PREMIUM LOAD (Step 1)")) -> PREMIUM LOAD (Step 1)
A11: =IF('入力 Inputs'!$F$1="English","Premium Load %",IF('入力 Inputs'!$F$1="日本語","プレミアムロード率","プレミアムロード率 / Premium Load %")) -> Premium Load % | B11: 0.06 | E11: 6% Premium Load on deposit
A12: =IF('入力 Inputs'!$F$1="English","3cStructures load %",IF('入力 Inputs'!$F$1="日本語","3cStructuresロード率","3cStructuresロード率 / 3cStructures load %")) -> 3cStructures load % | B12: 0.01
A13: =IF('入力 Inputs'!$F$1="English","Syndicated Capital holdback %",IF('入力 Inputs'!$F$1="日本語","Syndicated Capital保持率","Syndicated Capital保持率 / Syndicated Capital holdback %")) -> Syndicated Capital holdback % | B13: 0.05 | E13: ← 0.05 × Premium Load rate
A14: =IF('入力 Inputs'!$F$1="English","PB Investment Services holdback %",IF('入力 Inputs'!$F$1="日本語","PB Investment Services保持率","PB Investment Services保持率 / PB Investment Services holdback %")) -> PB Investment Services holdback % | B14: 0.05 | E14: ← 0.05 × Premium Load rate
A15: =IF('入力 Inputs'!$F$1="English","PBWR split % (of net to PB)",IF('入力 Inputs'!$F$1="日本語","PBWR分配率（PBネットの%）","PBWR分配率（PBネットの%） / PBWR split % (of net to PB)")) -> PBWR split % (of net to PB) | B15: 0.5 | E15: ← 50/50 split to Ohana
A16: =IF('入力 Inputs'!$F$1="English","Ohana share of net load %",IF('入力 Inputs'!$F$1="日本語","Ohanaのネットロード分配率","Ohanaのネットロード分配率 / Ohana share of net load %")) -> Ohana share of net load % | B16: =1-B15 -> 0.5 | E16: Auto = 100% minus PBWR share above
A18: =IF('入力 Inputs'!$F$1="English","ADMIN & BANK FEES (Step 2)",IF('入力 Inputs'!$F$1="日本語","管理・銀行手数料（ステップ2）","管理・銀行手数料（ステップ2） / ADMIN & BANK FEES (Step 2)")) -> ADMIN & BANK FEES (Step 2)
A19: =IF('入力 Inputs'!$F$1="English","Advantage annuity admin fee",IF('入力 Inputs'!$F$1="日本語","Advantage年金管理費","Advantage年金管理費 / Advantage annuity admin fee")) -> Advantage annuity admin fee | B19: 19500 | C19: Net to Fund Projected | D19: Net To Fund Actual | E19: Source: Sam Jensen email communication
A20: =IF('入力 Inputs'!$F$1="English","Misc. bank / setup fees",IF('入力 Inputs'!$F$1="日本語","その他銀行・設定費","その他銀行・設定費 / Misc. bank / setup fees")) -> Misc. bank / setup fees | B20: 1500 | C20: =(B7-(B7*B11)-(B7*B12)-B19-B20)*100% -> 12069000 | D20: 12069000 | E20: Source: Sam Jensen email communication — estimate
A21: Variance | C21: =C20-D20 -> 0
A23: =IF('入力 Inputs'!$F$1="English","Product",IF('入力 Inputs'!$F$1="日本語","商品","商品 / Product")) -> Product | B23: =IF('入力 Inputs'!$F$1="English","Alloc %",IF('入力 Inputs'!$F$1="日本語","配分率","配分率 / Alloc %")) -> Alloc % | C23: =IF('入力 Inputs'!$F$1="English","Amount ($)",IF('入力 Inputs'!$F$1="日本語","金額","金額 / Amount ($)")) -> Amount ($) | D23: =IF('入力 Inputs'!$F$1="English","Est. Rate",IF('入力 Inputs'!$F$1="日本語","推定利率","推定利率 / Est. Rate")) -> Est. Rate | E23: =IF('入力 Inputs'!$F$1="English","Weighted Return",IF('入力 Inputs'!$F$1="日本語","加重リターン","加重リターン / Weighted Return")) -> Weighted Return
A24: =IF('入力 Inputs'!$F$1="English"," GUARANTEED PRODUCTS ("&TEXT(SUM(B25:B27),"0%")&")",IF('入力 Inputs'!$F$1="日本語"," 保証商品 ("&TEXT(SUM(B25:B27),"0%")&")"," 保証商品 / GUARANTEED PRODUCTS ("&TEXT(SUM(B25:B27),"0%")&")")) -> GUARANTEED PRODUCTS (75%)
A25: =IF('入力 Inputs'!$F$1="English","Intl Fixed Rate Plan Plus",IF('入力 Inputs'!$F$1="日本語","国際固定金利プランプラス","国際固定金利プランプラス / Intl Fixed Rate Plan Plus")) -> Intl Fixed Rate Plan Plus | B25: 0.35 | C25: =(B7-(B7*B11)-(B7*B12)-B19-B20)*B25 -> 4224150 | D25: 0.058 | E25: =B25*D25 -> 0.0203
A26: =IF('入力 Inputs'!$F$1="English","Intl Fixed Rate Plan",IF('入力 Inputs'!$F$1="日本語","国際固定金利プラン","国際固定金利プラン / Intl Fixed Rate Plan")) -> Intl Fixed Rate Plan | B26: 0.25 | C26: =(B7-(B7*B11)-(B7*B12)-B19-B20)*B26 -> 3017250 | D26: 0.056 | E26: =B26*D26 -> 0.014
A27: =IF('入力 Inputs'!$F$1="English","US 5-Year FIA (AmFirst / Trailhead)",IF('入力 Inputs'!$F$1="日本語","米国5年FIA","米国5年FIA / US 5-Year FIA (AmFirst / Trailhead)")) -> US 5-Year FIA (AmFirst / Trailhead) | B27: 0.15 | C27: =(B7-(B7*B11)-(B7*B12)-B19-B20)*B27 -> 1810350 | D27: 0.0515 | E27: =B27*D27 -> 0.007725
A28: =IF('入力 Inputs'!$F$1="English"," NON-GUARANTEED ("&TEXT(SUM(B29:B31),"0%")&")",IF('入力 Inputs'!$F$1="日本語"," 非保証 ("&TEXT(SUM(B29:B31),"0%")&")"," 非保証 / NON-GUARANTEED ("&TEXT(SUM(B29:B31),"0%")&")")) -> NON-GUARANTEED (25%)
A29: =IF('入力 Inputs'!$F$1="English","AAIDX (Alt Income)",IF('入力 Inputs'!$F$1="日本語","AAIDX（代替収益）","AAIDX（代替収益） / AAIDX (Alt Income)")) -> AAIDX (Alt Income) | B29: 0.1 | C29: =(B7-(B7*B11)-(B7*B12)-B19-B20)*B29 -> 1206900 | D29: 0.07 | E29: =B29*D29 -> 0.007
A30: =IF('入力 Inputs'!$F$1="English","ACRE III (CRE Fund)",IF('入力 Inputs'!$F$1="日本語","ACRE III（CREファンド）","ACRE III（CREファンド） / ACRE III (CRE Fund)")) -> ACRE III (CRE Fund) | B30: 0.1 | C30: =(B7-(B7*B11)-(B7*B12)-B19-B20)*B30 -> 1206900 | D30: 0.12 | E30: =B30*D30 -> 0.012
A31: =IF('入力 Inputs'!$F$1="English","Cash (Liquidity)",IF('入力 Inputs'!$F$1="日本語","現金（流動性）","現金（流動性） / Cash (Liquidity)")) -> Cash (Liquidity) | B31: 0.05 | C31: =(B7-(B7*B11)-(B7*B12)-B19-B20)*B31 -> 603450 | D31: 0.03 | E31: =B31*D31 -> 0.0015
A32: =IF('入力 Inputs'!$F$1="English","GROSS WEIGHTED TOTAL",IF('入力 Inputs'!$F$1="日本語","加重合計","加重合計 / GROSS WEIGHTED TOTAL")) -> GROSS WEIGHTED TOTAL | B32: =B25+B26+B27+B29+B30+B31 -> 1 | C32: =SUM(C26+C25+C27+C29+C30+C31) -> 12069000 | D32: =AVERAGE(D29:D31,D25:D27) -> 0.06425 | E32: =SUM(E25:E31) -> 0.062525
A34: =IF('入力 Inputs'!$F$1="English","ANNUITY COMMISSION RATES",IF('入力 Inputs'!$F$1="日本語","年金コミッション率","年金コミッション率 / ANNUITY COMMISSION RATES")) -> ANNUITY COMMISSION RATES
A35: =IF('入力 Inputs'!$F$1="English","Product",IF('入力 Inputs'!$F$1="日本語","商品","商品 / Product")) -> Product | B35: =IF('入力 Inputs'!$F$1="English","OGA %",IF('入力 Inputs'!$F$1="日本語","OGA率","OGA率 / OGA %")) -> OGA % | C35: =IF('入力 Inputs'!$F$1="English","Processor (95%) %",IF('入力 Inputs'!$F$1="日本語","プロセッサー率","プロセッサー率 / Processor (95%) %")) -> Processor (95%) % | D35: =IF('入力 Inputs'!$F$1="English","Regional %",IF('入力 Inputs'!$F$1="日本語","リージョナル率","リージョナル率 / Regional %")) -> Regional % | E35: =IF('入力 Inputs'!$F$1="English","Notes",IF('入力 Inputs'!$F$1="日本語","備考","備考 / Notes")) -> Notes
A36: =IF('入力 Inputs'!$F$1="English","Intl Fixed Rate Plan Plus",IF('入力 Inputs'!$F$1="日本語","国際固定金利プランプラス","国際固定金利プランプラス / Intl Fixed Rate Plan Plus")) -> Intl Fixed Rate Plan Plus | B36: 0.05 | C36: 0.0475 | D36: 0.045
A37: =IF('入力 Inputs'!$F$1="English","Intl Fixed Rate Plan",IF('入力 Inputs'!$F$1="日本語","国際固定金利プラン","国際固定金利プラン / Intl Fixed Rate Plan")) -> Intl Fixed Rate Plan | B37: 0.043 | C37: 0.04085 | D37: 0.0387
A38: =IF('入力 Inputs'!$F$1="English","US 5-Year FIA (AmFirst / Trailhead)",IF('入力 Inputs'!$F$1="日本語","米国5年FIA","米国5年FIA / US 5-Year FIA (AmFirst / Trailhead)")) -> US 5-Year FIA (AmFirst / Trailhead) | B38: 0.0775 | C38: =B38*0.95 -> 0.073625 | D38: 0.045 | E38: No Processor tier in Axonic schedule. Regional = 4.5% per Axonic grid.
A40: =IF('入力 Inputs'!$F$1="English","ANNUAL FUND CHARGES (Step 4)",IF('入力 Inputs'!$F$1="日本語","年間ファンド手数料（ステップ4）","年間ファンド手数料（ステップ4） / ANNUAL FUND CHARGES (Step 4)")) -> ANNUAL FUND CHARGES (Step 4)
A41: =IF('入力 Inputs'!$F$1="English","Advantage M&E %",IF('入力 Inputs'!$F$1="日本語","Advantage M&E率","Advantage M&E率 / Advantage M&E %")) -> Advantage M&E % | B41: 0.0015
A42: =IF('入力 Inputs'!$F$1="English","Syndicated / Stephen RIA %",IF('入力 Inputs'!$F$1="日本語","シンジケート/Stephen RIA率","シンジケート/Stephen RIA率 / Syndicated / Stephen RIA %")) -> Syndicated / Stephen RIA % | B42: 0.0015
A43: =IF('入力 Inputs'!$F$1="English","Inspira custodian %",IF('入力 Inputs'!$F$1="日本語","インスピラ保管料率","インスピラ保管料率 / Inspira custodian %")) -> Inspira custodian % | B43: 0.0005 | E43: Updated per Inspira fee schedule
A44: =IF('入力 Inputs'!$F$1="English","Money Manager fee %",IF('入力 Inputs'!$F$1="日本語","マネーマネージャー手数料率","マネーマネージャー手数料率 / Money Manager fee %")) -> Money Manager fee % | B44: 0 | E44: Default 0% — set rate when money manager is engaged
A45: =IF('入力 Inputs'!$F$1="English","Est. Year 1 actual fees",IF('入力 Inputs'!$F$1="日本語","推定初年度実費","推定初年度実費 / Est. Year 1 actual fees")) -> Est. Year 1 actual fees | B45: 26000 | E45: ← adjust when confirmed (incl. Q1)
A47: =IF('入力 Inputs'!$F$1="English","GROWTH ASSUMPTIONS (Step 5)",IF('入力 Inputs'!$F$1="日本語","成長仮定（ステップ5）","成長仮定（ステップ5） / GROWTH ASSUMPTIONS (Step 5)")) -> GROWTH ASSUMPTIONS (Step 5)
A48: =IF('入力 Inputs'!$F$1="English","Blended portfolio return (auto)",IF('入力 Inputs'!$F$1="日本語","ブレンドポートフォリオリターン（自動）","ブレンドポートフォリオリターン（自動） / Blended portfolio return (auto)")) -> Blended portfolio return (auto) | B48: =SUMPRODUCT(B25:B27,D25:D27)+SUMPRODUCT(B29:B31,D29:D31) -> 0.062525 | E48: Auto-calculated from fund allocations above
A49: =IF('入力 Inputs'!$F$1="English","Override rate?",IF('入力 Inputs'!$F$1="日本語","オーバーライド率？","オーバーライド率？ / Override rate?")) -> Override rate? | B49: No | E49: Type "Yes" to use manual rate below instead of blended
A50: =IF('入力 Inputs'!$F$1="English","Manual override rate",IF('入力 Inputs'!$F$1="日本語","手動オーバーライド率","手動オーバーライド率 / Manual override rate")) -> Manual override rate | B50: 0.065 | E50: Only used if Override = "Yes"
A51: =IF('入力 Inputs'!$F$1="English","Assumed growth rate (used in projections)",IF('入力 Inputs'!$F$1="日本語","適用成長率（予測に使用）","適用成長率（予測に使用） / Assumed growth rate (used in projections)")) -> Assumed growth rate (used in projections) | B51: =IF(UPPER(B49)="YES",B50,B48) -> 0.062525 | E51: ← This rate feeds all projections
A53: =IF('入力 Inputs'!$F$1="English","CLIENT / INSURED DETAILS (Step 6)",IF('入力 Inputs'!$F$1="日本語","顧客・被保険者情報（ステップ6）","顧客・被保険者情報（ステップ6） / CLIENT / INSURED DETAILS (Step 6)")) -> CLIENT / INSURED DETAILS (Step 6)
A54: =IF('入力 Inputs'!$F$1="English","Insured Name",IF('入力 Inputs'!$F$1="日本語","被保険者名","被保険者名 / Insured Name")) -> Insured Name | B54: Akito Takata
A55: =IF('入力 Inputs'!$F$1="English","Current Age",IF('入力 Inputs'!$F$1="日本語","現在の年齢","現在の年齢 / Current Age")) -> Current Age | B55: 46
A56: =IF('入力 Inputs'!$F$1="English","Premium Charge %",IF('入力 Inputs'!$F$1="日本語","プレミアムチャージ率","プレミアムチャージ率 / Premium Charge %")) -> Premium Charge % | B56: =B11+B12 -> 0.07 | E56: Auto = Premium Load + 3cStructures load
A57: =IF('入力 Inputs'!$F$1="English","Year 1 COI (Cost of Insurance)",IF('入力 Inputs'!$F$1="日本語","初年度COI（保険コスト）","初年度COI（保険コスト） / Year 1 COI (Cost of Insurance)")) -> Year 1 COI (Cost of Insurance) | B57: 118.57 | E57: Source: Carrier illustration
A59: =IF('入力 Inputs'!$F$1="English","TAX & FX ASSUMPTIONS (Step 7)",IF('入力 Inputs'!$F$1="日本語","税金・為替仮定（ステップ7）","税金・為替仮定（ステップ7） / TAX & FX ASSUMPTIONS (Step 7)")) -> TAX & FX ASSUMPTIONS (Step 7)
A60: =IF('入力 Inputs'!$F$1="English","Current Insurance CSV (USD)",IF('入力 Inputs'!$F$1="日本語","現行保険解約返戻金（米ドル）","現行保険解約返戻金（米ドル） / Current Insurance CSV (USD)")) -> Current Insurance CSV (USD) | B60: 18963106 | E60: Current portfolio cash surrender value
A61: =IF('入力 Inputs'!$F$1="English","Basis (USD)",IF('入力 Inputs'!$F$1="日本語","基準額（米ドル）","基準額（米ドル） / Basis (USD)")) -> Basis (USD) | B61: 16195676 | E61: Original cost basis in existing policy
A62: =IF('入力 Inputs'!$F$1="English","FX at Original Contribution",IF('入力 Inputs'!$F$1="日本語","拠出時の為替レート（円/ドル）","拠出時の為替レート（円/ドル） / FX at Original Contribution")) -> FX at Original Contribution | B62: 110
A63: =IF('入力 Inputs'!$F$1="English","Current FX Rate",IF('入力 Inputs'!$F$1="日本語","現在の為替レート（円/ドル）","現在の為替レート（円/ドル） / Current FX Rate")) -> Current FX Rate | B63: 150
A64: =IF('入力 Inputs'!$F$1="English","FX at LLC Dissolution",IF('入力 Inputs'!$F$1="日本語","LLC解散時の為替レート（円/ドル）","LLC解散時の為替レート（円/ドル） / FX at LLC Dissolution")) -> FX at LLC Dissolution | B64: 160 | E64: Assumed rate at exit
A65: =IF('入力 Inputs'!$F$1="English","Assumed CSV Growth Rate",IF('入力 Inputs'!$F$1="日本語","解約返戻金成長率","解約返戻金成長率 / Assumed CSV Growth Rate")) -> Assumed CSV Growth Rate | B65: 0.06 | E65: Growth rate for existing portfolio projection
A66: =IF('入力 Inputs'!$F$1="English","Tax Rate",IF('入力 Inputs'!$F$1="日本語","税率","税率 / Tax Rate")) -> Tax Rate | B66: 0.55 | E66: Japanese income tax rate on gains
A67: =IF('入力 Inputs'!$F$1="English","Basis in JPY (auto)",IF('入力 Inputs'!$F$1="日本語","基準額（円・自動）","基準額（円・自動） / Basis in JPY (auto)")) -> Basis in JPY (auto) | B67: =B61*B62 -> 1781524360 | E67: Basis x FX at contribution
A69: =IF('入力 Inputs'!$F$1="English","SURRENDER CHARGE SCHEDULE (Step 8)",IF('入力 Inputs'!$F$1="日本語","解約手数料スケジュール（ステップ8）","解約手数料スケジュール（ステップ8） / SURRENDER CHARGE SCHEDULE (Step 8)")) -> SURRENDER CHARGE SCHEDULE (Step 8)
A70: =IF('入力 Inputs'!$F$1="English","Year",IF('入力 Inputs'!$F$1="日本語","年","年 / Year")) -> Year | B70: =IF('入力 Inputs'!$F$1="English","Surrender Charge %",IF('入力 Inputs'!$F$1="日本語","解約手数料率","解約手数料率 / Surrender Charge %")) -> Surrender Charge % | C70: =IF('入力 Inputs'!$F$1="English","Net CSV %",IF('入力 Inputs'!$F$1="日本語","正味CSV率","正味CSV率 / Net CSV %")) -> Net CSV %
A71: 1 | B71: 0.95 | C71: =1-B71 -> 0.05
A72: 2 | B72: 0.9 | C72: =1-B72 -> 0.1
A73: 3 | B73: 0.8 | C73: =1-B73 -> 0.2
A74: 4 | B74: 0.7 | C74: =1-B74 -> 0.3
A75: 5 | B75: 0.6 | C75: =1-B75 -> 0.4
A76: 6 | B76: 0 | C76: =1-B76 -> 1
A77: 7 | B77: 0 | C77: =1-B77 -> 1
A78: 8 | B78: 0 | C78: =1-B78 -> 1
A79: 9 | B79: 0 | C79: =1-B79 -> 1
A80: 10 | B80: 0 | C80: =1-B80 -> 1
A82: =IF('入力 Inputs'!$F$1="English","CARRIER ILLUSTRATION RATES (Step 9)",IF('入力 Inputs'!$F$1="日本語","キャリアイラストレーション率（ステップ9）","キャリアイラストレーション率（ステップ9） / CARRIER ILLUSTRATION RATES (Step 9)")) -> CARRIER ILLUSTRATION RATES (Step 9)
A83: =IF('入力 Inputs'!$F$1="English","Variable Basis Rate",IF('入力 Inputs'!$F$1="日本語","変動基準金利","変動基準金利 / Variable Basis Rate")) -> Variable Basis Rate | B83: =B51 -> 0.062525 | E83: Base illustration rate
A84: =IF('入力 Inputs'!$F$1="English","1st Alternate Rate",IF('入力 Inputs'!$F$1="日本語","第1代替金利","第1代替金利 / 1st Alternate Rate")) -> 1st Alternate Rate | B84: 0.065
A85: =IF('入力 Inputs'!$F$1="English","2nd Alternate Rate",IF('入力 Inputs'!$F$1="日本語","第2代替金利","第2代替金利 / 2nd Alternate Rate")) -> 2nd Alternate Rate | B85: 0.07
A86: =IF('入力 Inputs'!$F$1="English","Projection Horizon (years)",IF('入力 Inputs'!$F$1="日本語","予測期間（年）","予測期間（年） / Projection Horizon (years)")) -> Projection Horizon (years) | B86: 60
A87: =IF('入力 Inputs'!$F$1="English","Net to Policy (auto)",IF('入力 Inputs'!$F$1="日本語","正味保険料（自動）","正味保険料（自動） / Net to Policy (auto)")) -> Net to Policy (auto) | B87: =B7*(1-B56) -> 12090000 | E87: Deposit x (1 - Premium Charge)
A90: =IF('入力 Inputs'!$F$1="English","COI ESCALATION (Step 11)",IF('入力 Inputs'!$F$1="日本語","COI成長仮定（ステップ11）","COI成長仮定（ステップ11） / COI ESCALATION (Step 11)")) -> COI ESCALATION (Step 11)
A91: =IF('入力 Inputs'!$F$1="English","Annual COI Growth Rate",IF('入力 Inputs'!$F$1="日本語","年間COI成長率","年間COI成長率 / Annual COI Growth Rate")) -> Annual COI Growth Rate | B91: 0.03 | E91: =IF('入力 Inputs'!$F$1="English","COI increases with age — typically 3-5% annually",IF('入力 Inputs'!$F$1="日本語","COIは年齢とともに増加 — 典型的に年3-5%","COIは年齢とともに増加 — 典型的に年3-5% / COI increases with age — typically 3-5% annually")) -> COI increases with age — typically 3-5% annually
A93: =IF('入力 Inputs'!$F$1="English","ALTERNATE DESIGN B SURRENDER SCHEDULE (Step 12)",IF('入力 Inputs'!$F$1="日本語","代替デザインB解約スケジュール（ステップ12）","代替デザインB解約スケジュール（ステップ12） / ALTERNATE DESIGN B SURRENDER SCHEDULE (Step 12)")) -> ALTERNATE DESIGN B SURRENDER SCHEDULE (Step 12)
A94: =IF('入力 Inputs'!$F$1="English","Design B Name",IF('入力 Inputs'!$F$1="日本語","デザインB名","デザインB名 / Design B Name")) -> Design B Name | B94: Honey
A95: =IF('入力 Inputs'!$F$1="English","Design B Illustration Rate",IF('入力 Inputs'!$F$1="日本語","デザインBイラストレーション率","デザインBイラストレーション率 / Design B Illustration Rate")) -> Design B Illustration Rate | B95: 0.055
A96: =IF('入力 Inputs'!$F$1="English","Year",IF('入力 Inputs'!$F$1="日本語","年","年 / Year")) -> Year | B96: =IF('入力 Inputs'!$F$1="English","Design B Surrender %",IF('入力 Inputs'!$F$1="日本語","デザインB解約手数料率","デザインB解約手数料率 / Design B Surrender %")) -> Design B Surrender %
A97: 1 | B97: 1
A98: 2 | B98: 0.4
A99: 3 | B99: 0.2
A100: 4 | B100: 0.1
A101: 5 | B101: 0.05
A102: 6 | B102: 0
A103: 7 | B103: 0
A104: 8 | B104: 0
A105: 9 | B105: 0
A106: 10 | B106: 0

Sheet 計算 Calculations
A1: =IF('入力 Inputs'!$F$1="English","PPVA DEAL MODEL — FULL CALCULATION DETAIL",IF('入力 Inputs'!$F$1="日本語","PPVA取引モデル — 計算詳細","PPVA取引モデル — 計算詳細 / PPVA DEAL MODEL — FULL CALCULATION DETAIL")) -> PPVA DEAL MODEL — FULL CALCULATION DETAIL
A2: =IF('入力 Inputs'!$F$1="English","All values pull from Inputs sheet. Update inputs there.",IF('入力 Inputs'!$F$1="日本語","全ての値は入力シートから取得。入力を変更すると自動再計算","全ての値は入力シートから取得。入力を変更すると自動再計算 / All values pull from Inputs sheet. Update inputs there.")) -> All values pull from Inputs sheet. Update inputs there.
A4: =IF('入力 Inputs'!$F$1="English","STEP 1 — PREMIUM LOAD",IF('入力 Inputs'!$F$1="日本語","ステップ1 — プレミアムロード","ステップ1 — プレミアムロード / STEP 1 — PREMIUM LOAD")) -> STEP 1 — PREMIUM LOAD
A5: =IF('入力 Inputs'!$F$1="English","Total Deposit",IF('入力 Inputs'!$F$1="日本語","預入総額","預入総額 / Total Deposit")) -> Total Deposit | B5: ='入力 Inputs'!B7 -> 13000000
A6: =IF('入力 Inputs'!$F$1="English","Premium Load (6%)",IF('入力 Inputs'!$F$1="日本語","プレミアムロード（6%）","プレミアムロード（6%） / Premium Load (6%)")) -> Premium Load (6%) | B6: ='入力 Inputs'!B7*'入力 Inputs'!B11 -> 780000 | C6: ='入力 Inputs'!B11 -> 0.06
A7: =IF('入力 Inputs'!$F$1="English","3cStructures (1%)",IF('入力 Inputs'!$F$1="日本語","3cStructures（1%）","3cStructures（1%） / 3cStructures (1%)")) -> 3cStructures (1%) | B7: ='入力 Inputs'!B7*'入力 Inputs'!B12 -> 130000 | C7: ='入力 Inputs'!B12 -> 0.01
A8: =IF('入力 Inputs'!$F$1="English","Total Premium Load",IF('入力 Inputs'!$F$1="日本語","プレミアムロード合計","プレミアムロード合計 / Total Premium Load")) -> Total Premium Load | B8: =B6+B7 -> 910000 | C8: ='入力 Inputs'!B11+'入力 Inputs'!B12 -> 0.07
A10: =IF('入力 Inputs'!$F$1="English","Premium Load Payout Waterfall",IF('入力 Inputs'!$F$1="日本語","プレミアムロード支払ウォーターフォール","プレミアムロード支払ウォーターフォール / Premium Load Payout Waterfall")) -> Premium Load Payout Waterfall
A11: =IF('入力 Inputs'!$F$1="English","Syndicated Capital Holdback (0.05 × 6%)",IF('入力 Inputs'!$F$1="日本語","Syndicated Capital保持（0.05 × 6%）","Syndicated Capital保持（0.05 × 6%） / Syndicated Capital Holdback (0.05 × 6%)")) -> Syndicated Capital Holdback (0.05 × 6%) | B11: =B6*'入力 Inputs'!B13 -> 39000 | C11: ='入力 Inputs'!B13 -> 0.05 | E11: Syndicated Capital retains 5% of premium load
A12: =IF('入力 Inputs'!$F$1="English","Net to Stephen (Syndicated)",IF('入力 Inputs'!$F$1="日本語","Stephenへのネット（Syndicated）","Stephenへのネット（Syndicated） / Net to Stephen (Syndicated)")) -> Net to Stephen (Syndicated) | B12: =B6-B11 -> 741000 | E12: Sweeps from Stephen to PB Investment Services
A13: =IF('入力 Inputs'!$F$1="English","PB Investment Services Holdback (0.05 × 6%)",IF('入力 Inputs'!$F$1="日本語","PB Investment Services保持（0.05 × 6%）","PB Investment Services保持（0.05 × 6%） / PB Investment Services Holdback (0.05 × 6%)")) -> PB Investment Services Holdback (0.05 × 6%) | B13: =B6*'入力 Inputs'!B14 -> 39000 | C13: ='入力 Inputs'!B14 -> 0.05 | E13: PB Investment Services retains 5% of premium load
A14: =IF('入力 Inputs'!$F$1="English","PB sends to PBWR (5.4%)",IF('入力 Inputs'!$F$1="日本語","PBからPBWRへ送金（5.4%）","PBからPBWRへ送金（5.4%） / PB sends to PBWR (5.4%)")) -> PB sends to PBWR (5.4%) | B14: =B12-B13 -> 702000 | C14: =B14/'入力 Inputs'!B7 -> 0.054 | E14: Effective rate 5.4% of deposit
A15: =IF('入力 Inputs'!$F$1="English"," PBWR share (50%)",IF('入力 Inputs'!$F$1="日本語"," PBWR分配（50%）"," PBWR分配（50%） / PBWR share (50%)")) -> PBWR share (50%) | B15: =B14*'入力 Inputs'!B15 -> 351000 | C15: ='入力 Inputs'!B15 -> 0.5 | E15: ← verify per Ohana contract
A16: =IF('入力 Inputs'!$F$1="English"," Ohana share (50%)",IF('入力 Inputs'!$F$1="日本語"," Ohana分配（50%）"," Ohana分配（50%） / Ohana share (50%)")) -> Ohana share (50%) | B16: =B14*'入力 Inputs'!B16 -> 351000 | C16: ='入力 Inputs'!B16 -> 0.5 | E16: ← verify per Ohana contract
A18: =IF('入力 Inputs'!$F$1="English","STEP 2 — ADMIN & BANK FEES",IF('入力 Inputs'!$F$1="日本語","ステップ2 — 管理・銀行手数料","ステップ2 — 管理・銀行手数料 / STEP 2 — ADMIN & BANK FEES")) -> STEP 2 — ADMIN & BANK FEES
A19: =IF('入力 Inputs'!$F$1="English","Advantage annuity admin fee",IF('入力 Inputs'!$F$1="日本語","Advantage年金管理費","Advantage年金管理費 / Advantage annuity admin fee")) -> Advantage annuity admin fee | B19: ='入力 Inputs'!B19 -> 19500 | D19: Source: Sam Jensen email ( verify where this is being paid)
A20: =IF('入力 Inputs'!$F$1="English","Misc. bank / setup fees",IF('入力 Inputs'!$F$1="日本語","その他銀行・設定費","その他銀行・設定費 / Misc. bank / setup fees")) -> Misc. bank / setup fees | B20: ='入力 Inputs'!B20 -> 1500 | D20: Source: Sam Jensen email — Confirm total figure
A21: =IF('入力 Inputs'!$F$1="English","Total Admin & Fees",IF('入力 Inputs'!$F$1="日本語","管理手数料合計","管理手数料合計 / Total Admin & Fees")) -> Total Admin & Fees | B21: =B19+B20 -> 21000
A23: =IF('入力 Inputs'!$F$1="English","NET WIRED TO INSPIRA",IF('入力 Inputs'!$F$1="日本語","インスピラへの正味送金額","インスピラへの正味送金額 / NET WIRED TO INSPIRA")) -> NET WIRED TO INSPIRA | B23: ='入力 Inputs'!B7-B8-B21 -> 12069000
A25: =IF('入力 Inputs'!$F$1="English","STEP 3 — INSPIRA FUND ALLOCATIONS",IF('入力 Inputs'!$F$1="日本語","ステップ3 — インスピラファンド配分","ステップ3 — インスピラファンド配分 / STEP 3 — INSPIRA FUND ALLOCATIONS")) -> STEP 3 — INSPIRA FUND ALLOCATIONS
A26: =IF('入力 Inputs'!$F$1="English","Product",IF('入力 Inputs'!$F$1="日本語","商品","商品 / Product")) -> Product | B26: Alloc % | C26: Amount | D26: Est. Rate | E26: Wtd Return | F26: OGA Comm | H26: Proc Comm | I26: Reg Comm
A27: =IF('入力 Inputs'!$F$1="English","GUARANTEED PRODUCTS (75%)",IF('入力 Inputs'!$F$1="日本語","保証商品（75%）","保証商品（75%） / GUARANTEED PRODUCTS (75%)")) -> GUARANTEED PRODUCTS (75%)
A28: =IF('入力 Inputs'!$F$1="English","Intl Fixed Rate Plan Plus",IF('入力 Inputs'!$F$1="日本語","国際固定金利プランプラス","国際固定金利プランプラス / Intl Fixed Rate Plan Plus")) -> Intl Fixed Rate Plan Plus | B28: ='入力 Inputs'!B25 -> 0.35 | C28: ='入力 Inputs'!C25 -> 4224150 | D28: ='入力 Inputs'!D25 -> 0.058 | E28: =B28*D28 -> 0.0203 | F28: ='入力 Inputs'!C25*'入力 Inputs'!B36 -> 211207.5 | H28: ='入力 Inputs'!C25*'入力 Inputs'!C36 -> 200647.12 | I28: ='入力 Inputs'!C25*'入力 Inputs'!D36 -> 190086.75
A29: =IF('入力 Inputs'!$F$1="English","Intl Fixed Rate Plan",IF('入力 Inputs'!$F$1="日本語","国際固定金利プラン","国際固定金利プラン / Intl Fixed Rate Plan")) -> Intl Fixed Rate Plan | B29: ='入力 Inputs'!B26 -> 0.25 | C29: ='入力 Inputs'!C26 -> 3017250 | D29: ='入力 Inputs'!D26 -> 0.056 | E29: =B29*D29 -> 0.014 | F29: ='入力 Inputs'!C26*'入力 Inputs'!B37 -> 129741.75 | H29: ='入力 Inputs'!C26*'入力 Inputs'!C37 -> 123254.66 | I29: ='入力 Inputs'!C26*'入力 Inputs'!D37 -> 116767.57
A30: =IF('入力 Inputs'!$F$1="English","US 5-Year FIA (AmFirst / Trailhead)",IF('入力 Inputs'!$F$1="日本語","米国5年FIA","米国5年FIA / US 5-Year FIA (AmFirst / Trailhead)")) -> US 5-Year FIA (AmFirst / Trailhead) | B30: ='入力 Inputs'!B27 -> 0.15 | C30: ='入力 Inputs'!C27 -> 1810350 | D30: ='入力 Inputs'!D27 -> 0.0515 | E30: =B30*D30 -> 0.007725 | F30: ='入力 Inputs'!C27*'入力 Inputs'!B38 -> 140302.12 | H30: ='入力 Inputs'!C38*C30 -> 133287.02 | I30: ='入力 Inputs'!C27*'入力 Inputs'!D38 -> 81465.75
A31: =IF('入力 Inputs'!$F$1="English","Guaranteed Subtotal (75%)",IF('入力 Inputs'!$F$1="日本語","保証商品小計（75%）","保証商品小計（75%） / Guaranteed Subtotal (75%)")) -> Guaranteed Subtotal (75%) | B31: =B28+B29+B30 -> 0.75 | C31: =C28+C29+C30 -> 9051750 | E31: =E28+E29+E30 -> 0.042025 | F31: =F28+F29+F30 -> 481251.38 | H31: =H28+H29+H30 -> 457188.81 | I31: =I28+I29+I30 -> 388320.08
A33: =IF('入力 Inputs'!$F$1="English","NON-GUARANTEED (25%)",IF('入力 Inputs'!$F$1="日本語","非保証（25%）","非保証（25%） / NON-GUARANTEED (25%)")) -> NON-GUARANTEED (25%)
A34: =IF('入力 Inputs'!$F$1="English","AAIDX (Alt Income — Investment Fund)",IF('入力 Inputs'!$F$1="日本語","AAIDX（代替収益）","AAIDX（代替収益） / AAIDX (Alt Income — Investment Fund)")) -> AAIDX (Alt Income — Investment Fund) | B34: ='入力 Inputs'!B29 -> 0.1 | C34: ='入力 Inputs'!C29 -> 1206900 | D34: ='入力 Inputs'!D29 -> 0.07 | E34: =B34*D34 -> 0.007 | F34: — | H34: — | I34: —
A35: =IF('入力 Inputs'!$F$1="English","ACRE III (CRE Fund — Investment Fund)",IF('入力 Inputs'!$F$1="日本語","ACRE III（CREファンド）","ACRE III（CREファンド） / ACRE III (CRE Fund — Investment Fund)")) -> ACRE III (CRE Fund — Investment Fund) | B35: ='入力 Inputs'!B30 -> 0.1 | C35: ='入力 Inputs'!C30 -> 1206900 | D35: ='入力 Inputs'!D30 -> 0.12 | E35: =B35*D35 -> 0.012 | F35: — | H35: — | I35: —
A36: =IF('入力 Inputs'!$F$1="English","Cash (Liquidity)",IF('入力 Inputs'!$F$1="日本語","現金（流動性）","現金（流動性） / Cash (Liquidity)")) -> Cash (Liquidity) | B36: ='入力 Inputs'!B31 -> 0.05 | C36: ='入力 Inputs'!C31 -> 603450 | D36: ='入力 Inputs'!D31 -> 0.03 | E36: =B36*D36 -> 0.0015 | F36: — | H36: — | I36: —
A37: =IF('入力 Inputs'!$F$1="English","Non-Guaranteed Subtotal (25%)",IF('入力 Inputs'!$F$1="日本語","非保証商品小計（25%）","非保証商品小計（25%） / Non-Guaranteed Subtotal (25%)")) -> Non-Guaranteed Subtotal (25%) | B37: =B34+B35+B36 -> 0.25 | C37: =C34+C35+C36 -> 3017250 | E37: =E34+E35+E36 -> 0.0205 | F37: — | H37: — | I37: —
A39: =IF('入力 Inputs'!$F$1="English","TOTAL ALLOCATION",IF('入力 Inputs'!$F$1="日本語","配分合計","配分合計 / TOTAL ALLOCATION")) -> TOTAL ALLOCATION | B39: =B31+B37 -> 1 | C39: =C31+C37 -> 12069000 | E39: =E31+E37 -> 0.062525 | F39: =F31 -> 481251.38 | H39: =H31 -> 457188.81 | I39: =I31 -> 388320.08
A40: Commission applies to annuity products only. Investment funds (AAIDX, ACRE III, Cash) carry no commission.
A42: Marketing allowance = equivalent of Axonic regular commission on annuity premiums. Verify OGA vs. Processor vs. Regional rate level per contract language.
A44: =IF('入力 Inputs'!$F$1="English","STEP 4 — ONGOING ANNUAL FUND CHARGES",IF('入力 Inputs'!$F$1="日本語","ステップ4 — 年間ファンド手数料","ステップ4 — 年間ファンド手数料 / STEP 4 — ONGOING ANNUAL FUND CHARGES")) -> STEP 4 — ONGOING ANNUAL FUND CHARGES
A45: =IF('入力 Inputs'!$F$1="English","Fee Recipient",IF('入力 Inputs'!$F$1="日本語","手数料受取者","手数料受取者 / Fee Recipient")) -> Fee Recipient | B45: Rate | D45: Est. Annual $ on Net
A46: =IF('入力 Inputs'!$F$1="English","Advantage (M&E)",IF('入力 Inputs'!$F$1="日本語","Advantage（M&E）","Advantage（M&E） / Advantage (M&E)")) -> Advantage (M&E) | B46: ='入力 Inputs'!B41 -> 0.0015 | D46: =B23*'入力 Inputs'!B41 -> 18103.5
A47: =IF('入力 Inputs'!$F$1="English","Stephen / Syndicated (Investment Advisor)",IF('入力 Inputs'!$F$1="日本語","Stephen / シンジケート（投資アドバイザー）","Stephen / シンジケート（投資アドバイザー） / Stephen / Syndicated (Investment Advisor)")) -> Stephen / Syndicated (Investment Advisor) | B47: ='入力 Inputs'!B42 -> 0.0015 | D47: =B23*'入力 Inputs'!B42 -> 18103.5
A48: =IF('入力 Inputs'!$F$1="English","Inspira (Custodian 0.05%)",IF('入力 Inputs'!$F$1="日本語","インスピラ（保管料0.05%）","インスピラ（保管料0.05%） / Inspira (Custodian 0.05%)")) -> Inspira (Custodian 0.05%) | B48: ='入力 Inputs'!B43 -> 0.0005 | D48: =B23*'入力 Inputs'!B43 -> 6034.5
A49: =IF('入力 Inputs'!$F$1="English","Money Manager",IF('入力 Inputs'!$F$1="日本語","マネーマネージャー","マネーマネージャー / Money Manager")) -> Money Manager | B49: ='入力 Inputs'!B44 -> 0 | D49: =B23*'入力 Inputs'!B44 -> 0
A50: =IF('入力 Inputs'!$F$1="English","Total Annual Fund Charge Rate",IF('入力 Inputs'!$F$1="日本語","年間ファンド手数料率合計","年間ファンド手数料率合計 / Total Annual Fund Charge Rate")) -> Total Annual Fund Charge Rate | B50: ='入力 Inputs'!B41+'入力 Inputs'!B42+'入力 Inputs'!B43+'入力 Inputs'!B44 -> 0.0035 | D50: =B23*('入力 Inputs'!B41+'入力 Inputs'!B42+'入力 Inputs'!B43+'入力 Inputs'!B44) -> 42241.5
A51: =IF('入力 Inputs'!$F$1="English","Est. Year 1 actual fees (incl. Q1)",IF('入力 Inputs'!$F$1="日本語","推定初年度実費（Q1含む）","推定初年度実費（Q1含む） / Est. Year 1 actual fees (incl. Q1)")) -> Est. Year 1 actual fees (incl. Q1) | D51: ='入力 Inputs'!B45 -> 26000 | E51: ← adjust when confirmed
A52: =IF('入力 Inputs'!$F$1="English","10-YEAR FUND CHARGE INCOME PROJECTION",IF('入力 Inputs'!$F$1="日本語","10年間ファンド手数料収入予測","10年間ファンド手数料収入予測 / 10-YEAR FUND CHARGE INCOME PROJECTION")) -> 10-YEAR FUND CHARGE INCOME PROJECTION
A53: =IF('入力 Inputs'!$F$1="English","Year",IF('入力 Inputs'!$F$1="日本語","年","年 / Year")) -> Year | B53: AUM (BOY) | C53: Growth Rate | D53: Advantage (M&E) | E53: RIA / Syndicated | F53: Inspira (Custodian) | G53: Money Manager | H53: Total Annual Fees | I53: Cumulative Fees
A54: 1 | B54: =B23 -> 12069000 | C54: ='入力 Inputs'!$B$51 -> 0.062525 | D54: =B54*'入力 Inputs'!$B$41 -> 18103.5 | E54: =B54*'入力 Inputs'!$B$42 -> 18103.5 | F54: =B54*'入力 Inputs'!$B$43 -> 6034.5 | G54: =B54*'入力 Inputs'!$B$44 -> 0 | H54: =D54+E54+F54+G54 -> 42241.5 | I54: =H54 -> 42241.5
A55: 2 | B55: =B54*(1+C54) -> 12823614 | C55: ='入力 Inputs'!$B$51 -> 0.062525 | D55: =B55*'入力 Inputs'!$B$41 -> 19235.421 | E55: =B55*'入力 Inputs'!$B$42 -> 19235.421 | F55: =B55*'入力 Inputs'!$B$43 -> 6411.8071 | G55: =B55*'入力 Inputs'!$B$44 -> 0 | H55: =D55+E55+F55+G55 -> 44882.65 | I55: =I54+H55 -> 87124.15
A56: 3 | B56: =B55*(1+C55) -> 13625411 | C56: ='入力 Inputs'!$B$51 -> 0.062525 | D56: =B56*'入力 Inputs'!$B$41 -> 20438.116 | E56: =B56*'入力 Inputs'!$B$42 -> 20438.116 | F56: =B56*'入力 Inputs'!$B$43 -> 6812.7054 | G56: =B56*'入力 Inputs'!$B$44 -> 0 | H56: =D56+E56+F56+G56 -> 47688.937 | I56: =I55+H56 -> 134813.09
A57: 4 | B57: =B56*(1+C56) -> 14477340 | C57: ='入力 Inputs'!$B$51 -> 0.062525 | D57: =B57*'入力 Inputs'!$B$41 -> 21716.009 | E57: =B57*'入力 Inputs'!$B$42 -> 21716.009 | F57: =B57*'入力 Inputs'!$B$43 -> 7238.6698 | G57: =B57*'入力 Inputs'!$B$44 -> 0 | H57: =D57+E57+F57+G57 -> 50670.688 | I57: =I56+H57 -> 185483.78
A58: 5 | B58: =B57*(1+C57) -> 15382535 | C58: ='入力 Inputs'!$B$51 -> 0.062525 | D58: =B58*'入力 Inputs'!$B$41 -> 23073.803 | E58: =B58*'入力 Inputs'!$B$42 -> 23073.803 | F58: =B58*'入力 Inputs'!$B$43 -> 7691.2676 | G58: =B58*'入力 Inputs'!$B$44 -> 0 | H58: =D58+E58+F58+G58 -> 53838.873 | I58: =I57+H58 -> 239322.65
A59: 6 | B59: =B58*(1+C58) -> 16344328 | C59: ='入力 Inputs'!$B$51 -> 0.062525 | D59: =B59*'入力 Inputs'!$B$41 -> 24516.492 | E59: =B59*'入力 Inputs'!$B$42 -> 24516.492 | F59: =B59*'入力 Inputs'!$B$43 -> 8172.1641 | G59: =B59*'入力 Inputs'!$B$44 -> 0 | H59: =D59+E59+F59+G59 -> 57205.149 | I59: =I58+H59 -> 296527.8
A60: 7 | B60: =B59*(1+C59) -> 17366257 | C60: ='入力 Inputs'!$B$51 -> 0.062525 | D60: =B60*'入力 Inputs'!$B$41 -> 26049.386 | E60: =B60*'入力 Inputs'!$B$42 -> 26049.386 | F60: =B60*'入力 Inputs'!$B$43 -> 8683.1286 | G60: =B60*'入力 Inputs'!$B$44 -> 0 | H60: =D60+E60+F60+G60 -> 60781.901 | I60: =I59+H60 -> 357309.7
A61: 8 | B61: =B60*(1+C60) -> 18452083 | C61: ='入力 Inputs'!$B$51 -> 0.062525 | D61: =B61*'入力 Inputs'!$B$41 -> 27678.124 | E61: =B61*'入力 Inputs'!$B$42 -> 27678.124 | F61: =B61*'入力 Inputs'!$B$43 -> 9226.0413 | G61: =B61*'入力 Inputs'!$B$44 -> 0 | H61: =D61+E61+F61+G61 -> 64582.289 | I61: =I60+H61 -> 421891.99
A62: 9 | B62: =B61*(1+C61) -> 19605799 | C62: ='入力 Inputs'!$B$51 -> 0.062525 | D62: =B62*'入力 Inputs'!$B$41 -> 29408.698 | E62: =B62*'入力 Inputs'!$B$42 -> 29408.698 | F62: =B62*'入力 Inputs'!$B$43 -> 9802.8995 | G62: =B62*'入力 Inputs'!$B$44 -> 0 | H62: =D62+E62+F62+G62 -> 68620.296 | I62: =I61+H62 -> 490512.28
A63: 10 | B63: =B62*(1+C62) -> 20831652 | C63: ='入力 Inputs'!$B$51 -> 0.062525 | D63: =B63*'入力 Inputs'!$B$41 -> 31247.477 | E63: =B63*'入力 Inputs'!$B$42 -> 31247.477 | F63: =B63*'入力 Inputs'!$B$43 -> 10415.826 | G63: =B63*'入力 Inputs'!$B$44 -> 0 | H63: =D63+E63+F63+G63 -> 72910.78 | I63: =I62+H63 -> 563423.06
A64: =IF('入力 Inputs'!$F$1="English","TOTAL 10-YEAR",IF('入力 Inputs'!$F$1="日本語","10年間合計","10年間合計 / TOTAL 10-YEAR")) -> TOTAL 10-YEAR | D64: =SUM(D54:D63) -> 241467.03 | E64: =SUM(E54:E63) -> 241467.03 | F64: =SUM(F54:F63) -> 80489.009 | G64: =SUM(G54:G63) -> 0 | H64: =SUM(H54:H63) -> 563423.06 | I64: =I63 -> 563423.06
A67: =IF('入力 Inputs'!$F$1="English","DEAL SUMMARY",IF('入力 Inputs'!$F$1="日本語","取引概要","取引概要 / DEAL SUMMARY")) -> DEAL SUMMARY
A68: =IF('入力 Inputs'!$F$1="English","Total Deposit",IF('入力 Inputs'!$F$1="日本語","預入総額","預入総額 / Total Deposit")) -> Total Deposit | B68: ='入力 Inputs'!B7 -> 13000000
A69: =IF('入力 Inputs'!$F$1="English","Less: Premium Load (7%)",IF('入力 Inputs'!$F$1="日本語","差引：プレミアムロード（7%）","差引：プレミアムロード（7%） / Less: Premium Load (7%)")) -> Less: Premium Load (7%) | B69: =-B8 -> -910000
A70: =IF('入力 Inputs'!$F$1="English","Less: Admin & Bank Fees",IF('入力 Inputs'!$F$1="日本語","差引：管理・銀行手数料","差引：管理・銀行手数料 / Less: Admin & Bank Fees")) -> Less: Admin & Bank Fees | B70: =-B21 -> -21000
A71: =IF('入力 Inputs'!$F$1="English","Net Wired to Inspira",IF('入力 Inputs'!$F$1="日本語","インスピラへの正味送金額","インスピラへの正味送金額 / Net Wired to Inspira")) -> Net Wired to Inspira | B71: =B23 -> 12069000
A73: =IF('入力 Inputs'!$F$1="English","Guaranteed Products (75%)",IF('入力 Inputs'!$F$1="日本語","保証商品（75%）","保証商品（75%） / Guaranteed Products (75%)")) -> Guaranteed Products (75%) | B73: =C31 -> 9051750
A74: =IF('入力 Inputs'!$F$1="English","Non-Guaranteed (25%)",IF('入力 Inputs'!$F$1="日本語","非保証商品（25%）","非保証商品（25%） / Non-Guaranteed (25%)")) -> Non-Guaranteed (25%) | B74: =C37 -> 3017250
A75: =IF('入力 Inputs'!$F$1="English","Gross Weighted Return",IF('入力 Inputs'!$F$1="日本語","加重グロスリターン","加重グロスリターン / Gross Weighted Return")) -> Gross Weighted Return | B75: =E39 -> 0.062525
A77: =IF('入力 Inputs'!$F$1="English","Marketing Allowance — OGA Rate",IF('入力 Inputs'!$F$1="日本語","マーケティング手当 — OGA率","マーケティング手当 — OGA率 / Marketing Allowance — OGA Rate")) -> Marketing Allowance — OGA Rate | B77: =F39 -> 481251.38
A78: =IF('入力 Inputs'!$F$1="English","Marketing Allowance — Processor Rate",IF('入力 Inputs'!$F$1="日本語","マーケティング手当 — プロセッサー率","マーケティング手当 — プロセッサー率 / Marketing Allowance — Processor Rate")) -> Marketing Allowance — Processor Rate | B78: =H31 -> 457188.81
A79: =IF('入力 Inputs'!$F$1="English","Marketing Allowance — Regional Rate",IF('入力 Inputs'!$F$1="日本語","マーケティング手当 — リージョナル率","マーケティング手当 — リージョナル率 / Marketing Allowance — Regional Rate")) -> Marketing Allowance — Regional Rate | B79: =I39 -> 388320.08
A81: =IF('入力 Inputs'!$F$1="English","Annual Fund Charge Rate (total)",IF('入力 Inputs'!$F$1="日本語","年間ファンド手数料率（合計）","年間ファンド手数料率（合計） / Annual Fund Charge Rate (total)")) -> Annual Fund Charge Rate (total) | B81: ='入力 Inputs'!B41+'入力 Inputs'!B42+'入力 Inputs'!B43+'入力 Inputs'!B44 -> 0.0035
A82: =IF('入力 Inputs'!$F$1="English","Est. Year 1 Fees",IF('入力 Inputs'!$F$1="日本語","推定初年度手数料","推定初年度手数料 / Est. Year 1 Fees")) -> Est. Year 1 Fees | B82: ='入力 Inputs'!B45 -> 26000
A83: =IF('入力 Inputs'!$F$1="English","5-Year Cumulative Fund Charges",IF('入力 Inputs'!$F$1="日本語","5年累積ファンド手数料","5年累積ファンド手数料 / 5-Year Cumulative Fund Charges")) -> 5-Year Cumulative Fund Charges | B83: =I58 -> 239322.65
A84: =IF('入力 Inputs'!$F$1="English","10-Year Cumulative Fund Charges",IF('入力 Inputs'!$F$1="日本語","10年累積ファンド手数料","10年累積ファンド手数料 / 10-Year Cumulative Fund Charges")) -> 10-Year Cumulative Fund Charges | B84: =I63 -> 563423.06

Sheet キャリア Carrier Illust.
A1: =IF('入力 Inputs'!$F$1="English","PPVA CARRIER ILLUSTRATION",IF('入力 Inputs'!$F$1="日本語","PPVAキャリアイラストレーション","PPVAキャリアイラストレーション / PPVA CARRIER ILLUSTRATION")) -> PPVA CARRIER ILLUSTRATION
A2: =IF('入力 Inputs'!$F$1="English","All values pull from Inputs. Fund value at 3 illustrated rates.",IF('入力 Inputs'!$F$1="日本語","全ての値は入力シートから取得。3つの例示率でファンド価値を表示","全ての値は入力シートから取得。3つの例示率でファンド価値を表示 / All values pull from Inputs. Fund value at 3 illustrated rates.")) -> All values pull from Inputs. Fund value at 3 illustrated rates.
A4: =IF('入力 Inputs'!$F$1="English","Year",IF('入力 Inputs'!$F$1="日本語","年","年 / Year")) -> Year | B4: =IF('入力 Inputs'!$F$1="English","Age",IF('入力 Inputs'!$F$1="日本語","年齢","年齢 / Age")) -> Age | C4: =IF('入力 Inputs'!$F$1="English","Net Deposit",IF('入力 Inputs'!$F$1="日本語","正味預入額","正味預入額 / Net Deposit")) -> Net Deposit | D4: =IF('入力 Inputs'!$F$1="English","Fund Value ("&TEXT('入力 Inputs'!B83,"0.0%")&")",IF('入力 Inputs'!$F$1="日本語","ファンド価値（"&TEXT('入力 Inputs'!B83,"0.0%")&"）","ファンド価値 / Fund Value ("&TEXT('入力 Inputs'!B83,"0.0%")&")")) -> Fund Value (6.3%) | E4: =IF('入力 Inputs'!$F$1="English","Surrender Value ("&TEXT('入力 Inputs'!B83,"0.0%")&")",IF('入力 Inputs'!$F$1="日本語","解約返戻金（"&TEXT('入力 Inputs'!B83,"0.0%")&"）","解約返戻金 / Surrender Value ("&TEXT('入力 Inputs'!B83,"0.0%")&")")) -> Surrender Value (6.3%) | F4: =IF('入力 Inputs'!$F$1="English","Death Benefit ("&TEXT('入力 Inputs'!B83,"0.0%")&")",IF('入力 Inputs'!$F$1="日本語","死亡保険金（"&TEXT('入力 Inputs'!B83,"0.0%")&"）","死亡保険金 / Death Benefit ("&TEXT('入力 Inputs'!B83,"0.0%")&")")) -> Death Benefit (6.3%) | G4: =IF('入力 Inputs'!$F$1="English","Fund Value ("&TEXT('入力 Inputs'!B84,"0.0%")&")",IF('入力 Inputs'!$F$1="日本語","ファンド価値（"&TEXT('入力 Inputs'!B84,"0.0%")&"）","ファンド価値 / Fund Value ("&TEXT('入力 Inputs'!B84,"0.0%")&")")) -> Fund Value (6.5%) | H4: =IF('入力 Inputs'!$F$1="English","Surrender Value ("&TEXT('入力 Inputs'!B84,"0.0%")&")",IF('入力 Inputs'!$F$1="日本語","解約返戻金（"&TEXT('入力 Inputs'!B84,"0.0%")&"）","解約返戻金 / Surrender Value ("&TEXT('入力 Inputs'!B84,"0.0%")&")")) -> Surrender Value (6.5%) | I4: =IF('入力 Inputs'!$F$1="English","Death Benefit ("&TEXT('入力 Inputs'!B84,"0.0%")&")",IF('入力 Inputs'!$F$1="日本語","死亡保険金（"&TEXT('入力 Inputs'!B84,"0.0%")&"）","死亡保険金 / Death Benefit ("&TEXT('入力 Inputs'!B84,"0.0%")&")")) -> Death Benefit (6.5%) | J4: =IF('入力 Inputs'!$F$1="English","Fund Value ("&TEXT('入力 Inputs'!B85,"0.0%")&")",IF('入力 Inputs'!$F$1="日本語","ファンド価値（"&TEXT('入力 Inputs'!B85,"0.0%")&"）","ファンド価値 / Fund Value ("&TEXT('入力 Inputs'!B85,"0.0%")&")")) -> Fund Value (7.0%) | K4: =IF('入力 Inputs'!$F$1="English","Surrender Value ("&TEXT('入力 Inputs'!B85,"0.0%")&")",IF('入力 Inputs'!$F$1="日本語","解約返戻金（"&TEXT('入力 Inputs'!B85,"0.0%")&"）","解約返戻金 / Surrender Value ("&TEXT('入力 Inputs'!B85,"0.0%")&")")) -> Surrender Value (7.0%) | L4: =IF('入力 Inputs'!$F$1="English","Death Benefit ("&TEXT('入力 Inputs'!B85,"0.0%")&")",IF('入力 Inputs'!$F$1="日本語","死亡保険金（"&TEXT('入力 Inputs'!B85,"0.0%")&"）","死亡保険金 / Death Benefit ("&TEXT('入力 Inputs'!B85,"0.0%")&")")) -> Death Benefit (7.0%) | M4: =IF('入力 Inputs'!$F$1="English","Fund Value JPY (Base)",IF('入力 Inputs'!$F$1="日本語","ファンド価値・円（基準）","ファンド価値・円（基準） / Fund Value JPY (Base)")) -> Fund Value JPY (Base) | N4: Year | O4: ="Base ("&TEXT('入力 Inputs'!B83,"0.0%")&")" -> Base (6.3%) | P4: ="Alt 1 ("&TEXT('入力 Inputs'!B84,"0.0%")&")" -> Alt 1 (6.5%) | Q4: ="Alt 2 ("&TEXT('入力 Inputs'!B85,"0.0%")&")" -> Alt 2 (7.0%)
A5: =IF(1<='入力 Inputs'!$B$86,1,"") -> 1 | B5: =IF(A5="","",'入力 Inputs'!$B$55+A5) -> 47 | C5: =IF(A5="","",'入力 Inputs'!B7) -> 13000000 | D5: =IF(A5="","",('入力 Inputs'!B87-'入力 Inputs'!B87*'入力 Inputs'!B41-'入力 Inputs'!B57)*(1+'入力 Inputs'!B83)) -> 12826532 | E5: {=IF(A5="","",IF(A5<=10,D5*(1-INDEX('入力 Inputs'!$B$71:$B$80,A5)),D5))} -> 641326.62 | F5: =IF(A5="","",D5) -> 12826532 | G5: =IF(A5="","",('入力 Inputs'!B87-'入力 Inputs'!B87*'入力 Inputs'!B41-'入力 Inputs'!B57)*(1+'入力 Inputs'!B84)) -> 12856410 | H5: {=IF(A5="","",IF(A5<=10,G5*(1-INDEX('入力 Inputs'!$B$71:$B$80,A5)),G5))} -> 642820.5 | I5: =IF(A5="","",G5) -> 12856410 | J5: =IF(A5="","",('入力 Inputs'!B87-'入力 Inputs'!B87*'入力 Inputs'!B41-'入力 Inputs'!B57)*(1+'入力 Inputs'!B85)) -> 12916769 | K5: {=IF(A5="","",IF(A5<=10,J5*(1-INDEX('入力 Inputs'!$B$71:$B$80,A5)),J5))} -> 645838.43 | L5: =IF(A5="","",J5) -> 12916769 | M5: =IF(A5="","",D5*'入力 Inputs'!$B$64) -> 2.0522452e+09 | N5: =A5 -> 1 | O5: =IF(A5="","",D5) -> 12826532 | P5: =IF(A5="","",G5) -> 12856410 | Q5: =IF(A5="","",J5) -> 12916769
A6: =IF(2<='入力 Inputs'!$B$86,2,"") -> 2 | B6: =IF(A6="","",'入力 Inputs'!$B$55+A6) -> 48 | C6: =IF(A6="","",0) -> 0 | D6: =IF(A6="","",(D5-D5*'入力 Inputs'!$B$41-'入力 Inputs'!$B$57*(1+'入力 Inputs'!$B$91)^(2-1))*(1+'入力 Inputs'!$B$83)) -> 13607939 | E6: {=IF(A6="","",IF(A6<=10,D6*(1-INDEX('入力 Inputs'!$B$71:$B$80,A6)),D6))} -> 1360793.9 | F6: =IF(A6="","",D6) -> 13607939 | G6: =IF(A6="","",(G5-G5*'入力 Inputs'!$B$41-'入力 Inputs'!$B$57*(1+'入力 Inputs'!$B$91)^(2-1))*(1+'入力 Inputs'!$B$84)) -> 13671408 | H6: {=IF(A6="","",IF(A6<=10,G6*(1-INDEX('入力 Inputs'!$B$71:$B$80,A6)),G6))} -> 1367140.8 | I6: =IF(A6="","",G6) -> 13671408 | J6: =IF(A6="","",(J5-J5*'入力 Inputs'!$B$41-'入力 Inputs'!$B$57*(1+'入力 Inputs'!$B$91)^(2-1))*(1+'入力 Inputs'!$B$85)) -> 13800080 | K6: {=IF(A6="","",IF(A6<=10,J6*(1-INDEX('入力 Inputs'!$B$71:$B$80,A6)),J6))} -> 1380008 | L6: =IF(A6="","",J6) -> 13800080 | M6: =IF(A6="","",D6*'入力 Inputs'!$B$64) -> 2.1772702e+09 | N6: =A6 -> 2 | O6: =IF(A6="","",D6) -> 13607939 | P6: =IF(A6="","",G6) -> 13671408 | Q6: =IF(A6="","",J6) -> 13800080
A7: =IF(3<='入力 Inputs'!$B$86,3,"") -> 3 | B7: =IF(A7="","",'入力 Inputs'!$B$55+A7) -> 49 | C7: =IF(A7="","",0) -> 0 | D7: =IF(A7="","",(D6-D6*'入力 Inputs'!$B$41-'入力 Inputs'!$B$57*(1+'入力 Inputs'!$B$91)^(3-1))*(1+'入力 Inputs'!$B$83)) -> 14436953 | E7: {=IF(A7="","",IF(A7<=10,D7*(1-INDEX('入力 Inputs'!$B$71:$B$80,A7)),D7))} -> 2887390.7 | F7: =IF(A7="","",D7) -> 14436953 | G7: =IF(A7="","",(G6-G6*'入力 Inputs'!$B$41-'入力 Inputs'!$B$57*(1+'入力 Inputs'!$B$91)^(3-1))*(1+'入力 Inputs'!$B$84)) -> 14538076 | H7: {=IF(A7="","",IF(A7<=10,G7*(1-INDEX('入力 Inputs'!$B$71:$B$80,A7)),G7))} -> 2907615.2 | I7: =IF(A7="","",G7) -> 14538076 | J7: =IF(A7="","",(J6-J6*'入力 Inputs'!$B$41-'入力 Inputs'!$B$57*(1+'入力 Inputs'!$B$91)^(3-1))*(1+'入力 Inputs'!$B$85)) -> 14743802 | K7: {=IF(A7="","",IF(A7<=10,J7*(1-INDEX('入力 Inputs'!$B$71:$B$80,A7)),J7))} -> 2948760.5 | L7: =IF(A7="","",J7) -> 14743802 | M7: =IF(A7="","",D7*'入力 Inputs'!$B$64) -> 2.3099125e+09 | N7: =A7 -> 3 | O7: =IF(A7="","",D7) -> 14436953 | P7: =IF(A7="","",G7) -> 14538076 | Q7: =IF(A7="","",J7) -> 14743802
A8: =IF(4<='入力 Inputs'!$B$86,4,"") -> 4 | B8: =IF(A8="","",'入力 Inputs'!$B$55+A8) -> 50 | C8: =IF(A8="","",0) -> 0 | D8: =IF(A8="","",(D7-D7*'入力 Inputs'!$B$41-'入力 Inputs'!$B$57*(1+'入力 Inputs'!$B$91)^(4-1))*(1+'入力 Inputs'!$B$83)) -> 15316477 | E8: {=IF(A8="","",IF(A8<=10,D8*(1-INDEX('入力 Inputs'!$B$71:$B$80,A8)),D8))} -> 4594943 | F8: =IF(A8="","",D8) -> 15316477 | G8: =IF(A8="","",(G7-G7*'入力 Inputs'!$B$41-'入力 Inputs'!$B$57*(1+'入力 Inputs'!$B$91)^(4-1))*(1+'入力 Inputs'!$B$84)) -> 15459688 | H8: {=IF(A8="","",IF(A8<=10,G8*(1-INDEX('入力 Inputs'!$B$71:$B$80,A8)),G8))} -> 4637906.5 | I8: =IF(A8="","",G8) -> 15459688 | J8: =IF(A8="","",(J7-J7*'入力 Inputs'!$B$41-'入力 Inputs'!$B$57*(1+'入力 Inputs'!$B$91)^(4-1))*(1+'入力 Inputs'!$B$85)) -> 15752066 | K8: {=IF(A8="","",IF(A8<=10,J8*(1-INDEX('入力 Inputs'!$B$71:$B$80,A8)),J8))} -> 4725619.8 | L8: =IF(A8="","",J8) -> 15752066 | M8: =IF(A8="","",D8*'入力 Inputs'!$B$64) -> 2.4506363e+09 | N8: =A8 -> 4 | O8: =IF(A8="","",D8) -> 15316477 | P8: =IF(A8="","",G8) -> 15459688 | Q8: =IF(A8="","",J8) -> 15752066
A9: =IF(5<='入力 Inputs'!$B$86,5,"") -> 5 | B9: =IF(A9="","",'入力 Inputs'!$B$55+A9) -> 51 | C9: =IF(A9="","",0) -> 0 | D9: =IF(A9="","",(D8-D8*'入力 Inputs'!$B$41-'入力 Inputs'!$B$57*(1+'入力 Inputs'!$B$91)^(5-1))*(1+'入力 Inputs'!$B$83)) -> 16249586 | E9: {=IF(A9="","",IF(A9<=10,D9*(1-INDEX('入力 Inputs'!$B$71:$B$80,A9)),D9))} -> 6499834.6 | F9: =IF(A9="","",D9) -> 16249586 | G9: =IF(A9="","",(G8-G8*'入力 Inputs'!$B$41-'入力 Inputs'!$B$57*(1+'入力 Inputs'!$B$91)^(5-1))*(1+'入力 Inputs'!$B$84)) -> 16439729 | H9: {=IF(A9="","",IF(A9<=10,G9*(1-INDEX('入力 Inputs'!$B$71:$B$80,A9)),G9))} -> 6575891.6 | I9: =IF(A9="","",G9) -> 16439729 | J9: =IF(A9="","",(J8-J8*'入力 Inputs'!$B$41-'入力 Inputs'!$B$57*(1+'入力 Inputs'!$B$91)^(5-1))*(1+'入力 Inputs'!$B$85)) -> 16829286 | K9: {=IF(A9="","",IF(A9<=10,J9*(1-INDEX('入力 Inputs'!$B$71:$B$80,A9)),J9))} -> 6731714.3 | L9: =IF(A9="","",J9) -> 16829286 | M9: =IF(A9="","",D9*'入力 Inputs'!$B$64) -> 2.5999338e+09 | N9: =A9 -> 5 | O9: =IF(A9="","",D9) -> 16249586 | P9: =IF(A9="","",G9) -> 16439729 | Q9: =IF(A9="","",J9) -> 16829286
A10: =IF(6<='入力 Inputs'!$B$86,6,"") -> 6 | B10: =IF(A10="","",'入力 Inputs'!$B$55+A10) -> 52 | C10: =IF(A10="","",0) -> 0 | D10: =IF(A10="","",(D9-D9*'入力 Inputs'!$B$41-'入力 Inputs'!$B$57*(1+'入力 Inputs'!$B$91)^(6-1))*(1+'入力 Inputs'!$B$83)) -> 17239547 | E10: {=IF(A10="","",IF(A10<=10,D10*(1-INDEX('入力 Inputs'!$B$71:$B$80,A10)),D10))} -> 17239547 | F10: =IF(A10="","",D10) -> 17239547 | G10: =IF(A10="","",(G9-G9*'入力 Inputs'!$B$41-'入力 Inputs'!$B$57*(1+'入力 Inputs'!$B$91)^(6-1))*(1+'入力 Inputs'!$B$84)) -> 17481903 | H10: {=IF(A10="","",IF(A10<=10,G10*(1-INDEX('入力 Inputs'!$B$71:$B$80,A10)),G10))} -> 17481903 | I10: =IF(A10="","",G10) -> 17481903 | J10: =IF(A10="","",(J9-J9*'入力 Inputs'!$B$41-'入力 Inputs'!$B$57*(1+'入力 Inputs'!$B$91)^(6-1))*(1+'入力 Inputs'!$B$85)) -> 17980178 | K10: {=IF(A10="","",IF(A10<=10,J10*(1-INDEX('入力 Inputs'!$B$71:$B$80,A10)),J10))} -> 17980178 | L10: =IF(A10="","",J10) -> 17980178 | M10: =IF(A10="","",D10*'入力 Inputs'!$B$64) -> 2.7583276e+09 | N10: =A10 -> 6 | O10: =IF(A10="","",D10) -> 17239547 | P10: =IF(A10="","",G10) -> 17481903 | Q10: =IF(A10="","",J10) -> 17980178
A11: =IF(7<='入力 Inputs'!$B$86,7,"") -> 7 | B11: =IF(A11="","",'入力 Inputs'!$B$55+A11) -> 53 | C11: =IF(A11="","",0) -> 0 | D11: =IF(A11="","",(D10-D10*'入力 Inputs'!$B$41-'入力 Inputs'!$B$57*(1+'入力 Inputs'!$B$91)^(7-1))*(1+'入力 Inputs'!$B$83)) -> 18289823 | E11: {=IF(A11="","",IF(A11<=10,D11*(1-INDEX('入力 Inputs'!$B$71:$B$80,A11)),D11))} -> 18289823 | F11: =IF(A11="","",D11) -> 18289823 | G11: =IF(A11="","",(G10-G10*'入力 Inputs'!$B$41-'入力 Inputs'!$B$57*(1+'入力 Inputs'!$B$91)^(7-1))*(1+'入力 Inputs'!$B$84)) -> 18590148 | H11: {=IF(A11="","",IF(A11<=10,G11*(1-INDEX('入力 Inputs'!$B$71:$B$80,A11)),G11))} -> 18590148 | I11: =IF(A11="","",G11) -> 18590148 | J11: =IF(A11="","",(J10-J10*'入力 Inputs'!$B$41-'入力 Inputs'!$B$57*(1+'入力 Inputs'!$B$91)^(7-1))*(1+'入力 Inputs'!$B$85)) -> 19209780 | K11: {=IF(A11="","",IF(A11<=10,J11*(1-INDEX('入力 Inputs'!$B$71:$B$80,A11)),J11))} -> 19209780 | L11: =IF(A11="","",J11) -> 19209780 | M11: =IF(A11="","",D11*'入力 Inputs'!$B$64) -> 2.9263718e+09 | N11: =A11 -> 7 | O11: =IF(A11="","",D11) -> 18289823 | P11: =IF(A11="","",G11) -> 18590148 | Q11: =IF(A11="","",J11) -> 19209780
A12: =IF(8<='入力 Inputs'!$B$86,8,"") -> 8 | B12: =IF(A12="","",'入力 Inputs'!$B$55+A12) -> 54 | C12: =IF(A12="","",0) -> 0 | D12: =IF(A12="","",(D11-D11*'入力 Inputs'!$B$41-'入力 Inputs'!$B$57*(1+'入力 Inputs'!$B$91)^(8-1))*(1+'入力 Inputs'!$B$83)) -> 19404090 | E12: {=IF(A12="","",IF(A12<=10,D12*(1-INDEX('入力 Inputs'!$B$71:$B$80,A12)),D12))} -> 19404090 | F12: =IF(A12="","",D12) -> 19404090 | G12: =IF(A12="","",(G11-G11*'入力 Inputs'!$B$41-'入力 Inputs'!$B$57*(1+'入力 Inputs'!$B$91)^(8-1))*(1+'入力 Inputs'!$B$84)) -> 19768655 | H12: {=IF(A12="","",IF(A12<=10,G12*(1-INDEX('入力 Inputs'!$B$71:$B$80,A12)),G12))} -> 19768655 | I12: =IF(A12="","",G12) -> 19768655 | J12: =IF(A12="","",(J11-J11*'入力 Inputs'!$B$41-'入力 Inputs'!$B$57*(1+'入力 Inputs'!$B$91)^(8-1))*(1+'入力 Inputs'!$B$85)) -> 20523477 | K12: {=IF(A12="","",IF(A12<=10,J12*(1-INDEX('入力 Inputs'!$B$71:$B$80,A12)),J12))} -> 20523477 | L12: =IF(A12="","",J12) -> 20523477 | M12: =IF(A12="","",D12*'入力 Inputs'!$B$64) -> 3.1046543e+09 | N12: =A12 -> 8 | O12: =IF(A12="","",D12) -> 19404090 | P12: =IF(A12="","",G12) -> 19768655 | Q12: =IF(A12="","",J12) -> 20523477
A13: =IF(9<='入力 Inputs'!$B$86,9,"") -> 9 | B13: =IF(A13="","",'入力 Inputs'!$B$55+A13) -> 55 | C13: =IF(A13="","",0) -> 0 | D13: =IF(A13="","",(D12-D12*'入力 Inputs'!$B$41-'入力 Inputs'!$B$57*(1+'入力 Inputs'!$B$91)^(9-1))*(1+'入力 Inputs'!$B$83)) -> 20586245 | E13: {=IF(A13="","",IF(A13<=10,D13*(1-INDEX('入力 Inputs'!$B$71:$B$80,A13)),D13))} -> 20586245 | F13: =IF(A13="","",D13) -> 20586245 | G13: =IF(A13="","",(G12-G12*'入力 Inputs'!$B$41-'入力 Inputs'!$B$57*(1+'入力 Inputs'!$B$91)^(9-1))*(1+'入力 Inputs'!$B$84)) -> 21021877 | H13: {=IF(A13="","",IF(A13<=10,G13*(1-INDEX('入力 Inputs'!$B$71:$B$80,A13)),G13))} -> 21021877 | I13: =IF(A13="","",G13) -> 21021877 | J13: =IF(A13="","",(J12-J12*'入力 Inputs'!$B$41-'入力 Inputs'!$B$57*(1+'入力 Inputs'!$B$91)^(9-1))*(1+'入力 Inputs'!$B$85)) -> 21927020 | K13: {=IF(A13="","",IF(A13<=10,J13*(1-INDEX('入力 Inputs'!$B$71:$B$80,A13)),J13))} -> 21927020 | L13: =IF(A13="","",J13) -> 21927020 | M13: =IF(A13="","",D13*'入力 Inputs'!$B$64) -> 3.2937992e+09 | N13: =A13 -> 9 | O13: =IF(A13="","",D13) -> 20586245 | P13: =IF(A13="","",G13) -> 21021877 | Q13: =IF(A13="","",J13) -> 21927020
A14: =IF(10<='入力 Inputs'!$B$86,10,"") -> 10 | B14: =IF(A14="","",'入力 Inputs'!$B$55+A14) -> 56 | C14: =IF(A14="","",0) -> 0 | D14: =IF(A14="","",(D13-D13*'入力 Inputs'!$B$41-'入力 Inputs'!$B$57*(1+'入力 Inputs'!$B$91)^(10-1))*(1+'入力 Inputs'!$B$83)) -> 21840425 | E14: {=IF(A14="","",IF(A14<=10,D14*(1-INDEX('入力 Inputs'!$B$71:$B$80,A14)),D14))} -> 21840425 | F14: =IF(A14="","",D14) -> 21840425 | G14: =IF(A14="","",(G13-G13*'入力 Inputs'!$B$41-'入力 Inputs'!$B$57*(1+'入力 Inputs'!$B$91)^(10-1))*(1+'入力 Inputs'!$B$84)) -> 22354552 | H14: {=IF(A14="","",IF(A14<=10,G14*(1-INDEX('入力 Inputs'!$B$71:$B$80,A14)),G14))} -> 22354552 | I14: =IF(A14="","",G14) -> 22354552 | J14: =IF(A14="","",(J13-J13*'入力 Inputs'!$B$41-'入力 Inputs'!$B$57*(1+'入力 Inputs'!$B$91)^(10-1))*(1+'入力 Inputs'!$B$85)) -> 23426553 | K14: {=IF(A14="","",IF(A14<=10,J14*(1-INDEX('入力 Inputs'!$B$71:$B$80,A14)),J14))} -> 23426553 | L14: =IF(A14="","",J14) -> 23426553 | M14: =IF(A14="","",D14*'入力 Inputs'!$B$64) -> 3.494468e+09 | N14: =A14 -> 10 | O14: =IF(A14="","",D14) -> 21840425 | P14: =IF(A14="","",G14) -> 22354552 | Q14: =IF(A14="","",J14) -> 23426553
A15: =IF(11<='入力 Inputs'!$B$86,11,"") -> 11 | B15: =IF(A15="","",'入力 Inputs'!$B$55+A15) -> 57 | C15: =IF(A15="","",0) -> 0 | D15: =IF(A15="","",(D14-D14*'入力 Inputs'!$B$41-'入力 Inputs'!$B$57*(1+'入力 Inputs'!$B$91)^(11-1))*(1+'入力 Inputs'!$B$83)) -> 23171020 | E15: {=IF(A15="","",IF(A15<=10,D15*(1-INDEX('入力 Inputs'!$B$71:$B$80,A15)),D15))} -> 23171020 | F15: =IF(A15="","",D15) -> 23171020 | G15: =IF(A15="","",(G14-G14*'入力 Inputs'!$B$41-'入力 Inputs'!$B$57*(1+'入力 Inputs'!$B$91)^(11-1))*(1+'入力 Inputs'!$B$84)) -> 23771716 | H15: {=IF(A15="","",IF(A15<=10,G15*(1-INDEX('入力 Inputs'!$B$71:$B$80,A15)),G15))} -> 23771716 | I15: =IF(A15="","",G15) -> 23771716 | J15: =IF(A15="","",(J14-J14*'入力 Inputs'!$B$41-'入力 Inputs'!$B$57*(1+'入力 Inputs'!$B$91)^(11-1))*(1+'入力 Inputs'!$B$85)) -> 25028641 | K15: {=IF(A15="","",IF(A15<=10,J15*(1-INDEX('入力 Inputs'!$B$71:$B$80,A15)),J15))} -> 25028641 | L15: =IF(A15="","",J15) -> 25028641 | M15: =IF(A15="","",D15*'入力 Inputs'!$B$64) -> 3.7073631e+09 | N15: =A15 -> 11 | O15: =IF(A15="","",D15) -> 23171020 | P15: =IF(A15="","",G15) -> 23771716 | Q15: =IF(A15="","",J15) -> 25028641
A16: =IF(12<='入力 Inputs'!$B$86,12,"") -> 12 | B16: =IF(A16="","",'入力 Inputs'!$B$55+A16) -> 58 | C16: =IF(A16="","",0) -> 0 | D16: =IF(A16="","",(D15-D15*'入力 Inputs'!$B$41-'入力 Inputs'!$B$57*(1+'入力 Inputs'!$B$91)^(12-1))*(1+'入力 Inputs'!$B$83)) -> 24582683 | E16: {=IF(A16="","",IF(A16<=10,D16*(1-INDEX('入力 Inputs'!$B$71:$B$80,A16)),D16))} -> 24582683 | F16: =IF(A16="","",D16) -> 24582683 | G16: =IF(A16="","",(G15-G15*'入力 Inputs'!$B$41-'入力 Inputs'!$B$57*(1+'入力 Inputs'!$B$91)^(12-1))*(1+'入力 Inputs'!$B$84)) -> 25278728 | H16: {=IF(A16="","",IF(A16<=10,G16*(1-INDEX('入力 Inputs'!$B$71:$B$80,A16)),G16))} -> 25278728 | I16: =IF(A16="","",G16) -> 25278728 | J16: =IF(A16="","",(J15-J15*'入力 Inputs'!$B$41-'入力 Inputs'!$B$57*(1+'入力 Inputs'!$B$91)^(12-1))*(1+'入力 Inputs'!$B$85)) -> 26740300 | K16: {=IF(A16="","",IF(A16<=10,J16*(1-INDEX('入力 Inputs'!$B$71:$B$80,A16)),J16))} -> 26740300 | L16: =IF(A16="","",J16) -> 26740300 | M16: =IF(A16="","",D16*'入力 Inputs'!$B$64) -> 3.9332294e+09 | N16: =A16 -> 12 | O16: =IF(A16="","",D16) -> 24582683 | P16: =IF(A16="","",G16) -> 25278728 | Q16: =IF(A16="","",J16) -> 26740300
A17: =IF(13<='入力 Inputs'!$B$86,13,"") -> 13 | B17: =IF(A17="","",'入力 Inputs'!$B$55+A17) -> 59 | C17: =IF(A17="","",0) -> 0 | D17: =IF(A17="","",(D16-D16*'入力 Inputs'!$B$41-'入力 Inputs'!$B$57*(1+'入力 Inputs'!$B$91)^(13-1))*(1+'入力 Inputs'!$B$83)) -> 26080357 | E17: {=IF(A17="","",IF(A17<=10,D17*(1-INDEX('入力 Inputs'!$B$71:$B$80,A17)),D17))} -> 26080357 | F17: =IF(A17="","",D17) -> 26080357 | G17: =IF(A17="","",(G16-G16*'入力 Inputs'!$B$41-'入力 Inputs'!$B$57*(1+'入力 Inputs'!$B$91)^(13-1))*(1+'入力 Inputs'!$B$84)) -> 26881282 | H17: {=IF(A17="","",IF(A17<=10,G17*(1-INDEX('入力 Inputs'!$B$71:$B$80,A17)),G17))} -> 26881282 | I17: =IF(A17="","",G17) -> 26881282 | J17: =IF(A17="","",(J16-J16*'入力 Inputs'!$B$41-'入力 Inputs'!$B$57*(1+'入力 Inputs'!$B$91)^(13-1))*(1+'入力 Inputs'!$B$85)) -> 28569022 | K17: {=IF(A17="","",IF(A17<=10,J17*(1-INDEX('入力 Inputs'!$B$71:$B$80,A17)),J17))} -> 28569022 | L17: =IF(A17="","",J17) -> 28569022 | M17: =IF(A17="","",D17*'入力 Inputs'!$B$64) -> 4.1728571e+09 | N17: =A17 -> 13 | O17: =IF(A17="","",D17) -> 26080357 | P17: =IF(A17="","",G17) -> 26881282 | Q17: =IF(A17="","",J17) -> 28569022
A18: =IF(14<='入力 Inputs'!$B$86,14,"") -> 14 | B18: =IF(A18="","",'入力 Inputs'!$B$55+A18) -> 60 | C18: =IF(A18="","",0) -> 0 | D18: =IF(A18="","",(D17-D17*'入力 Inputs'!$B$41-'入力 Inputs'!$B$57*(1+'入力 Inputs'!$B$91)^(14-1))*(1+'入力 Inputs'!$B$83)) -> 27669279 | E18: {=IF(A18="","",IF(A18<=10,D18*(1-INDEX('入力 Inputs'!$B$71:$B$80,A18)),D18))} -> 27669279 | F18: =IF(A18="","",D18) -> 27669279 | G18: =IF(A18="","",(G17-G17*'入力 Inputs'!$B$41-'入力 Inputs'!$B$57*(1+'入力 Inputs'!$B$91)^(14-1))*(1+'入力 Inputs'!$B$84)) -> 28585437 | H18: {=IF(A18="","",IF(A18<=10,G18*(1-INDEX('入力 Inputs'!$B$71:$B$80,A18)),G18))} -> 28585437 | I18: =IF(A18="","",G18) -> 28585437 | J18: =IF(A18="","",(J17-J17*'入力 Inputs'!$B$41-'入力 Inputs'!$B$57*(1+'入力 Inputs'!$B$91)^(14-1))*(1+'入力 Inputs'!$B$85)) -> 30522814 | K18: {=IF(A18="","",IF(A18<=10,J18*(1-INDEX('入力 Inputs'!$B$71:$B$80,A18)),J18))} -> 30522814 | L18: =IF(A18="","",J18) -> 30522814 | M18: =IF(A18="","",D18*'入力 Inputs'!$B$64) -> 4.4270847e+09 | N18: =A18 -> 14 | O18: =IF(A18="","",D18) -> 27669279 | P18: =IF(A18="","",G18) -> 28585437 | Q18: =IF(A18="","",J18) -> 30522814
A19: =IF(15<='入力 Inputs'!$B$86,15,"") -> 15 | B19: =IF(A19="","",'入力 Inputs'!$B$55+A19) -> 61 | C19: =IF(A19="","",0) -> 0 | D19: =IF(A19="","",(D18-D18*'入力 Inputs'!$B$41-'入力 Inputs'!$B$57*(1+'入力 Inputs'!$B$91)^(15-1))*(1+'入力 Inputs'!$B$83)) -> 29355011 | E19: {=IF(A19="","",IF(A19<=10,D19*(1-INDEX('入力 Inputs'!$B$71:$B$80,A19)),D19))} -> 29355011 | F19: =IF(A19="","",D19) -> 29355011 | G19: =IF(A19="","",(G18-G18*'入力 Inputs'!$B$41-'入力 Inputs'!$B$57*(1+'入力 Inputs'!$B$91)^(15-1))*(1+'入力 Inputs'!$B$84)) -> 30397635 | H19: {=IF(A19="","",IF(A19<=10,G19*(1-INDEX('入力 Inputs'!$B$71:$B$80,A19)),G19))} -> 30397635 | I19: =IF(A19="","",G19) -> 30397635 | J19: =IF(A19="","",(J18-J18*'入力 Inputs'!$B$41-'入力 Inputs'!$B$57*(1+'入力 Inputs'!$B$91)^(15-1))*(1+'入力 Inputs'!$B$85)) -> 32610230 | K19: {=IF(A19="","",IF(A19<=10,J19*(1-INDEX('入力 Inputs'!$B$71:$B$80,A19)),J19))} -> 32610230 | L19: =IF(A19="","",J19) -> 32610230 | M19: =IF(A19="","",D19*'入力 Inputs'!$B$64) -> 4.6968018e+09 | N19: =A19 -> 15 | O19: =IF(A19="","",D19) -> 29355011 | P19: =IF(A19="","",G19) -> 30397635 | Q19: =IF(A19="","",J19) -> 32610230
A20: =IF(16<='入力 Inputs'!$B$86,16,"") -> 16 | B20: =IF(A20="","",'入力 Inputs'!$B$55+A20) -> 62 | C20: =IF(A20="","",0) -> 0 | D20: =IF(A20="","",(D19-D19*'入力 Inputs'!$B$41-'入力 Inputs'!$B$57*(1+'入力 Inputs'!$B$91)^(16-1))*(1+'入力 Inputs'!$B$83)) -> 31143452 | E20: {=IF(A20="","",IF(A20<=10,D20*(1-INDEX('入力 Inputs'!$B$71:$B$80,A20)),D20))} -> 31143452 | F20: =IF(A20="","",D20) -> 31143452 | G20: =IF(A20="","",(G19-G19*'入力 Inputs'!$B$41-'入力 Inputs'!$B$57*(1+'入力 Inputs'!$B$91)^(16-1))*(1+'入力 Inputs'!$B$84)) -> 32324724 | H20: {=IF(A20="","",IF(A20<=10,G20*(1-INDEX('入力 Inputs'!$B$71:$B$80,A20)),G20))} -> 32324724 | I20: =IF(A20="","",G20) -> 32324724 | J20: =IF(A20="","",(J19-J19*'入力 Inputs'!$B$41-'入力 Inputs'!$B$57*(1+'入力 Inputs'!$B$91)^(16-1))*(1+'入力 Inputs'!$B$85)) -> 34840409 | K20: {=IF(A20="","",IF(A20<=10,J20*(1-INDEX('入力 Inputs'!$B$71:$B$80,A20)),J20))} -> 34840409 | L20: =IF(A20="","",J20) -> 34840409 | M20: =IF(A20="","",D20*'入力 Inputs'!$B$64) -> 4.9829523e+09 | N20: =A20 -> 16 | O20: =IF(A20="","",D20) -> 31143452 | P20: =IF(A20="","",G20) -> 32324724 | Q20: =IF(A20="","",J20) -> 34840409
A21: =IF(17<='入力 Inputs'!$B$86,17,"") -> 17 | B21: =IF(A21="","",'入力 Inputs'!$B$55+A21) -> 63 | C21: =IF(A21="","",0) -> 0 | D21: =IF(A21="","",(D20-D20*'入力 Inputs'!$B$41-'入力 Inputs'!$B$57*(1+'入力 Inputs'!$B$91)^(17-1))*(1+'入力 Inputs'!$B$83)) -> 33040858 | E21: {=IF(A21="","",IF(A21<=10,D21*(1-INDEX('入力 Inputs'!$B$71:$B$80,A21)),D21))} -> 33040858 | F21: =IF(A21="","",D21) -> 33040858 | G21: =IF(A21="","",(G20-G20*'入力 Inputs'!$B$41-'入力 Inputs'!$B$57*(1+'入力 Inputs'!$B$91)^(17-1))*(1+'入力 Inputs'!$B$84)) -> 34373990 | H21: {=IF(A21="","",IF(A21<=10,G21*(1-INDEX('入力 Inputs'!$B$71:$B$80,A21)),G21))} -> 34373990 | I21: =IF(A21="","",G21) -> 34373990 | J21: =IF(A21="","",(J20-J20*'入力 Inputs'!$B$41-'入力 Inputs'!$B$57*(1+'入力 Inputs'!$B$91)^(17-1))*(1+'入力 Inputs'!$B$85)) -> 37223115 | K21: {=IF(A21="","",IF(A21<=10,J21*(1-INDEX('入力 Inputs'!$B$71:$B$80,A21)),J21))} -> 37223115 | L21: =IF(A21="","",J21) -> 37223115 | M21: =IF(A21="","",D21*'入力 Inputs'!$B$64) -> 5.2865372e+09 | N21: =A21 -> 17 | O21: =IF(A21="","",D21) -> 33040858 | P21: =IF(A21="","",G21) -> 34373990 | Q21: =IF(A21="","",J21) -> 37223115
A22: =IF(18<='入力 Inputs'!$B$86,18,"") -> 18 | B22: =IF(A22="","",'入力 Inputs'!$B$55+A22) -> 64 | C22: =IF(A22="","",0) -> 0 | D22: =IF(A22="","",(D21-D21*'入力 Inputs'!$B$41-'入力 Inputs'!$B$57*(1+'入力 Inputs'!$B$91)^(18-1))*(1+'入力 Inputs'!$B$83)) -> 35053869 | E22: {=IF(A22="","",IF(A22<=10,D22*(1-INDEX('入力 Inputs'!$B$71:$B$80,A22)),D22))} -> 35053869 | F22: =IF(A22="","",D22) -> 35053869 | G22: =IF(A22="","",(G21-G21*'入力 Inputs'!$B$41-'入力 Inputs'!$B$57*(1+'入力 Inputs'!$B$91)^(18-1))*(1+'入力 Inputs'!$B$84)) -> 36553178 | H22: {=IF(A22="","",IF(A22<=10,G22*(1-INDEX('入力 Inputs'!$B$71:$B$80,A22)),G22))} -> 36553178 | I22: =IF(A22="","",G22) -> 36553178 | J22: =IF(A22="","",(J21-J21*'入力 Inputs'!$B$41-'入力 Inputs'!$B$57*(1+'入力 Inputs'!$B$91)^(18-1))*(1+'入力 Inputs'!$B$85)) -> 39768780 | K22: {=IF(A22="","",IF(A22<=10,J22*(1-INDEX('入力 Inputs'!$B$71:$B$80,A22)),J22))} -> 39768780 | L22: =IF(A22="","",J22) -> 39768780 | M22: =IF(A22="","",D22*'入力 Inputs'!$B$64) -> 5.608619e+09 | N22: =A22 -> 18 | O22: =IF(A22="","",D22) -> 35053869 | P22: =IF(A22="","",G22) -> 36553178 | Q22: =IF(A22="","",J22) -> 39768780
A23: =IF(19<='入力 Inputs'!$B$86,19,"") -> 19 | B23: =IF(A23="","",'入力 Inputs'!$B$55+A23) -> 65 | C23: =IF(A23="","",0) -> 0 | D23: =IF(A23="","",(D22-D22*'入力 Inputs'!$B$41-'入力 Inputs'!$B$57*(1+'入力 Inputs'!$B$91)^(19-1))*(1+'入力 Inputs'!$B$83)) -> 37189529 | E23: {=IF(A23="","",IF(A23<=10,D23*(1-INDEX('入力 Inputs'!$B$71:$B$80,A23)),D23))} -> 37189529 | F23: =IF(A23="","",D23) -> 37189529 | G23: =IF(A23="","",(G22-G22*'入力 Inputs'!$B$41-'入力 Inputs'!$B$57*(1+'入力 Inputs'!$B$91)^(19-1))*(1+'入力 Inputs'!$B$84)) -> 38870526 | H23: {=IF(A23="","",IF(A23<=10,G23*(1-INDEX('入力 Inputs'!$B$71:$B$80,A23)),G23))} -> 38870526 | I23: =IF(A23="","",G23) -> 38870526 | J23: =IF(A23="","",(J22-J22*'入力 Inputs'!$B$41-'入力 Inputs'!$B$57*(1+'入力 Inputs'!$B$91)^(19-1))*(1+'入力 Inputs'!$B$85)) -> 42488550 | K23: {=IF(A23="","",IF(A23<=10,J23*(1-INDEX('入力 Inputs'!$B$71:$B$80,A23)),J23))} -> 42488550 | L23: =IF(A23="","",J23) -> 42488550 | M23: =IF(A23="","",D23*'入力 Inputs'!$B$64) -> 5.9503247e+09 | N23: =A23 -> 19 | O23: =IF(A23="","",D23) -> 37189529 | P23: =IF(A23="","",G23) -> 38870526 | Q23: =IF(A23="","",J23) -> 42488550
A24: =IF(20<='入力 Inputs'!$B$86,20,"") -> 20 | B24: =IF(A24="","",'入力 Inputs'!$B$55+A24) -> 66 | C24: =IF(A24="","",0) -> 0 | D24: =IF(A24="","",(D23-D23*'入力 Inputs'!$B$41-'入力 Inputs'!$B$57*(1+'入力 Inputs'!$B$91)^(20-1))*(1+'入力 Inputs'!$B$83)) -> 39455311 | E24: {=IF(A24="","",IF(A24<=10,D24*(1-INDEX('入力 Inputs'!$B$71:$B$80,A24)),D24))} -> 39455311 | F24: =IF(A24="","",D24) -> 39455311 | G24: =IF(A24="","",(G23-G23*'入力 Inputs'!$B$41-'入力 Inputs'!$B$57*(1+'入力 Inputs'!$B$91)^(20-1))*(1+'入力 Inputs'!$B$84)) -> 41334793 | H24: {=IF(A24="","",IF(A24<=10,G24*(1-INDEX('入力 Inputs'!$B$71:$B$80,A24)),G24))} -> 41334793 | I24: =IF(A24="","",G24) -> 41334793 | J24: =IF(A24="","",(J23-J23*'入力 Inputs'!$B$41-'入力 Inputs'!$B$57*(1+'入力 Inputs'!$B$91)^(20-1))*(1+'入力 Inputs'!$B$85)) -> 45394332 | K24: {=IF(A24="","",IF(A24<=10,J24*(1-INDEX('入力 Inputs'!$B$71:$B$80,A24)),J24))} -> 45394332 | L24: =IF(A24="","",J24) -> 45394332 | M24: =IF(A24="","",D24*'入力 Inputs'!$B$64) -> 6.3128498e+09 | N24: =A24 -> 20 | O24: =IF(A24="","",D24) -> 39455311 | P24: =IF(A24="","",G24) -> 41334793 | Q24: =IF(A24="","",J24) -> 45394332
A25: =IF(21<='入力 Inputs'!$B$86,21,"") -> 21 | B25: =IF(A25="","",'入力 Inputs'!$B$55+A25) -> 67 | C25: =IF(A25="","",0) -> 0 | D25: =IF(A25="","",(D24-D24*'入力 Inputs'!$B$41-'入力 Inputs'!$B$57*(1+'入力 Inputs'!$B$91)^(21-1))*(1+'入力 Inputs'!$B$83)) -> 41859144 | E25: {=IF(A25="","",IF(A25<=10,D25*(1-INDEX('入力 Inputs'!$B$71:$B$80,A25)),D25))} -> 41859144 | F25: =IF(A25="","",D25) -> 41859144 | G25: =IF(A25="","",(G24-G24*'入力 Inputs'!$B$41-'入力 Inputs'!$B$57*(1+'入力 Inputs'!$B$91)^(21-1))*(1+'入力 Inputs'!$B$84)) -> 43955294 | H25: {=IF(A25="","",IF(A25<=10,G25*(1-INDEX('入力 Inputs'!$B$71:$B$80,A25)),G25))} -> 43955294 | I25: =IF(A25="","",G25) -> 43955294 | J25: =IF(A25="","",(J24-J24*'入力 Inputs'!$B$41-'入力 Inputs'!$B$57*(1+'入力 Inputs'!$B$91)^(21-1))*(1+'入力 Inputs'!$B$85)) -> 48498848 | K25: {=IF(A25="","",IF(A25<=10,J25*(1-INDEX('入力 Inputs'!$B$71:$B$80,A25)),J25))} -> 48498848 | L25: =IF(A25="","",J25) -> 48498848 | M25: =IF(A25="","",D25*'入力 Inputs'!$B$64) -> 6.697463e+09 | N25: =A25 -> 21 | O25: =IF(A25="","",D25) -> 41859144 | P25: =IF(A25="","",G25) -> 43955294 | Q25: =IF(A25="","",J25) -> 48498848
A26: =IF(22<='入力 Inputs'!$B$86,22,"") -> 22 | B26: =IF(A26="","",'入力 Inputs'!$B$55+A26) -> 68 | C26: =IF(A26="","",0) -> 0 | D26: =IF(A26="","",(D25-D25*'入力 Inputs'!$B$41-'入力 Inputs'!$B$57*(1+'入力 Inputs'!$B$91)^(22-1))*(1+'入力 Inputs'!$B$83)) -> 44409438 | E26: {=IF(A26="","",IF(A26<=10,D26*(1-INDEX('入力 Inputs'!$B$71:$B$80,A26)),D26))} -> 44409438 | F26: =IF(A26="","",D26) -> 44409438 | G26: =IF(A26="","",(G25-G25*'入力 Inputs'!$B$41-'入力 Inputs'!$B$57*(1+'入力 Inputs'!$B$91)^(22-1))*(1+'入力 Inputs'!$B$84)) -> 46741934 | H26: {=IF(A26="","",IF(A26<=10,G26*(1-INDEX('入力 Inputs'!$B$71:$B$80,A26)),G26))} -> 46741934 | I26: =IF(A26="","",G26) -> 46741934 | J26: =IF(A26="","",(J25-J25*'入力 Inputs'!$B$41-'入力 Inputs'!$B$57*(1+'入力 Inputs'!$B$91)^(22-1))*(1+'入力 Inputs'!$B$85)) -> 51815690 | K26: {=IF(A26="","",IF(A26<=10,J26*(1-INDEX('入力 Inputs'!$B$71:$B$80,A26)),J26))} -> 51815690 | L26: =IF(A26="","",J26) -> 51815690 | M26: =IF(A26="","",D26*'入力 Inputs'!$B$64) -> 7.1055101e+09 | N26: =A26 -> 22 | O26: =IF(A26="","",D26) -> 44409438 | P26: =IF(A26="","",G26) -> 46741934 | Q26: =IF(A26="","",J26) -> 51815690
A27: =IF(23<='入力 Inputs'!$B$86,23,"") -> 23 | B27: =IF(A27="","",'入力 Inputs'!$B$55+A27) -> 69 | C27: =IF(A27="","",0) -> 0 | D27: =IF(A27="","",(D26-D26*'入力 Inputs'!$B$41-'入力 Inputs'!$B$57*(1+'入力 Inputs'!$B$91)^(23-1))*(1+'入力 Inputs'!$B$83)) -> 47115117 | E27: {=IF(A27="","",IF(A27<=10,D27*(1-INDEX('入力 Inputs'!$B$71:$B$80,A27)),D27))} -> 47115117 | F27: =IF(A27="","",D27) -> 47115117 | G27: =IF(A27="","",(G26-G26*'入力 Inputs'!$B$41-'入力 Inputs'!$B$57*(1+'入力 Inputs'!$B$91)^(23-1))*(1+'入力 Inputs'!$B$84)) -> 49705248 | H27: {=IF(A27="","",IF(A27<=10,G27*(1-INDEX('入力 Inputs'!$B$71:$B$80,A27)),G27))} -> 49705248 | I27: =IF(A27="","",G27) -> 49705248 | J27: =IF(A27="","",(J26-J26*'入力 Inputs'!$B$41-'入力 Inputs'!$B$57*(1+'入力 Inputs'!$B$91)^(23-1))*(1+'入力 Inputs'!$B$85)) -> 55359381 | K27: {=IF(A27="","",IF(A27<=10,J27*(1-INDEX('入力 Inputs'!$B$71:$B$80,A27)),J27))} -> 55359381 | L27: =IF(A27="","",J27) -> 55359381 | M27: =IF(A27="","",D27*'入力 Inputs'!$B$64) -> 7.5384188e+09 | N27: =A27 -> 23 | O27: =IF(A27="","",D27) -> 47115117 | P27: =IF(A27="","",G27) -> 49705248 | Q27: =IF(A27="","",J27) -> 55359381
A28: =IF(24<='入力 Inputs'!$B$86,24,"") -> 24 | B28: =IF(A28="","",'入力 Inputs'!$B$55+A28) -> 70 | C28: =IF(A28="","",0) -> 0 | D28: =IF(A28="","",(D27-D27*'入力 Inputs'!$B$41-'入力 Inputs'!$B$57*(1+'入力 Inputs'!$B$91)^(24-1))*(1+'入力 Inputs'!$B$83)) -> 49985650 | E28: {=IF(A28="","",IF(A28<=10,D28*(1-INDEX('入力 Inputs'!$B$71:$B$80,A28)),D28))} -> 49985650 | F28: =IF(A28="","",D28) -> 49985650 | G28: =IF(A28="","",(G27-G27*'入力 Inputs'!$B$41-'入力 Inputs'!$B$57*(1+'入力 Inputs'!$B$91)^(24-1))*(1+'入力 Inputs'!$B$84)) -> 52856436 | H28: {=IF(A28="","",IF(A28<=10,G28*(1-INDEX('入力 Inputs'!$B$71:$B$80,A28)),G28))} -> 52856436 | I28: =IF(A28="","",G28) -> 52856436 | J28: =IF(A28="","",(J27-J27*'入力 Inputs'!$B$41-'入力 Inputs'!$B$57*(1+'入力 Inputs'!$B$91)^(24-1))*(1+'入力 Inputs'!$B$85)) -> 59145436 | K28: {=IF(A28="","",IF(A28<=10,J28*(1-INDEX('入力 Inputs'!$B$71:$B$80,A28)),J28))} -> 59145436 | L28: =IF(A28="","",J28) -> 59145436 | M28: =IF(A28="","",D28*'入力 Inputs'!$B$64) -> 7.997704e+09 | N28: =A28 -> 24 | O28: =IF(A28="","",D28) -> 49985650 | P28: =IF(A28="","",G28) -> 52856436 | Q28: =IF(A28="","",J28) -> 59145436
A29: =IF(25<='入力 Inputs'!$B$86,25,"") -> 25 | B29: =IF(A29="","",'入力 Inputs'!$B$55+A29) -> 71 | C29: =IF(A29="","",0) -> 0 | D29: =IF(A29="","",(D28-D28*'入力 Inputs'!$B$41-'入力 Inputs'!$B$57*(1+'入力 Inputs'!$B$91)^(25-1))*(1+'入力 Inputs'!$B$83)) -> 53031080 | E29: {=IF(A29="","",IF(A29<=10,D29*(1-INDEX('入力 Inputs'!$B$71:$B$80,A29)),D29))} -> 53031080 | F29: =IF(A29="","",D29) -> 53031080 | G29: =IF(A29="","",(G28-G28*'入力 Inputs'!$B$41-'入力 Inputs'!$B$57*(1+'入力 Inputs'!$B$91)^(25-1))*(1+'入力 Inputs'!$B$84)) -> 56207409 | H29: {=IF(A29="","",IF(A29<=10,G29*(1-INDEX('入力 Inputs'!$B$71:$B$80,A29)),G29))} -> 56207409 | I29: =IF(A29="","",G29) -> 56207409 | J29: =IF(A29="","",(J28-J28*'入力 Inputs'!$B$41-'入力 Inputs'!$B$57*(1+'入力 Inputs'!$B$91)^(25-1))*(1+'入力 Inputs'!$B$85)) -> 63190430 | K29: {=IF(A29="","",IF(A29<=10,J29*(1-INDEX('入力 Inputs'!$B$71:$B$80,A29)),J29))} -> 63190430 | L29: =IF(A29="","",J29) -> 63190430 | M29: =IF(A29="","",D29*'入力 Inputs'!$B$64) -> 8.4849728e+09 | N29: =A29 -> 25 | O29: =IF(A29="","",D29) -> 53031080 | P29: =IF(A29="","",G29) -> 56207409 | Q29: =IF(A29="","",J29) -> 63190430
A30: =IF(26<='入力 Inputs'!$B$86,26,"") -> 26 | B30: =IF(A30="","",'入力 Inputs'!$B$55+A30) -> 72 | C30: =IF(A30="","",0) -> 0 | D30: =IF(A30="","",(D29-D29*'入力 Inputs'!$B$41-'入力 Inputs'!$B$57*(1+'入力 Inputs'!$B$91)^(26-1))*(1+'入力 Inputs'!$B$83)) -> 56262064 | E30: {=IF(A30="","",IF(A30<=10,D30*(1-INDEX('入力 Inputs'!$B$71:$B$80,A30)),D30))} -> 56262064 | F30: =IF(A30="","",D30) -> 56262064 | G30: =IF(A30="","",(G29-G29*'入力 Inputs'!$B$41-'入力 Inputs'!$B$57*(1+'入力 Inputs'!$B$91)^(26-1))*(1+'入力 Inputs'!$B$84)) -> 59770835 | H30: {=IF(A30="","",IF(A30<=10,G30*(1-INDEX('入力 Inputs'!$B$71:$B$80,A30)),G30))} -> 59770835 | I30: =IF(A30="","",G30) -> 59770835 | J30: =IF(A30="","",(J29-J29*'入力 Inputs'!$B$41-'入力 Inputs'!$B$57*(1+'入力 Inputs'!$B$91)^(26-1))*(1+'入力 Inputs'!$B$85)) -> 67512074 | K30: {=IF(A30="","",IF(A30<=10,J30*(1-INDEX('入力 Inputs'!$B$71:$B$80,A30)),J30))} -> 67512074 | L30: =IF(A30="","",J30) -> 67512074 | M30: =IF(A30="","",D30*'入力 Inputs'!$B$64) -> 9.0019303e+09 | N30: =A30 -> 26 | O30: =IF(A30="","",D30) -> 56262064 | P30: =IF(A30="","",G30) -> 59770835 | Q30: =IF(A30="","",J30) -> 67512074
A31: =IF(27<='入力 Inputs'!$B$86,27,"") -> 27 | B31: =IF(A31="","",'入力 Inputs'!$B$55+A31) -> 73 | C31: =IF(A31="","",0) -> 0 | D31: =IF(A31="","",(D30-D30*'入力 Inputs'!$B$41-'入力 Inputs'!$B$57*(1+'入力 Inputs'!$B$91)^(27-1))*(1+'入力 Inputs'!$B$83)) -> 59689909 | E31: {=IF(A31="","",IF(A31<=10,D31*(1-INDEX('入力 Inputs'!$B$71:$B$80,A31)),D31))} -> 59689909 | F31: =IF(A31="","",D31) -> 59689909 | G31: =IF(A31="","",(G30-G30*'入力 Inputs'!$B$41-'入力 Inputs'!$B$57*(1+'入力 Inputs'!$B$91)^(27-1))*(1+'入力 Inputs'!$B$84)) -> 63560183 | H31: {=IF(A31="","",IF(A31<=10,G31*(1-INDEX('入力 Inputs'!$B$71:$B$80,A31)),G31))} -> 63560183 | I31: =IF(A31="","",G31) -> 63560183 | J31: =IF(A31="","",(J30-J30*'入力 Inputs'!$B$41-'入力 Inputs'!$B$57*(1+'入力 Inputs'!$B$91)^(27-1))*(1+'入力 Inputs'!$B$85)) -> 72129289 | K31: {=IF(A31="","",IF(A31<=10,J31*(1-INDEX('入力 Inputs'!$B$71:$B$80,A31)),J31))} -> 72129289 | L31: =IF(A31="","",J31) -> 72129289 | M31: =IF(A31="","",D31*'入力 Inputs'!$B$64) -> 9.5503854e+09 | N31: =A31 -> 27 | O31: =IF(A31="","",D31) -> 59689909 | P31: =IF(A31="","",G31) -> 63560183 | Q31: =IF(A31="","",J31) -> 72129289
A32: =IF(28<='入力 Inputs'!$B$86,28,"") -> 28 | B32: =IF(A32="","",'入力 Inputs'!$B$55+A32) -> 74 | C32: =IF(A32="","",0) -> 0 | D32: =IF(A32="","",(D31-D31*'入力 Inputs'!$B$41-'入力 Inputs'!$B$57*(1+'入力 Inputs'!$B$91)^(28-1))*(1+'入力 Inputs'!$B$83)) -> 63326607 | E32: {=IF(A32="","",IF(A32<=10,D32*(1-INDEX('入力 Inputs'!$B$71:$B$80,A32)),D32))} -> 63326607 | F32: =IF(A32="","",D32) -> 63326607 | G32: =IF(A32="","",(G31-G31*'入力 Inputs'!$B$41-'入力 Inputs'!$B$57*(1+'入力 Inputs'!$B$91)^(28-1))*(1+'入力 Inputs'!$B$84)) -> 67589777 | H32: {=IF(A32="","",IF(A32<=10,G32*(1-INDEX('入力 Inputs'!$B$71:$B$80,A32)),G32))} -> 67589777 | I32: =IF(A32="","",G32) -> 67589777 | J32: =IF(A32="","",(J31-J31*'入力 Inputs'!$B$41-'入力 Inputs'!$B$57*(1+'入力 Inputs'!$B$91)^(28-1))*(1+'入力 Inputs'!$B$85)) -> 77062290 | K32: {=IF(A32="","",IF(A32<=10,J32*(1-INDEX('入力 Inputs'!$B$71:$B$80,A32)),J32))} -> 77062290 | L32: =IF(A32="","",J32) -> 77062290 | M32: =IF(A32="","",D32*'入力 Inputs'!$B$64) -> 1.0132257e+10 | N32: =A32 -> 28 | O32: =IF(A32="","",D32) -> 63326607 | P32: =IF(A32="","",G32) -> 67589777 | Q32: =IF(A32="","",J32) -> 77062290
A33: =IF(29<='入力 Inputs'!$B$86,29,"") -> 29 | B33: =IF(A33="","",'入力 Inputs'!$B$55+A33) -> 75 | C33: =IF(A33="","",0) -> 0 | D33: =IF(A33="","",(D32-D32*'入力 Inputs'!$B$41-'入力 Inputs'!$B$57*(1+'入力 Inputs'!$B$91)^(29-1))*(1+'入力 Inputs'!$B$83)) -> 67184886 | E33: {=IF(A33="","",IF(A33<=10,D33*(1-INDEX('入力 Inputs'!$B$71:$B$80,A33)),D33))} -> 67184886 | F33: =IF(A33="","",D33) -> 67184886 | G33: =IF(A33="","",(G32-G32*'入力 Inputs'!$B$41-'入力 Inputs'!$B$57*(1+'入力 Inputs'!$B$91)^(29-1))*(1+'入力 Inputs'!$B$84)) -> 71874849 | H33: {=IF(A33="","",IF(A33<=10,G33*(1-INDEX('入力 Inputs'!$B$71:$B$80,A33)),G33))} -> 71874849 | I33: =IF(A33="","",G33) -> 71874849 | J33: =IF(A33="","",(J32-J32*'入力 Inputs'!$B$41-'入力 Inputs'!$B$57*(1+'入力 Inputs'!$B$91)^(29-1))*(1+'入力 Inputs'!$B$85)) -> 82332675 | K33: {=IF(A33="","",IF(A33<=10,J33*(1-INDEX('入力 Inputs'!$B$71:$B$80,A33)),J33))} -> 82332675 | L33: =IF(A33="","",J33) -> 82332675 | M33: =IF(A33="","",D33*'入力 Inputs'!$B$64) -> 1.0749582e+10 | N33: =A33 -> 29 | O33: =IF(A33="","",D33) -> 67184886 | P33: =IF(A33="","",G33) -> 71874849 | Q33: =IF(A33="","",J33) -> 82332675
A34: =IF(30<='入力 Inputs'!$B$86,30,"") -> 30 | B34: =IF(A34="","",'入力 Inputs'!$B$55+A34) -> 76 | C34: =IF(A34="","",0) -> 0 | D34: =IF(A34="","",(D33-D33*'入力 Inputs'!$B$41-'入力 Inputs'!$B$57*(1+'入力 Inputs'!$B$91)^(30-1))*(1+'入力 Inputs'!$B$83)) -> 71278246 | E34: {=IF(A34="","",IF(A34<=10,D34*(1-INDEX('入力 Inputs'!$B$71:$B$80,A34)),D34))} -> 71278246 | F34: =IF(A34="","",D34) -> 71278246 | G34: =IF(A34="","",(G33-G33*'入力 Inputs'!$B$41-'入力 Inputs'!$B$57*(1+'入力 Inputs'!$B$91)^(30-1))*(1+'入力 Inputs'!$B$84)) -> 76431597 | H34: {=IF(A34="","",IF(A34<=10,G34*(1-INDEX('入力 Inputs'!$B$71:$B$80,A34)),G34))} -> 76431597 | I34: =IF(A34="","",G34) -> 76431597 | J34: =IF(A34="","",(J33-J33*'入力 Inputs'!$B$41-'入力 Inputs'!$B$57*(1+'入力 Inputs'!$B$91)^(30-1))*(1+'入力 Inputs'!$B$85)) -> 87963519 | K34: {=IF(A34="","",IF(A34<=10,J34*(1-INDEX('入力 Inputs'!$B$71:$B$80,A34)),J34))} -> 87963519 | L34: =IF(A34="","",J34) -> 87963519 | M34: =IF(A34="","",D34*'入力 Inputs'!$B$64) -> 1.1404519e+10 | N34: =A34 -> 30 | O34: =IF(A34="","",D34) -> 71278246 | P34: =IF(A34="","",G34) -> 76431597 | Q34: =IF(A34="","",J34) -> 87963519
A35: =IF(31<='入力 Inputs'!$B$86,31,"") -> 31 | B35: =IF(A35="","",'入力 Inputs'!$B$55+A35) -> 77 | C35: =IF(A35="","",0) -> 0 | D35: =IF(A35="","",(D34-D34*'入力 Inputs'!$B$41-'入力 Inputs'!$B$57*(1+'入力 Inputs'!$B$91)^(31-1))*(1+'入力 Inputs'!$B$83)) -> 75621010 | E35: {=IF(A35="","",IF(A35<=10,D35*(1-INDEX('入力 Inputs'!$B$71:$B$80,A35)),D35))} -> 75621010 | F35: =IF(A35="","",D35) -> 75621010 | G35: =IF(A35="","",(G34-G34*'入力 Inputs'!$B$41-'入力 Inputs'!$B$57*(1+'入力 Inputs'!$B$91)^(31-1))*(1+'入力 Inputs'!$B$84)) -> 81277244 | H35: {=IF(A35="","",IF(A35<=10,G35*(1-INDEX('入力 Inputs'!$B$71:$B$80,A35)),G35))} -> 81277244 | I35: =IF(A35="","",G35) -> 81277244 | J35: =IF(A35="","",(J34-J34*'入力 Inputs'!$B$41-'入力 Inputs'!$B$57*(1+'入力 Inputs'!$B$91)^(31-1))*(1+'入力 Inputs'!$B$85)) -> 93979476 | K35: {=IF(A35="","",IF(A35<=10,J35*(1-INDEX('入力 Inputs'!$B$71:$B$80,A35)),J35))} -> 93979476 | L35: =IF(A35="","",J35) -> 93979476 | M35: =IF(A35="","",D35*'入力 Inputs'!$B$64) -> 1.2099362e+10 | N35: =A35 -> 31 | O35: =IF(A35="","",D35) -> 75621010 | P35: =IF(A35="","",G35) -> 81277244 | Q35: =IF(A35="","",J35) -> 93979476
A36: =IF(32<='入力 Inputs'!$B$86,32,"") -> 32 | B36: =IF(A36="","",'入力 Inputs'!$B$55+A36) -> 78 | C36: =IF(A36="","",0) -> 0 | D36: =IF(A36="","",(D35-D35*'入力 Inputs'!$B$41-'入力 Inputs'!$B$57*(1+'入力 Inputs'!$B$91)^(32-1))*(1+'入力 Inputs'!$B$83)) -> 80228375 | E36: {=IF(A36="","",IF(A36<=10,D36*(1-INDEX('入力 Inputs'!$B$71:$B$80,A36)),D36))} -> 80228375 | F36: =IF(A36="","",D36) -> 80228375 | G36: =IF(A36="","",(G35-G35*'入力 Inputs'!$B$41-'入力 Inputs'!$B$57*(1+'入力 Inputs'!$B$91)^(32-1))*(1+'入力 Inputs'!$B$84)) -> 86430109 | H36: {=IF(A36="","",IF(A36<=10,G36*(1-INDEX('入力 Inputs'!$B$71:$B$80,A36)),G36))} -> 86430109 | I36: =IF(A36="","",G36) -> 86430109 | J36: =IF(A36="","",(J35-J35*'入力 Inputs'!$B$41-'入力 Inputs'!$B$57*(1+'入力 Inputs'!$B$91)^(32-1))*(1+'入力 Inputs'!$B$85)) -> 1.0040688e+08 | K36: {=IF(A36="","",IF(A36<=10,J36*(1-INDEX('入力 Inputs'!$B$71:$B$80,A36)),J36))} -> 1.0040688e+08 | L36: =IF(A36="","",J36) -> 1.0040688e+08 | M36: =IF(A36="","",D36*'入力 Inputs'!$B$64) -> 1.283654e+10 | N36: =A36 -> 32 | O36: =IF(A36="","",D36) -> 80228375 | P36: =IF(A36="","",G36) -> 86430109 | Q36: =IF(A36="","",J36) -> 1.0040688e+08
A37: =IF(33<='入力 Inputs'!$B$86,33,"") -> 33 | B37: =IF(A37="","",'入力 Inputs'!$B$55+A37) -> 79 | C37: =IF(A37="","",0) -> 0 | D37: =IF(A37="","",(D36-D36*'入力 Inputs'!$B$41-'入力 Inputs'!$B$57*(1+'入力 Inputs'!$B$91)^(33-1))*(1+'入力 Inputs'!$B$83)) -> 85116462 | E37: {=IF(A37="","",IF(A37<=10,D37*(1-INDEX('入力 Inputs'!$B$71:$B$80,A37)),D37))} -> 85116462 | F37: =IF(A37="","",D37) -> 85116462 | G37: =IF(A37="","",(G36-G36*'入力 Inputs'!$B$41-'入力 Inputs'!$B$57*(1+'入力 Inputs'!$B$91)^(33-1))*(1+'入力 Inputs'!$B$84)) -> 91909669 | H37: {=IF(A37="","",IF(A37<=10,G37*(1-INDEX('入力 Inputs'!$B$71:$B$80,A37)),G37))} -> 91909669 | I37: =IF(A37="","",G37) -> 91909669 | J37: =IF(A37="","",(J36-J36*'入力 Inputs'!$B$41-'入力 Inputs'!$B$57*(1+'入力 Inputs'!$B$91)^(33-1))*(1+'入力 Inputs'!$B$85)) -> 1.0727389e+08 | K37: {=IF(A37="","",IF(A37<=10,J37*(1-INDEX('入力 Inputs'!$B$71:$B$80,A37)),J37))} -> 1.0727389e+08 | L37: =IF(A37="","",J37) -> 1.0727389e+08 | M37: =IF(A37="","",D37*'入力 Inputs'!$B$64) -> 1.3618634e+10 | N37: =A37 -> 33 | O37: =IF(A37="","",D37) -> 85116462 | P37: =IF(A37="","",G37) -> 91909669 | Q37: =IF(A37="","",J37) -> 1.0727389e+08
A38: =IF(34<='入力 Inputs'!$B$86,34,"") -> 34 | B38: =IF(A38="","",'入力 Inputs'!$B$55+A38) -> 80 | C38: =IF(A38="","",0) -> 0 | D38: =IF(A38="","",(D37-D37*'入力 Inputs'!$B$41-'入力 Inputs'!$B$57*(1+'入力 Inputs'!$B$91)^(34-1))*(1+'入力 Inputs'!$B$83)) -> 90302377 | E38: {=IF(A38="","",IF(A38<=10,D38*(1-INDEX('入力 Inputs'!$B$71:$B$80,A38)),D38))} -> 90302377 | F38: =IF(A38="","",D38) -> 90302377 | G38: =IF(A38="","",(G37-G37*'入力 Inputs'!$B$41-'入力 Inputs'!$B$57*(1+'入力 Inputs'!$B$91)^(34-1))*(1+'入力 Inputs'!$B$84)) -> 97736637 | H38: {=IF(A38="","",IF(A38<=10,G38*(1-INDEX('入力 Inputs'!$B$71:$B$80,A38)),G38))} -> 97736637 | I38: =IF(A38="","",G38) -> 97736637 | J38: =IF(A38="","",(J37-J37*'入力 Inputs'!$B$41-'入力 Inputs'!$B$57*(1+'入力 Inputs'!$B$91)^(34-1))*(1+'入力 Inputs'!$B$85)) -> 1.1461055e+08 | K38: {=IF(A38="","",IF(A38<=10,J38*(1-INDEX('入力 Inputs'!$B$71:$B$80,A38)),J38))} -> 1.1461055e+08 | L38: =IF(A38="","",J38) -> 1.1461055e+08 | M38: =IF(A38="","",D38*'入力 Inputs'!$B$64) -> 1.444838e+10 | N38: =A38 -> 34 | O38: =IF(A38="","",D38) -> 90302377 | P38: =IF(A38="","",G38) -> 97736637 | Q38: =IF(A38="","",J38) -> 1.1461055e+08
A39: =IF(35<='入力 Inputs'!$B$86,35,"") -> 35 | B39: =IF(A39="","",'入力 Inputs'!$B$55+A39) -> 81 | C39: =IF(A39="","",0) -> 0 | D39: =IF(A39="","",(D38-D38*'入力 Inputs'!$B$41-'入力 Inputs'!$B$57*(1+'入力 Inputs'!$B$91)^(35-1))*(1+'入力 Inputs'!$B$83)) -> 95804267 | E39: {=IF(A39="","",IF(A39<=10,D39*(1-INDEX('入力 Inputs'!$B$71:$B$80,A39)),D39))} -> 95804267 | F39: =IF(A39="","",D39) -> 95804267 | G39: =IF(A39="","",(G38-G38*'入力 Inputs'!$B$41-'入力 Inputs'!$B$57*(1+'入力 Inputs'!$B$91)^(35-1))*(1+'入力 Inputs'!$B$84)) -> 1.0393304e+08 | H39: {=IF(A39="","",IF(A39<=10,G39*(1-INDEX('入力 Inputs'!$B$71:$B$80,A39)),G39))} -> 1.0393304e+08 | I39: =IF(A39="","",G39) -> 1.0393304e+08 | J39: =IF(A39="","",(J38-J38*'入力 Inputs'!$B$41-'入力 Inputs'!$B$57*(1+'入力 Inputs'!$B$91)^(35-1))*(1+'入力 Inputs'!$B$85)) -> 1.2244899e+08 | K39: {=IF(A39="","",IF(A39<=10,J39*(1-INDEX('入力 Inputs'!$B$71:$B$80,A39)),J39))} -> 1.2244899e+08 | L39: =IF(A39="","",J39) -> 1.2244899e+08 | M39: =IF(A39="","",D39*'入力 Inputs'!$B$64) -> 1.5328683e+10 | N39: =A39 -> 35 | O39: =IF(A39="","",D39) -> 95804267 | P39: =IF(A39="","",G39) -> 1.0393304e+08 | Q39: =IF(A39="","",J39) -> 1.2244899e+08
A40: =IF(36<='入力 Inputs'!$B$86,36,"") -> 36 | B40: =IF(A40="","",'入力 Inputs'!$B$55+A40) -> 82 | C40: =IF(A40="","",0) -> 0 | D40: =IF(A40="","",(D39-D39*'入力 Inputs'!$B$41-'入力 Inputs'!$B$57*(1+'入力 Inputs'!$B$91)^(36-1))*(1+'入力 Inputs'!$B$83)) -> 1.0164138e+08 | E40: {=IF(A40="","",IF(A40<=10,D40*(1-INDEX('入力 Inputs'!$B$71:$B$80,A40)),D40))} -> 1.0164138e+08 | F40: =IF(A40="","",D40) -> 1.0164138e+08 | G40: =IF(A40="","",(G39-G39*'入力 Inputs'!$B$41-'入力 Inputs'!$B$57*(1+'入力 Inputs'!$B$91)^(36-1))*(1+'入力 Inputs'!$B$84)) -> 1.105223e+08 | H40: {=IF(A40="","",IF(A40<=10,G40*(1-INDEX('入力 Inputs'!$B$71:$B$80,A40)),G40))} -> 1.105223e+08 | I40: =IF(A40="","",G40) -> 1.105223e+08 | J40: =IF(A40="","",(J39-J39*'入力 Inputs'!$B$41-'入力 Inputs'!$B$57*(1+'入力 Inputs'!$B$91)^(36-1))*(1+'入力 Inputs'!$B$85)) -> 1.3082353e+08 | K40: {=IF(A40="","",IF(A40<=10,J40*(1-INDEX('入力 Inputs'!$B$71:$B$80,A40)),J40))} -> 1.3082353e+08 | L40: =IF(A40="","",J40) -> 1.3082353e+08 | M40: =IF(A40="","",D40*'入力 Inputs'!$B$64) -> 1.6262621e+10 | N40: =A40 -> 36 | O40: =IF(A40="","",D40) -> 1.0164138e+08 | P40: =IF(A40="","",G40) -> 1.105223e+08 | Q40: =IF(A40="","",J40) -> 1.3082353e+08
A41: =IF(37<='入力 Inputs'!$B$86,37,"") -> 37 | B41: =IF(A41="","",'入力 Inputs'!$B$55+A41) -> 83 | C41: =IF(A41="","",0) -> 0 | D41: =IF(A41="","",(D40-D40*'入力 Inputs'!$B$41-'入力 Inputs'!$B$57*(1+'入力 Inputs'!$B$91)^(37-1))*(1+'入力 Inputs'!$B$83)) -> 1.0783415e+08 | E41: {=IF(A41="","",IF(A41<=10,D41*(1-INDEX('入力 Inputs'!$B$71:$B$80,A41)),D41))} -> 1.0783415e+08 | F41: =IF(A41="","",D41) -> 1.0783415e+08 | G41: =IF(A41="","",(G40-G40*'入力 Inputs'!$B$41-'入力 Inputs'!$B$57*(1+'入力 Inputs'!$B$91)^(37-1))*(1+'入力 Inputs'!$B$84)) -> 1.1752932e+08 | H41: {=IF(A41="","",IF(A41<=10,G41*(1-INDEX('入力 Inputs'!$B$71:$B$80,A41)),G41))} -> 1.1752932e+08 | I41: =IF(A41="","",G41) -> 1.1752932e+08 | J41: =IF(A41="","",(J40-J40*'入力 Inputs'!$B$41-'入力 Inputs'!$B$57*(1+'入力 Inputs'!$B$91)^(37-1))*(1+'入力 Inputs'!$B$85)) -> 1.3977084e+08 | K41: {=IF(A41="","",IF(A41<=10,J41*(1-INDEX('入力 Inputs'!$B$71:$B$80,A41)),J41))} -> 1.3977084e+08 | L41: =IF(A41="","",J41) -> 1.3977084e+08 | M41: =IF(A41="","",D41*'入力 Inputs'!$B$64) -> 1.7253464e+10 | N41: =A41 -> 37 | O41: =IF(A41="","",D41) -> 1.0783415e+08 | P41: =IF(A41="","",G41) -> 1.1752932e+08 | Q41: =IF(A41="","",J41) -> 1.3977084e+08
A42: =IF(38<='入力 Inputs'!$B$86,38,"") -> 38 | B42: =IF(A42="","",'入力 Inputs'!$B$55+A42) -> 84 | C42: =IF(A42="","",0) -> 0 | D42: =IF(A42="","",(D41-D41*'入力 Inputs'!$B$41-'入力 Inputs'!$B$57*(1+'入力 Inputs'!$B$91)^(38-1))*(1+'入力 Inputs'!$B$83)) -> 1.1440424e+08 | E42: {=IF(A42="","",IF(A42<=10,D42*(1-INDEX('入力 Inputs'!$B$71:$B$80,A42)),D42))} -> 1.1440424e+08 | F42: =IF(A42="","",D42) -> 1.1440424e+08 | G42: =IF(A42="","",(G41-G41*'入力 Inputs'!$B$41-'入力 Inputs'!$B$57*(1+'入力 Inputs'!$B$91)^(38-1))*(1+'入力 Inputs'!$B$84)) -> 1.249806e+08 | H42: {=IF(A42="","",IF(A42<=10,G42*(1-INDEX('入力 Inputs'!$B$71:$B$80,A42)),G42))} -> 1.249806e+08 | I42: =IF(A42="","",G42) -> 1.249806e+08 | J42: =IF(A42="","",(J41-J41*'入力 Inputs'!$B$41-'入力 Inputs'!$B$57*(1+'入力 Inputs'!$B$91)^(38-1))*(1+'入力 Inputs'!$B$85)) -> 1.4933009e+08 | K42: {=IF(A42="","",IF(A42<=10,J42*(1-INDEX('入力 Inputs'!$B$71:$B$80,A42)),J42))} -> 1.4933009e+08 | L42: =IF(A42="","",J42) -> 1.4933009e+08 | M42: =IF(A42="","",D42*'入力 Inputs'!$B$64) -> 1.8304678e+10 | N42: =A42 -> 38 | O42: =IF(A42="","",D42) -> 1.1440424e+08 | P42: =IF(A42="","",G42) -> 1.249806e+08 | Q42: =IF(A42="","",J42) -> 1.4933009e+08
A43: =IF(39<='入力 Inputs'!$B$86,39,"") -> 39 | B43: =IF(A43="","",'入力 Inputs'!$B$55+A43) -> 85 | C43: =IF(A43="","",0) -> 0 | D43: =IF(A43="","",(D42-D42*'入力 Inputs'!$B$41-'入力 Inputs'!$B$57*(1+'入力 Inputs'!$B$91)^(39-1))*(1+'入力 Inputs'!$B$83)) -> 1.2137464e+08 | E43: {=IF(A43="","",IF(A43<=10,D43*(1-INDEX('入力 Inputs'!$B$71:$B$80,A43)),D43))} -> 1.2137464e+08 | F43: =IF(A43="","",D43) -> 1.2137464e+08 | G43: =IF(A43="","",(G42-G42*'入力 Inputs'!$B$41-'入力 Inputs'!$B$57*(1+'入力 Inputs'!$B$91)^(39-1))*(1+'入力 Inputs'!$B$84)) -> 1.3290429e+08 | H43: {=IF(A43="","",IF(A43<=10,G43*(1-INDEX('入力 Inputs'!$B$71:$B$80,A43)),G43))} -> 1.3290429e+08 | I43: =IF(A43="","",G43) -> 1.3290429e+08 | J43: =IF(A43="","",(J42-J42*'入力 Inputs'!$B$41-'入力 Inputs'!$B$57*(1+'入力 Inputs'!$B$91)^(39-1))*(1+'入力 Inputs'!$B$85)) -> 1.5954313e+08 | K43: {=IF(A43="","",IF(A43<=10,J43*(1-INDEX('入力 Inputs'!$B$71:$B$80,A43)),J43))} -> 1.5954313e+08 | L43: =IF(A43="","",J43) -> 1.5954313e+08 | M43: =IF(A43="","",D43*'入力 Inputs'!$B$64) -> 1.9419943e+10 | N43: =A43 -> 39 | O43: =IF(A43="","",D43) -> 1.2137464e+08 | P43: =IF(A43="","",G43) -> 1.3290429e+08 | Q43: =IF(A43="","",J43) -> 1.5954313e+08
A44: =IF(40<='入力 Inputs'!$B$86,40,"") -> 40 | B44: =IF(A44="","",'入力 Inputs'!$B$55+A44) -> 86 | C44: =IF(A44="","",0) -> 0 | D44: =IF(A44="","",(D43-D43*'入力 Inputs'!$B$41-'入力 Inputs'!$B$57*(1+'入力 Inputs'!$B$91)^(40-1))*(1+'入力 Inputs'!$B$83)) -> 1.2876975e+08 | E44: {=IF(A44="","",IF(A44<=10,D44*(1-INDEX('入力 Inputs'!$B$71:$B$80,A44)),D44))} -> 1.2876975e+08 | F44: =IF(A44="","",D44) -> 1.2876975e+08 | G44: =IF(A44="","",(G43-G43*'入力 Inputs'!$B$41-'入力 Inputs'!$B$57*(1+'入力 Inputs'!$B$91)^(40-1))*(1+'入力 Inputs'!$B$84)) -> 1.4133036e+08 | H44: {=IF(A44="","",IF(A44<=10,G44*(1-INDEX('入力 Inputs'!$B$71:$B$80,A44)),G44))} -> 1.4133036e+08 | I44: =IF(A44="","",G44) -> 1.4133036e+08 | J44: =IF(A44="","",(J43-J43*'入力 Inputs'!$B$41-'入力 Inputs'!$B$57*(1+'入力 Inputs'!$B$91)^(40-1))*(1+'入力 Inputs'!$B$85)) -> 1.7045468e+08 | K44: {=IF(A44="","",IF(A44<=10,J44*(1-INDEX('入力 Inputs'!$B$71:$B$80,A44)),J44))} -> 1.7045468e+08 | L44: =IF(A44="","",J44) -> 1.7045468e+08 | M44: =IF(A44="","",D44*'入力 Inputs'!$B$64) -> 2.0603159e+10 | N44: =A44 -> 40 | O44: =IF(A44="","",D44) -> 1.2876975e+08 | P44: =IF(A44="","",G44) -> 1.4133036e+08 | Q44: =IF(A44="","",J44) -> 1.7045468e+08
A45: =IF(41<='入力 Inputs'!$B$86,41,"") -> 41 | B45: =IF(A45="","",'入力 Inputs'!$B$55+A45) -> 87 | C45: =IF(A45="","",0) -> 0 | D45: =IF(A45="","",(D44-D44*'入力 Inputs'!$B$41-'入力 Inputs'!$B$57*(1+'入力 Inputs'!$B$91)^(41-1))*(1+'入力 Inputs'!$B$83)) -> 1.3661543e+08 | E45: {=IF(A45="","",IF(A45<=10,D45*(1-INDEX('入力 Inputs'!$B$71:$B$80,A45)),D45))} -> 1.3661543e+08 | F45: =IF(A45="","",D45) -> 1.3661543e+08 | G45: =IF(A45="","",(G44-G44*'入力 Inputs'!$B$41-'入力 Inputs'!$B$57*(1+'入力 Inputs'!$B$91)^(41-1))*(1+'入力 Inputs'!$B$84)) -> 1.5029064e+08 | H45: {=IF(A45="","",IF(A45<=10,G45*(1-INDEX('入力 Inputs'!$B$71:$B$80,A45)),G45))} -> 1.5029064e+08 | I45: =IF(A45="","",G45) -> 1.5029064e+08 | J45: =IF(A45="","",(J44-J44*'入力 Inputs'!$B$41-'入力 Inputs'!$B$57*(1+'入力 Inputs'!$B$91)^(41-1))*(1+'入力 Inputs'!$B$85)) -> 1.8211251e+08 | K45: {=IF(A45="","",IF(A45<=10,J45*(1-INDEX('入力 Inputs'!$B$71:$B$80,A45)),J45))} -> 1.8211251e+08 | L45: =IF(A45="","",J45) -> 1.8211251e+08 | M45: =IF(A45="","",D45*'入力 Inputs'!$B$64) -> 2.1858469e+10 | N45: =A45 -> 41 | O45: =IF(A45="","",D45) -> 1.3661543e+08 | P45: =IF(A45="","",G45) -> 1.5029064e+08 | Q45: =IF(A45="","",J45) -> 1.8211251e+08
A46: =IF(42<='入力 Inputs'!$B$86,42,"") -> 42 | B46: =IF(A46="","",'入力 Inputs'!$B$55+A46) -> 88 | C46: =IF(A46="","",0) -> 0 | D46: =IF(A46="","",(D45-D45*'入力 Inputs'!$B$41-'入力 Inputs'!$B$57*(1+'入力 Inputs'!$B$91)^(42-1))*(1+'入力 Inputs'!$B$83)) -> 1.4493915e+08 | E46: {=IF(A46="","",IF(A46<=10,D46*(1-INDEX('入力 Inputs'!$B$71:$B$80,A46)),D46))} -> 1.4493915e+08 | F46: =IF(A46="","",D46) -> 1.4493915e+08 | G46: =IF(A46="","",(G45-G45*'入力 Inputs'!$B$41-'入力 Inputs'!$B$57*(1+'入力 Inputs'!$B$91)^(42-1))*(1+'入力 Inputs'!$B$84)) -> 1.5981902e+08 | H46: {=IF(A46="","",IF(A46<=10,G46*(1-INDEX('入力 Inputs'!$B$71:$B$80,A46)),G46))} -> 1.5981902e+08 | I46: =IF(A46="","",G46) -> 1.5981902e+08 | J46: =IF(A46="","",(J45-J45*'入力 Inputs'!$B$41-'入力 Inputs'!$B$57*(1+'入力 Inputs'!$B$91)^(42-1))*(1+'入力 Inputs'!$B$85)) -> 1.9456767e+08 | K46: {=IF(A46="","",IF(A46<=10,J46*(1-INDEX('入力 Inputs'!$B$71:$B$80,A46)),J46))} -> 1.9456767e+08 | L46: =IF(A46="","",J46) -> 1.9456767e+08 | M46: =IF(A46="","",D46*'入力 Inputs'!$B$64) -> 2.3190264e+10 | N46: =A46 -> 42 | O46: =IF(A46="","",D46) -> 1.4493915e+08 | P46: =IF(A46="","",G46) -> 1.5981902e+08 | Q46: =IF(A46="","",J46) -> 1.9456767e+08
A47: =IF(43<='入力 Inputs'!$B$86,43,"") -> 43 | B47: =IF(A47="","",'入力 Inputs'!$B$55+A47) -> 89 | C47: =IF(A47="","",0) -> 0 | D47: =IF(A47="","",(D46-D46*'入力 Inputs'!$B$41-'入力 Inputs'!$B$57*(1+'入力 Inputs'!$B$91)^(43-1))*(1+'入力 Inputs'!$B$83)) -> 1.5377003e+08 | E47: {=IF(A47="","",IF(A47<=10,D47*(1-INDEX('入力 Inputs'!$B$71:$B$80,A47)),D47))} -> 1.5377003e+08 | F47: =IF(A47="","",D47) -> 1.5377003e+08 | G47: =IF(A47="","",(G46-G46*'入力 Inputs'!$B$41-'入力 Inputs'!$B$57*(1+'入力 Inputs'!$B$91)^(43-1))*(1+'入力 Inputs'!$B$84)) -> 1.6995151e+08 | H47: {=IF(A47="","",IF(A47<=10,G47*(1-INDEX('入力 Inputs'!$B$71:$B$80,A47)),G47))} -> 1.6995151e+08 | I47: =IF(A47="","",G47) -> 1.6995151e+08 | J47: =IF(A47="","",(J46-J46*'入力 Inputs'!$B$41-'入力 Inputs'!$B$57*(1+'入力 Inputs'!$B$91)^(43-1))*(1+'入力 Inputs'!$B$85)) -> 2.0787469e+08 | K47: {=IF(A47="","",IF(A47<=10,J47*(1-INDEX('入力 Inputs'!$B$71:$B$80,A47)),J47))} -> 2.0787469e+08 | L47: =IF(A47="","",J47) -> 2.0787469e+08 | M47: =IF(A47="","",D47*'入力 Inputs'!$B$64) -> 2.4603206e+10 | N47: =A47 -> 43 | O47: =IF(A47="","",D47) -> 1.5377003e+08 | P47: =IF(A47="","",G47) -> 1.6995151e+08 | Q47: =IF(A47="","",J47) -> 2.0787469e+08
A48: =IF(44<='入力 Inputs'!$B$86,44,"") -> 44 | B48: =IF(A48="","",'入力 Inputs'!$B$55+A48) -> 90 | C48: =IF(A48="","",0) -> 0 | D48: =IF(A48="","",(D47-D47*'入力 Inputs'!$B$41-'入力 Inputs'!$B$57*(1+'入力 Inputs'!$B$91)^(44-1))*(1+'入力 Inputs'!$B$83)) -> 1.6313898e+08 | E48: {=IF(A48="","",IF(A48<=10,D48*(1-INDEX('入力 Inputs'!$B$71:$B$80,A48)),D48))} -> 1.6313898e+08 | F48: =IF(A48="","",D48) -> 1.6313898e+08 | G48: =IF(A48="","",(G47-G47*'入力 Inputs'!$B$41-'入力 Inputs'!$B$57*(1+'入力 Inputs'!$B$91)^(44-1))*(1+'入力 Inputs'!$B$84)) -> 1.8072641e+08 | H48: {=IF(A48="","",IF(A48<=10,G48*(1-INDEX('入力 Inputs'!$B$71:$B$80,A48)),G48))} -> 1.8072641e+08 | I48: =IF(A48="","",G48) -> 1.8072641e+08 | J48: =IF(A48="","",(J47-J47*'入力 Inputs'!$B$41-'入力 Inputs'!$B$57*(1+'入力 Inputs'!$B$91)^(44-1))*(1+'入力 Inputs'!$B$85)) -> 2.2209183e+08 | K48: {=IF(A48="","",IF(A48<=10,J48*(1-INDEX('入力 Inputs'!$B$71:$B$80,A48)),J48))} -> 2.2209183e+08 | L48: =IF(A48="","",J48) -> 2.2209183e+08 | M48: =IF(A48="","",D48*'入力 Inputs'!$B$64) -> 2.6102237e+10 | N48: =A48 -> 44 | O48: =IF(A48="","",D48) -> 1.6313898e+08 | P48: =IF(A48="","",G48) -> 1.8072641e+08 | Q48: =IF(A48="","",J48) -> 2.2209183e+08
A49: =IF(45<='入力 Inputs'!$B$86,45,"") -> 45 | B49: =IF(A49="","",'入力 Inputs'!$B$55+A49) -> 91 | C49: =IF(A49="","",0) -> 0 | D49: =IF(A49="","",(D48-D48*'入力 Inputs'!$B$41-'入力 Inputs'!$B$57*(1+'入力 Inputs'!$B$91)^(45-1))*(1+'入力 Inputs'!$B$83)) -> 1.7307877e+08 | E49: {=IF(A49="","",IF(A49<=10,D49*(1-INDEX('入力 Inputs'!$B$71:$B$80,A49)),D49))} -> 1.7307877e+08 | F49: =IF(A49="","",D49) -> 1.7307877e+08 | G49: =IF(A49="","",(G48-G48*'入力 Inputs'!$B$41-'入力 Inputs'!$B$57*(1+'入力 Inputs'!$B$91)^(45-1))*(1+'入力 Inputs'!$B$84)) -> 1.9218445e+08 | H49: {=IF(A49="","",IF(A49<=10,G49*(1-INDEX('入力 Inputs'!$B$71:$B$80,A49)),G49))} -> 1.9218445e+08 | I49: =IF(A49="","",G49) -> 1.9218445e+08 | J49: =IF(A49="","",(J48-J48*'入力 Inputs'!$B$41-'入力 Inputs'!$B$57*(1+'入力 Inputs'!$B$91)^(45-1))*(1+'入力 Inputs'!$B$85)) -> 2.3728133e+08 | K49: {=IF(A49="","",IF(A49<=10,J49*(1-INDEX('入力 Inputs'!$B$71:$B$80,A49)),J49))} -> 2.3728133e+08 | L49: =IF(A49="","",J49) -> 2.3728133e+08 | M49: =IF(A49="","",D49*'入力 Inputs'!$B$64) -> 2.7692604e+10 | N49: =A49 -> 45 | O49: =IF(A49="","",D49) -> 1.7307877e+08 | P49: =IF(A49="","",G49) -> 1.9218445e+08 | Q49: =IF(A49="","",J49) -> 2.3728133e+08
A50: =IF(46<='入力 Inputs'!$B$86,46,"") -> 46 | B50: =IF(A50="","",'入力 Inputs'!$B$55+A50) -> 92 | C50: =IF(A50="","",0) -> 0 | D50: =IF(A50="","",(D49-D49*'入力 Inputs'!$B$41-'入力 Inputs'!$B$57*(1+'入力 Inputs'!$B$91)^(46-1))*(1+'入力 Inputs'!$B$83)) -> 1.836242e+08 | E50: {=IF(A50="","",IF(A50<=10,D50*(1-INDEX('入力 Inputs'!$B$71:$B$80,A50)),D50))} -> 1.836242e+08 | F50: =IF(A50="","",D50) -> 1.836242e+08 | G50: =IF(A50="","",(G49-G49*'入力 Inputs'!$B$41-'入力 Inputs'!$B$57*(1+'入力 Inputs'!$B$91)^(46-1))*(1+'入力 Inputs'!$B$84)) -> 2.0436895e+08 | H50: {=IF(A50="","",IF(A50<=10,G50*(1-INDEX('入力 Inputs'!$B$71:$B$80,A50)),G50))} -> 2.0436895e+08 | I50: =IF(A50="","",G50) -> 2.0436895e+08 | J50: =IF(A50="","",(J49-J49*'入力 Inputs'!$B$41-'入力 Inputs'!$B$57*(1+'入力 Inputs'!$B$91)^(46-1))*(1+'入力 Inputs'!$B$85)) -> 2.5350971e+08 | K50: {=IF(A50="","",IF(A50<=10,J50*(1-INDEX('入力 Inputs'!$B$71:$B$80,A50)),J50))} -> 2.5350971e+08 | L50: =IF(A50="","",J50) -> 2.5350971e+08 | M50: =IF(A50="","",D50*'入力 Inputs'!$B$64) -> 2.9379871e+10 | N50: =A50 -> 46 | O50: =IF(A50="","",D50) -> 1.836242e+08 | P50: =IF(A50="","",G50) -> 2.0436895e+08 | Q50: =IF(A50="","",J50) -> 2.5350971e+08
A51: =IF(47<='入力 Inputs'!$B$86,47,"") -> 47 | B51: =IF(A51="","",'入力 Inputs'!$B$55+A51) -> 93 | C51: =IF(A51="","",0) -> 0 | D51: =IF(A51="","",(D50-D50*'入力 Inputs'!$B$41-'入力 Inputs'!$B$57*(1+'入力 Inputs'!$B$91)^(47-1))*(1+'入力 Inputs'!$B$83)) -> 1.9481215e+08 | E51: {=IF(A51="","",IF(A51<=10,D51*(1-INDEX('入力 Inputs'!$B$71:$B$80,A51)),D51))} -> 1.9481215e+08 | F51: =IF(A51="","",D51) -> 1.9481215e+08 | G51: =IF(A51="","",(G50-G50*'入力 Inputs'!$B$41-'入力 Inputs'!$B$57*(1+'入力 Inputs'!$B$91)^(47-1))*(1+'入力 Inputs'!$B$84)) -> 2.1732596e+08 | H51: {=IF(A51="","",IF(A51<=10,G51*(1-INDEX('入力 Inputs'!$B$71:$B$80,A51)),G51))} -> 2.1732596e+08 | I51: =IF(A51="","",G51) -> 2.1732596e+08 | J51: =IF(A51="","",(J50-J50*'入力 Inputs'!$B$41-'入力 Inputs'!$B$57*(1+'入力 Inputs'!$B$91)^(47-1))*(1+'入力 Inputs'!$B$85)) -> 2.7084801e+08 | K51: {=IF(A51="","",IF(A51<=10,J51*(1-INDEX('入力 Inputs'!$B$71:$B$80,A51)),J51))} -> 2.7084801e+08 | L51: =IF(A51="","",J51) -> 2.7084801e+08 | M51: =IF(A51="","",D51*'入力 Inputs'!$B$64) -> 3.1169944e+10 | N51: =A51 -> 47 | O51: =IF(A51="","",D51) -> 1.9481215e+08 | P51: =IF(A51="","",G51) -> 2.1732596e+08 | Q51: =IF(A51="","",J51) -> 2.7084801e+08
A52: =IF(48<='入力 Inputs'!$B$86,48,"") -> 48 | B52: =IF(A52="","",'入力 Inputs'!$B$55+A52) -> 94 | C52: =IF(A52="","",0) -> 0 | D52: =IF(A52="","",(D51-D51*'入力 Inputs'!$B$41-'入力 Inputs'!$B$57*(1+'入力 Inputs'!$B$91)^(48-1))*(1+'入力 Inputs'!$B$83)) -> 2.0668179e+08 | E52: {=IF(A52="","",IF(A52<=10,D52*(1-INDEX('入力 Inputs'!$B$71:$B$80,A52)),D52))} -> 2.0668179e+08 | F52: =IF(A52="","",D52) -> 2.0668179e+08 | G52: =IF(A52="","",(G51-G51*'入力 Inputs'!$B$41-'入力 Inputs'!$B$57*(1+'入力 Inputs'!$B$91)^(48-1))*(1+'入力 Inputs'!$B$84)) -> 2.3110446e+08 | H52: {=IF(A52="","",IF(A52<=10,G52*(1-INDEX('入力 Inputs'!$B$71:$B$80,A52)),G52))} -> 2.3110446e+08 | I52: =IF(A52="","",G52) -> 2.3110446e+08 | J52: =IF(A52="","",(J51-J51*'入力 Inputs'!$B$41-'入力 Inputs'!$B$57*(1+'入力 Inputs'!$B$91)^(48-1))*(1+'入力 Inputs'!$B$85)) -> 2.8937215e+08 | K52: {=IF(A52="","",IF(A52<=10,J52*(1-INDEX('入力 Inputs'!$B$71:$B$80,A52)),J52))} -> 2.8937215e+08 | L52: =IF(A52="","",J52) -> 2.8937215e+08 | M52: =IF(A52="","",D52*'入力 Inputs'!$B$64) -> 3.3069086e+10 | N52: =A52 -> 48 | O52: =IF(A52="","",D52) -> 2.0668179e+08 | P52: =IF(A52="","",G52) -> 2.3110446e+08 | Q52: =IF(A52="","",J52) -> 2.8937215e+08
A53: =IF(49<='入力 Inputs'!$B$86,49,"") -> 49 | B53: =IF(A53="","",'入力 Inputs'!$B$55+A53) -> 95 | C53: =IF(A53="","",0) -> 0 | D53: =IF(A53="","",(D52-D52*'入力 Inputs'!$B$41-'入力 Inputs'!$B$57*(1+'入力 Inputs'!$B$91)^(49-1))*(1+'入力 Inputs'!$B$83)) -> 2.1927464e+08 | E53: {=IF(A53="","",IF(A53<=10,D53*(1-INDEX('入力 Inputs'!$B$71:$B$80,A53)),D53))} -> 2.1927464e+08 | F53: =IF(A53="","",D53) -> 2.1927464e+08 | G53: =IF(A53="","",(G52-G52*'入力 Inputs'!$B$41-'入力 Inputs'!$B$57*(1+'入力 Inputs'!$B$91)^(49-1))*(1+'入力 Inputs'!$B$84)) -> 2.4575654e+08 | H53: {=IF(A53="","",IF(A53<=10,G53*(1-INDEX('入力 Inputs'!$B$71:$B$80,A53)),G53))} -> 2.4575654e+08 | I53: =IF(A53="","",G53) -> 2.4575654e+08 | J53: =IF(A53="","",(J52-J52*'入力 Inputs'!$B$41-'入力 Inputs'!$B$57*(1+'入力 Inputs'!$B$91)^(49-1))*(1+'入力 Inputs'!$B$85)) -> 3.0916323e+08 | K53: {=IF(A53="","",IF(A53<=10,J53*(1-INDEX('入力 Inputs'!$B$71:$B$80,A53)),J53))} -> 3.0916323e+08 | L53: =IF(A53="","",J53) -> 3.0916323e+08 | M53: =IF(A53="","",D53*'入力 Inputs'!$B$64) -> 3.5083942e+10 | N53: =A53 -> 49 | O53: =IF(A53="","",D53) -> 2.1927464e+08 | P53: =IF(A53="","",G53) -> 2.4575654e+08 | Q53: =IF(A53="","",J53) -> 3.0916323e+08
A54: =IF(50<='入力 Inputs'!$B$86,50,"") -> 50 | B54: =IF(A54="","",'入力 Inputs'!$B$55+A54) -> 96 | C54: =IF(A54="","",0) -> 0 | D54: =IF(A54="","",(D53-D53*'入力 Inputs'!$B$41-'入力 Inputs'!$B$57*(1+'入力 Inputs'!$B$91)^(50-1))*(1+'入力 Inputs'!$B$83)) -> 2.3263477e+08 | E54: {=IF(A54="","",IF(A54<=10,D54*(1-INDEX('入力 Inputs'!$B$71:$B$80,A54)),D54))} -> 2.3263477e+08 | F54: =IF(A54="","",D54) -> 2.3263477e+08 | G54: =IF(A54="","",(G53-G53*'入力 Inputs'!$B$41-'入力 Inputs'!$B$57*(1+'入力 Inputs'!$B$91)^(50-1))*(1+'入力 Inputs'!$B$84)) -> 2.6133758e+08 | H54: {=IF(A54="","",IF(A54<=10,G54*(1-INDEX('入力 Inputs'!$B$71:$B$80,A54)),G54))} -> 2.6133758e+08 | I54: =IF(A54="","",G54) -> 2.6133758e+08 | J54: =IF(A54="","",(J53-J53*'入力 Inputs'!$B$41-'入力 Inputs'!$B$57*(1+'入力 Inputs'!$B$91)^(50-1))*(1+'入力 Inputs'!$B$85)) -> 3.3030791e+08 | K54: {=IF(A54="","",IF(A54<=10,J54*(1-INDEX('入力 Inputs'!$B$71:$B$80,A54)),J54))} -> 3.3030791e+08 | L54: =IF(A54="","",J54) -> 3.3030791e+08 | M54: =IF(A54="","",D54*'入力 Inputs'!$B$64) -> 3.7221563e+10 | N54: =A54 -> 50 | O54: =IF(A54="","",D54) -> 2.3263477e+08 | P54: =IF(A54="","",G54) -> 2.6133758e+08 | Q54: =IF(A54="","",J54) -> 3.3030791e+08
A55: =IF(51<='入力 Inputs'!$B$86,51,"") -> 51 | B55: =IF(A55="","",'入力 Inputs'!$B$55+A55) -> 97 | C55: =IF(A55="","",0) -> 0 | D55: =IF(A55="","",(D54-D54*'入力 Inputs'!$B$41-'入力 Inputs'!$B$57*(1+'入力 Inputs'!$B$91)^(51-1))*(1+'入力 Inputs'!$B$83)) -> 2.4680894e+08 | E55: {=IF(A55="","",IF(A55<=10,D55*(1-INDEX('入力 Inputs'!$B$71:$B$80,A55)),D55))} -> 2.4680894e+08 | F55: =IF(A55="","",D55) -> 2.4680894e+08 | G55: =IF(A55="","",(G54-G54*'入力 Inputs'!$B$41-'入力 Inputs'!$B$57*(1+'入力 Inputs'!$B$91)^(51-1))*(1+'入力 Inputs'!$B$84)) -> 2.7790649e+08 | H55: {=IF(A55="","",IF(A55<=10,G55*(1-INDEX('入力 Inputs'!$B$71:$B$80,A55)),G55))} -> 2.7790649e+08 | I55: =IF(A55="","",G55) -> 2.7790649e+08 | J55: =IF(A55="","",(J54-J54*'入力 Inputs'!$B$41-'入力 Inputs'!$B$57*(1+'入力 Inputs'!$B$91)^(51-1))*(1+'入力 Inputs'!$B$85)) -> 3.5289877e+08 | K55: {=IF(A55="","",IF(A55<=10,J55*(1-INDEX('入力 Inputs'!$B$71:$B$80,A55)),J55))} -> 3.5289877e+08 | L55: =IF(A55="","",J55) -> 3.5289877e+08 | M55: =IF(A55="","",D55*'入力 Inputs'!$B$64) -> 3.948943e+10 | N55: =A55 -> 51 | O55: =IF(A55="","",D55) -> 2.4680894e+08 | P55: =IF(A55="","",G55) -> 2.7790649e+08 | Q55: =IF(A55="","",J55) -> 3.5289877e+08
A56: =IF(52<='入力 Inputs'!$B$86,52,"") -> 52 | B56: =IF(A56="","",'入力 Inputs'!$B$55+A56) -> 98 | C56: =IF(A56="","",0) -> 0 | D56: =IF(A56="","",(D55-D55*'入力 Inputs'!$B$41-'入力 Inputs'!$B$57*(1+'入力 Inputs'!$B$91)^(52-1))*(1+'入力 Inputs'!$B$83)) -> 2.6184674e+08 | E56: {=IF(A56="","",IF(A56<=10,D56*(1-INDEX('入力 Inputs'!$B$71:$B$80,A56)),D56))} -> 2.6184674e+08 | F56: =IF(A56="","",D56) -> 2.6184674e+08 | G56: =IF(A56="","",(G55-G55*'入力 Inputs'!$B$41-'入力 Inputs'!$B$57*(1+'入力 Inputs'!$B$91)^(52-1))*(1+'入力 Inputs'!$B$84)) -> 2.9552588e+08 | H56: {=IF(A56="","",IF(A56<=10,G56*(1-INDEX('入力 Inputs'!$B$71:$B$80,A56)),G56))} -> 2.9552588e+08 | I56: =IF(A56="","",G56) -> 2.9552588e+08 | J56: =IF(A56="","",(J55-J55*'入力 Inputs'!$B$41-'入力 Inputs'!$B$57*(1+'入力 Inputs'!$B$91)^(52-1))*(1+'入力 Inputs'!$B$85)) -> 3.7703471e+08 | K56: {=IF(A56="","",IF(A56<=10,J56*(1-INDEX('入力 Inputs'!$B$71:$B$80,A56)),J56))} -> 3.7703471e+08 | L56: =IF(A56="","",J56) -> 3.7703471e+08 | M56: =IF(A56="","",D56*'入力 Inputs'!$B$64) -> 4.1895478e+10 | N56: =A56 -> 52 | O56: =IF(A56="","",D56) -> 2.6184674e+08 | P56: =IF(A56="","",G56) -> 2.9552588e+08 | Q56: =IF(A56="","",J56) -> 3.7703471e+08
A57: =IF(53<='入力 Inputs'!$B$86,53,"") -> 53 | B57: =IF(A57="","",'入力 Inputs'!$B$55+A57) -> 99 | C57: =IF(A57="","",0) -> 0 | D57: =IF(A57="","",(D56-D56*'入力 Inputs'!$B$41-'入力 Inputs'!$B$57*(1+'入力 Inputs'!$B$91)^(53-1))*(1+'入力 Inputs'!$B$83)) -> 2.7780079e+08 | E57: {=IF(A57="","",IF(A57<=10,D57*(1-INDEX('入力 Inputs'!$B$71:$B$80,A57)),D57))} -> 2.7780079e+08 | F57: =IF(A57="","",D57) -> 2.7780079e+08 | G57: =IF(A57="","",(G56-G56*'入力 Inputs'!$B$41-'入力 Inputs'!$B$57*(1+'入力 Inputs'!$B$91)^(53-1))*(1+'入力 Inputs'!$B$84)) -> 3.1426237e+08 | H57: {=IF(A57="","",IF(A57<=10,G57*(1-INDEX('入力 Inputs'!$B$71:$B$80,A57)),G57))} -> 3.1426237e+08 | I57: =IF(A57="","",G57) -> 3.1426237e+08 | J57: =IF(A57="","",(J56-J56*'入力 Inputs'!$B$41-'入力 Inputs'!$B$57*(1+'入力 Inputs'!$B$91)^(53-1))*(1+'入力 Inputs'!$B$85)) -> 4.028214e+08 | K57: {=IF(A57="","",IF(A57<=10,J57*(1-INDEX('入力 Inputs'!$B$71:$B$80,A57)),J57))} -> 4.028214e+08 | L57: =IF(A57="","",J57) -> 4.028214e+08 | M57: =IF(A57="","",D57*'入力 Inputs'!$B$64) -> 4.4448126e+10 | N57: =A57 -> 53 | O57: =IF(A57="","",D57) -> 2.7780079e+08 | P57: =IF(A57="","",G57) -> 3.1426237e+08 | Q57: =IF(A57="","",J57) -> 4.028214e+08
A58: =IF(54<='入力 Inputs'!$B$86,54,"") -> 54 | B58: =IF(A58="","",'入力 Inputs'!$B$55+A58) -> 100 | C58: =IF(A58="","",0) -> 0 | D58: =IF(A58="","",(D57-D57*'入力 Inputs'!$B$41-'入力 Inputs'!$B$57*(1+'入力 Inputs'!$B$91)^(54-1))*(1+'入力 Inputs'!$B$83)) -> 2.9472692e+08 | E58: {=IF(A58="","",IF(A58<=10,D58*(1-INDEX('入力 Inputs'!$B$71:$B$80,A58)),D58))} -> 2.9472692e+08 | F58: =IF(A58="","",D58) -> 2.9472692e+08 | G58: =IF(A58="","",(G57-G57*'入力 Inputs'!$B$41-'入力 Inputs'!$B$57*(1+'入力 Inputs'!$B$91)^(54-1))*(1+'入力 Inputs'!$B$84)) -> 3.3418679e+08 | H58: {=IF(A58="","",IF(A58<=10,G58*(1-INDEX('入力 Inputs'!$B$71:$B$80,A58)),G58))} -> 3.3418679e+08 | I58: =IF(A58="","",G58) -> 3.3418679e+08 | J58: =IF(A58="","",(J57-J57*'入力 Inputs'!$B$41-'入力 Inputs'!$B$57*(1+'入力 Inputs'!$B$91)^(54-1))*(1+'入力 Inputs'!$B$85)) -> 4.3037177e+08 | K58: {=IF(A58="","",IF(A58<=10,J58*(1-INDEX('入力 Inputs'!$B$71:$B$80,A58)),J58))} -> 4.3037177e+08 | L58: =IF(A58="","",J58) -> 4.3037177e+08 | M58: =IF(A58="","",D58*'入力 Inputs'!$B$64) -> 4.7156308e+10 | N58: =A58 -> 54 | O58: =IF(A58="","",D58) -> 2.9472692e+08 | P58: =IF(A58="","",G58) -> 3.3418679e+08 | Q58: =IF(A58="","",J58) -> 4.3037177e+08
A59: =IF(55<='入力 Inputs'!$B$86,55,"") -> 55 | B59: =IF(A59="","",'入力 Inputs'!$B$55+A59) -> 101 | C59: =IF(A59="","",0) -> 0 | D59: =IF(A59="","",(D58-D58*'入力 Inputs'!$B$41-'入力 Inputs'!$B$57*(1+'入力 Inputs'!$B$91)^(55-1))*(1+'入力 Inputs'!$B$83)) -> 3.1268437e+08 | E59: {=IF(A59="","",IF(A59<=10,D59*(1-INDEX('入力 Inputs'!$B$71:$B$80,A59)),D59))} -> 3.1268437e+08 | F59: =IF(A59="","",D59) -> 3.1268437e+08 | G59: =IF(A59="","",(G58-G58*'入力 Inputs'!$B$41-'入力 Inputs'!$B$57*(1+'入力 Inputs'!$B$91)^(55-1))*(1+'入力 Inputs'!$B$84)) -> 3.5537444e+08 | H59: {=IF(A59="","",IF(A59<=10,G59*(1-INDEX('入力 Inputs'!$B$71:$B$80,A59)),G59))} -> 3.5537444e+08 | I59: =IF(A59="","",G59) -> 3.5537444e+08 | J59: =IF(A59="","",(J58-J58*'入力 Inputs'!$B$41-'入力 Inputs'!$B$57*(1+'入力 Inputs'!$B$91)^(55-1))*(1+'入力 Inputs'!$B$85)) -> 4.5980642e+08 | K59: {=IF(A59="","",IF(A59<=10,J59*(1-INDEX('入力 Inputs'!$B$71:$B$80,A59)),J59))} -> 4.5980642e+08 | L59: =IF(A59="","",J59) -> 4.5980642e+08 | M59: =IF(A59="","",D59*'入力 Inputs'!$B$64) -> 5.0029499e+10 | N59: =A59 -> 55 | O59: =IF(A59="","",D59) -> 3.1268437e+08 | P59: =IF(A59="","",G59) -> 3.5537444e+08 | Q59: =IF(A59="","",J59) -> 4.5980642e+08
A60: =IF(56<='入力 Inputs'!$B$86,56,"") -> 56 | B60: =IF(A60="","",'入力 Inputs'!$B$55+A60) -> 102 | C60: =IF(A60="","",0) -> 0 | D60: =IF(A60="","",(D59-D59*'入力 Inputs'!$B$41-'入力 Inputs'!$B$57*(1+'入力 Inputs'!$B$91)^(56-1))*(1+'入力 Inputs'!$B$83)) -> 3.3173597e+08 | E60: {=IF(A60="","",IF(A60<=10,D60*(1-INDEX('入力 Inputs'!$B$71:$B$80,A60)),D60))} -> 3.3173597e+08 | F60: =IF(A60="","",D60) -> 3.3173597e+08 | G60: =IF(A60="","",(G59-G59*'入力 Inputs'!$B$41-'入力 Inputs'!$B$57*(1+'入力 Inputs'!$B$91)^(56-1))*(1+'入力 Inputs'!$B$84)) -> 3.7790543e+08 | H60: {=IF(A60="","",IF(A60<=10,G60*(1-INDEX('入力 Inputs'!$B$71:$B$80,A60)),G60))} -> 3.7790543e+08 | I60: =IF(A60="","",G60) -> 3.7790543e+08 | J60: =IF(A60="","",(J59-J59*'入力 Inputs'!$B$41-'入力 Inputs'!$B$57*(1+'入力 Inputs'!$B$91)^(56-1))*(1+'入力 Inputs'!$B$85)) -> 4.9125423e+08 | K60: {=IF(A60="","",IF(A60<=10,J60*(1-INDEX('入力 Inputs'!$B$71:$B$80,A60)),J60))} -> 4.9125423e+08 | L60: =IF(A60="","",J60) -> 4.9125423e+08 | M60: =IF(A60="","",D60*'入力 Inputs'!$B$64) -> 5.3077755e+10 | N60: =A60 -> 56 | O60: =IF(A60="","",D60) -> 3.3173597e+08 | P60: =IF(A60="","",G60) -> 3.7790543e+08 | Q60: =IF(A60="","",J60) -> 4.9125423e+08
A61: =IF(57<='入力 Inputs'!$B$86,57,"") -> 57 | B61: =IF(A61="","",'入力 Inputs'!$B$55+A61) -> 103 | C61: =IF(A61="","",0) -> 0 | D61: =IF(A61="","",(D60-D60*'入力 Inputs'!$B$41-'入力 Inputs'!$B$57*(1+'入力 Inputs'!$B$91)^(57-1))*(1+'入力 Inputs'!$B$83)) -> 3.5194838e+08 | E61: {=IF(A61="","",IF(A61<=10,D61*(1-INDEX('入力 Inputs'!$B$71:$B$80,A61)),D61))} -> 3.5194838e+08 | F61: =IF(A61="","",D61) -> 3.5194838e+08 | G61: =IF(A61="","",(G60-G60*'入力 Inputs'!$B$41-'入力 Inputs'!$B$57*(1+'入力 Inputs'!$B$91)^(57-1))*(1+'入力 Inputs'!$B$84)) -> 4.0186492e+08 | H61: {=IF(A61="","",IF(A61<=10,G61*(1-INDEX('入力 Inputs'!$B$71:$B$80,A61)),G61))} -> 4.0186492e+08 | I61: =IF(A61="","",G61) -> 4.0186492e+08 | J61: =IF(A61="","",(J60-J60*'入力 Inputs'!$B$41-'入力 Inputs'!$B$57*(1+'入力 Inputs'!$B$91)^(57-1))*(1+'入力 Inputs'!$B$85)) -> 5.248529e+08 | K61: {=IF(A61="","",IF(A61<=10,J61*(1-INDEX('入力 Inputs'!$B$71:$B$80,A61)),J61))} -> 5.248529e+08 | L61: =IF(A61="","",J61) -> 5.248529e+08 | M61: =IF(A61="","",D61*'入力 Inputs'!$B$64) -> 5.6311741e+10 | N61: =A61 -> 57 | O61: =IF(A61="","",D61) -> 3.5194838e+08 | P61: =IF(A61="","",G61) -> 4.0186492e+08 | Q61: =IF(A61="","",J61) -> 5.248529e+08
A62: =IF(58<='入力 Inputs'!$B$86,58,"") -> 58 | B62: =IF(A62="","",'入力 Inputs'!$B$55+A62) -> 104 | C62: =IF(A62="","",0) -> 0 | D62: =IF(A62="","",(D61-D61*'入力 Inputs'!$B$41-'入力 Inputs'!$B$57*(1+'入力 Inputs'!$B$91)^(58-1))*(1+'入力 Inputs'!$B$83)) -> 3.7339235e+08 | E62: {=IF(A62="","",IF(A62<=10,D62*(1-INDEX('入力 Inputs'!$B$71:$B$80,A62)),D62))} -> 3.7339235e+08 | F62: =IF(A62="","",D62) -> 3.7339235e+08 | G62: =IF(A62="","",(G61-G61*'入力 Inputs'!$B$41-'入力 Inputs'!$B$57*(1+'入力 Inputs'!$B$91)^(58-1))*(1+'入力 Inputs'!$B$84)) -> 4.2734348e+08 | H62: {=IF(A62="","",IF(A62<=10,G62*(1-INDEX('入力 Inputs'!$B$71:$B$80,A62)),G62))} -> 4.2734348e+08 | I62: =IF(A62="","",G62) -> 4.2734348e+08 | J62: =IF(A62="","",(J61-J61*'入力 Inputs'!$B$41-'入力 Inputs'!$B$57*(1+'入力 Inputs'!$B$91)^(58-1))*(1+'入力 Inputs'!$B$85)) -> 5.6074953e+08 | K62: {=IF(A62="","",IF(A62<=10,J62*(1-INDEX('入力 Inputs'!$B$71:$B$80,A62)),J62))} -> 5.6074953e+08 | L62: =IF(A62="","",J62) -> 5.6074953e+08 | M62: =IF(A62="","",D62*'入力 Inputs'!$B$64) -> 5.9742775e+10 | N62: =A62 -> 58 | O62: =IF(A62="","",D62) -> 3.7339235e+08 | P62: =IF(A62="","",G62) -> 4.2734348e+08 | Q62: =IF(A62="","",J62) -> 5.6074953e+08
A63: =IF(59<='入力 Inputs'!$B$86,59,"") -> 59 | B63: =IF(A63="","",'入力 Inputs'!$B$55+A63) -> 105 | C63: =IF(A63="","",0) -> 0 | D63: =IF(A63="","",(D62-D62*'入力 Inputs'!$B$41-'入力 Inputs'!$B$57*(1+'入力 Inputs'!$B$91)^(59-1))*(1+'入力 Inputs'!$B$83)) -> 3.961429e+08 | E63: {=IF(A63="","",IF(A63<=10,D63*(1-INDEX('入力 Inputs'!$B$71:$B$80,A63)),D63))} -> 3.961429e+08 | F63: =IF(A63="","",D63) -> 3.961429e+08 | G63: =IF(A63="","",(G62-G62*'入力 Inputs'!$B$41-'入力 Inputs'!$B$57*(1+'入力 Inputs'!$B$91)^(59-1))*(1+'入力 Inputs'!$B$84)) -> 4.5443742e+08 | H63: {=IF(A63="","",IF(A63<=10,G63*(1-INDEX('入力 Inputs'!$B$71:$B$80,A63)),G63))} -> 4.5443742e+08 | I63: =IF(A63="","",G63) -> 4.5443742e+08 | J63: =IF(A63="","",(J62-J62*'入力 Inputs'!$B$41-'入力 Inputs'!$B$57*(1+'入力 Inputs'!$B$91)^(59-1))*(1+'入力 Inputs'!$B$85)) -> 5.9910129e+08 | K63: {=IF(A63="","",IF(A63<=10,J63*(1-INDEX('入力 Inputs'!$B$71:$B$80,A63)),J63))} -> 5.9910129e+08 | L63: =IF(A63="","",J63) -> 5.9910129e+08 | M63: =IF(A63="","",D63*'入力 Inputs'!$B$64) -> 6.3382863e+10 | N63: =A63 -> 59 | O63: =IF(A63="","",D63) -> 3.961429e+08 | P63: =IF(A63="","",G63) -> 4.5443742e+08 | Q63: =IF(A63="","",J63) -> 5.9910129e+08
A64: =IF(60<='入力 Inputs'!$B$86,60,"") -> 60 | B64: =IF(A64="","",'入力 Inputs'!$B$55+A64) -> 106 | C64: =IF(A64="","",0) -> 0 | D64: =IF(A64="","",(D63-D63*'入力 Inputs'!$B$41-'入力 Inputs'!$B$57*(1+'入力 Inputs'!$B$91)^(60-1))*(1+'入力 Inputs'!$B$83)) -> 4.2027964e+08 | E64: {=IF(A64="","",IF(A64<=10,D64*(1-INDEX('入力 Inputs'!$B$71:$B$80,A64)),D64))} -> 4.2027964e+08 | F64: =IF(A64="","",D64) -> 4.2027964e+08 | G64: =IF(A64="","",(G63-G63*'入力 Inputs'!$B$41-'入力 Inputs'!$B$57*(1+'入力 Inputs'!$B$91)^(60-1))*(1+'入力 Inputs'!$B$84)) -> 4.8324917e+08 | H64: {=IF(A64="","",IF(A64<=10,G64*(1-INDEX('入力 Inputs'!$B$71:$B$80,A64)),G64))} -> 4.8324917e+08 | I64: =IF(A64="","",G64) -> 4.8324917e+08 | J64: =IF(A64="","",(J63-J63*'入力 Inputs'!$B$41-'入力 Inputs'!$B$57*(1+'入力 Inputs'!$B$91)^(60-1))*(1+'入力 Inputs'!$B$85)) -> 6.400761e+08 | K64: {=IF(A64="","",IF(A64<=10,J64*(1-INDEX('入力 Inputs'!$B$71:$B$80,A64)),J64))} -> 6.400761e+08 | L64: =IF(A64="","",J64) -> 6.400761e+08 | M64: =IF(A64="","",D64*'入力 Inputs'!$B$64) -> 6.7244743e+10 | N64: =A64 -> 60 | O64: =IF(A64="","",D64) -> 4.2027964e+08 | P64: =IF(A64="","",G64) -> 4.8324917e+08 | Q64: =IF(A64="","",J64) -> 6.400761e+08
A65: =IF(61<='入力 Inputs'!$B$86,61,"") | B65: =IF(A65="","",'入力 Inputs'!$B$55+A65) | C65: =IF(A65="","",0) | D65: =IF(A65="","",(D64-D64*'入力 Inputs'!$B$41-'入力 Inputs'!$B$57*(1+'入力 Inputs'!$B$91)^(61-1))*(1+'入力 Inputs'!$B$83)) | E65: {=IF(A65="","",IF(A65<=10,D65*(1-INDEX('入力 Inputs'!$B$71:$B$80,A65)),D65))} | F65: =IF(A65="","",D65) | G65: =IF(A65="","",(G64-G64*'入力 Inputs'!$B$41-'入力 Inputs'!$B$57*(1+'入力 Inputs'!$B$91)^(61-1))*(1+'入力 Inputs'!$B$84)) | H65: {=IF(A65="","",IF(A65<=10,G65*(1-INDEX('入力 Inputs'!$B$71:$B$80,A65)),G65))} | I65: =IF(A65="","",G65) | J65: =IF(A65="","",(J64-J64*'入力 Inputs'!$B$41-'入力 Inputs'!$B$57*(1+'入力 Inputs'!$B$91)^(61-1))*(1+'入力 Inputs'!$B$85)) | K65: {=IF(A65="","",IF(A65<=10,J65*(1-INDEX('入力 Inputs'!$B$71:$B$80,A65)),J65))} | L65: =IF(A65="","",J65) | M65: =IF(A65="","",D65*'入力 Inputs'!$B$64) | N65: =A65 | O65: =IF(A65="","",D65) | P65: =IF(A65="","",G65) | Q65: =IF(A65="","",J65)
A66: =IF(62<='入力 Inputs'!$B$86,62,"") | B66: =IF(A66="","",'入力 Inputs'!$B$55+A66) | C66: =IF(A66="","",0) | D66: =IF(A66="","",(D65-D65*'入力 Inputs'!$B$41-'入力 Inputs'!$B$57*(1+'入力 Inputs'!$B$91)^(62-1))*(1+'入力 Inputs'!$B$83)) | E66: {=IF(A66="","",IF(A66<=10,D66*(1-INDEX('入力 Inputs'!$B$71:$B$80,A66)),D66))} | F66: =IF(A66="","",D66) | G66: =IF(A66="","",(G65-G65*'入力 Inputs'!$B$41-'入力 Inputs'!$B$57*(1+'入力 Inputs'!$B$91)^(62-1))*(1+'入力 Inputs'!$B$84)) | H66: {=IF(A66="","",IF(A66<=10,G66*(1-INDEX('入力 Inputs'!$B$71:$B$80,A66)),G66))} | I66: =IF(A66="","",G66) | J66: =IF(A66="","",(J65-J65*'入力 Inputs'!$B$41-'入力 Inputs'!$B$57*(1+'入力 Inputs'!$B$91)^(62-1))*(1+'入力 Inputs'!$B$85)) | K66: {=IF(A66="","",IF(A66<=10,J66*(1-INDEX('入力 Inputs'!$B$71:$B$80,A66)),J66))} | L66: =IF(A66="","",J66) | M66: =IF(A66="","",D66*'入力 Inputs'!$B$64) | N66: =A66 | O66: =IF(A66="","",D66) | P66: =IF(A66="","",G66) | Q66: =IF(A66="","",J66)
A67: =IF(63<='入力 Inputs'!$B$86,63,"") | B67: =IF(A67="","",'入力 Inputs'!$B$55+A67) | C67: =IF(A67="","",0) | D67: =IF(A67="","",(D66-D66*'入力 Inputs'!$B$41-'入力 Inputs'!$B$57*(1+'入力 Inputs'!$B$91)^(63-1))*(1+'入力 Inputs'!$B$83)) | E67: {=IF(A67="","",IF(A67<=10,D67*(1-INDEX('入力 Inputs'!$B$71:$B$80,A67)),D67))} | F67: =IF(A67="","",D67) | G67: =IF(A67="","",(G66-G66*'入力 Inputs'!$B$41-'入力 Inputs'!$B$57*(1+'入力 Inputs'!$B$91)^(63-1))*(1+'入力 Inputs'!$B$84)) | H67: {=IF(A67="","",IF(A67<=10,G67*(1-INDEX('入力 Inputs'!$B$71:$B$80,A67)),G67))} | I67: =IF(A67="","",G67) | J67: =IF(A67="","",(J66-J66*'入力 Inputs'!$B$41-'入力 Inputs'!$B$57*(1+'入力 Inputs'!$B$91)^(63-1))*(1+'入力 Inputs'!$B$85)) | K67: {=IF(A67="","",IF(A67<=10,J67*(1-INDEX('入力 Inputs'!$B$71:$B$80,A67)),J67))} | L67: =IF(A67="","",J67) | M67: =IF(A67="","",D67*'入力 Inputs'!$B$64) | N67: =A67 | O67: =IF(A67="","",D67) | P67: =IF(A67="","",G67) | Q67: =IF(A67="","",J67)
A68: =IF(64<='入力 Inputs'!$B$86,64,"") | B68: =IF(A68="","",'入力 Inputs'!$B$55+A68) | C68: =IF(A68="","",0) | D68: =IF(A68="","",(D67-D67*'入力 Inputs'!$B$41-'入力 Inputs'!$B$57*(1+'入力 Inputs'!$B$91)^(64-1))*(1+'入力 Inputs'!$B$83)) | E68: {=IF(A68="","",IF(A68<=10,D68*(1-INDEX('入力 Inputs'!$B$71:$B$80,A68)),D68))} | F68: =IF(A68="","",D68) | G68: =IF(A68="","",(G67-G67*'入力 Inputs'!$B$41-'入力 Inputs'!$B$57*(1+'入力 Inputs'!$B$91)^(64-1))*(1+'入力 Inputs'!$B$84)) | H68: {=IF(A68="","",IF(A68<=10,G68*(1-INDEX('入力 Inputs'!$B$71:$B$80,A68)),G68))} | I68: =IF(A68="","",G68) | J68: =IF(A68="","",(J67-J67*'入力 Inputs'!$B$41-'入力 Inputs'!$B$57*(1+'入力 Inputs'!$B$91)^(64-1))*(1+'入力 Inputs'!$B$85)) | K68: {=IF(A68="","",IF(A68<=10,J68*(1-INDEX('入力 Inputs'!$B$71:$B$80,A68)),J68))} | L68: =IF(A68="","",J68) | M68: =IF(A68="","",D68*'入力 Inputs'!$B$64) | N68: =A68 | O68: =IF(A68="","",D68) | P68: =IF(A68="","",G68) | Q68: =IF(A68="","",J68)
A69: =IF(65<='入力 Inputs'!$B$86,65,"") | B69: =IF(A69="","",'入力 Inputs'!$B$55+A69) | C69: =IF(A69="","",0) | D69: =IF(A69="","",(D68-D68*'入力 Inputs'!$B$41-'入力 Inputs'!$B$57*(1+'入力 Inputs'!$B$91)^(65-1))*(1+'入力 Inputs'!$B$83)) | E69: {=IF(A69="","",IF(A69<=10,D69*(1-INDEX('入力 Inputs'!$B$71:$B$80,A69)),D69))} | F69: =IF(A69="","",D69) | G69: =IF(A69="","",(G68-G68*'入力 Inputs'!$B$41-'入力 Inputs'!$B$57*(1+'入力 Inputs'!$B$91)^(65-1))*(1+'入力 Inputs'!$B$84)) | H69: {=IF(A69="","",IF(A69<=10,G69*(1-INDEX('入力 Inputs'!$B$71:$B$80,A69)),G69))} | I69: =IF(A69="","",G69) | J69: =IF(A69="","",(J68-J68*'入力 Inputs'!$B$41-'入力 Inputs'!$B$57*(1+'入力 Inputs'!$B$91)^(65-1))*(1+'入力 Inputs'!$B$85)) | K69: {=IF(A69="","",IF(A69<=10,J69*(1-INDEX('入力 Inputs'!$B$71:$B$80,A69)),J69))} | L69: =IF(A69="","",J69) | M69: =IF(A69="","",D69*'入力 Inputs'!$B$64) | N69: =A69 | O69: =IF(A69="","",D69) | P69: =IF(A69="","",G69) | Q69: =IF(A69="","",J69)
A70: =IF(66<='入力 Inputs'!$B$86,66,"") | B70: =IF(A70="","",'入力 Inputs'!$B$55+A70) | C70: =IF(A70="","",0) | D70: =IF(A70="","",(D69-D69*'入力 Inputs'!$B$41-'入力 Inputs'!$B$57*(1+'入力 Inputs'!$B$91)^(66-1))*(1+'入力 Inputs'!$B$83)) | E70: {=IF(A70="","",IF(A70<=10,D70*(1-INDEX('入力 Inputs'!$B$71:$B$80,A70)),D70))} | F70: =IF(A70="","",D70) | G70: =IF(A70="","",(G69-G69*'入力 Inputs'!$B$41-'入力 Inputs'!$B$57*(1+'入力 Inputs'!$B$91)^(66-1))*(1+'入力 Inputs'!$B$84)) | H70: {=IF(A70="","",IF(A70<=10,G70*(1-INDEX('入力 Inputs'!$B$71:$B$80,A70)),G70))} | I70: =IF(A70="","",G70) | J70: =IF(A70="","",(J69-J69*'入力 Inputs'!$B$41-'入力 Inputs'!$B$57*(1+'入力 Inputs'!$B$91)^(66-1))*(1+'入力 Inputs'!$B$85)) | K70: {=IF(A70="","",IF(A70<=10,J70*(1-INDEX('入力 Inputs'!$B$71:$B$80,A70)),J70))} | L70: =IF(A70="","",J70) | M70: =IF(A70="","",D70*'入力 Inputs'!$B$64) | N70: =A70 | O70: =IF(A70="","",D70) | P70: =IF(A70="","",G70) | Q70: =IF(A70="","",J70)
A71: =IF(67<='入力 Inputs'!$B$86,67,"") | B71: =IF(A71="","",'入力 Inputs'!$B$55+A71) | C71: =IF(A71="","",0) | D71: =IF(A71="","",(D70-D70*'入力 Inputs'!$B$41-'入力 Inputs'!$B$57*(1+'入力 Inputs'!$B$91)^(67-1))*(1+'入力 Inputs'!$B$83)) | E71: {=IF(A71="","",IF(A71<=10,D71*(1-INDEX('入力 Inputs'!$B$71:$B$80,A71)),D71))} | F71: =IF(A71="","",D71) | G71: =IF(A71="","",(G70-G70*'入力 Inputs'!$B$41-'入力 Inputs'!$B$57*(1+'入力 Inputs'!$B$91)^(67-1))*(1+'入力 Inputs'!$B$84)) | H71: {=IF(A71="","",IF(A71<=10,G71*(1-INDEX('入力 Inputs'!$B$71:$B$80,A71)),G71))} | I71: =IF(A71="","",G71) | J71: =IF(A71="","",(J70-J70*'入力 Inputs'!$B$41-'入力 Inputs'!$B$57*(1+'入力 Inputs'!$B$91)^(67-1))*(1+'入力 Inputs'!$B$85)) | K71: {=IF(A71="","",IF(A71<=10,J71*(1-INDEX('入力 Inputs'!$B$71:$B$80,A71)),J71))} | L71: =IF(A71="","",J71) | M71: =IF(A71="","",D71*'入力 Inputs'!$B$64) | N71: =A71 | O71: =IF(A71="","",D71) | P71: =IF(A71="","",G71) | Q71: =IF(A71="","",J71)
A72: =IF(68<='入力 Inputs'!$B$86,68,"") | B72: =IF(A72="","",'入力 Inputs'!$B$55+A72) | C72: =IF(A72="","",0) | D72: =IF(A72="","",(D71-D71*'入力 Inputs'!$B$41-'入力 Inputs'!$B$57*(1+'入力 Inputs'!$B$91)^(68-1))*(1+'入力 Inputs'!$B$83)) | E72: {=IF(A72="","",IF(A72<=10,D72*(1-INDEX('入力 Inputs'!$B$71:$B$80,A72)),D72))} | F72: =IF(A72="","",D72) | G72: =IF(A72="","",(G71-G71*'入力 Inputs'!$B$41-'入力 Inputs'!$B$57*(1+'入力 Inputs'!$B$91)^(68-1))*(1+'入力 Inputs'!$B$84)) | H72: {=IF(A72="","",IF(A72<=10,G72*(1-INDEX('入力 Inputs'!$B$71:$B$80,A72)),G72))} | I72: =IF(A72="","",G72) | J72: =IF(A72="","",(J71-J71*'入力 Inputs'!$B$41-'入力 Inputs'!$B$57*(1+'入力 Inputs'!$B$91)^(68-1))*(1+'入力 Inputs'!$B$85)) | K72: {=IF(A72="","",IF(A72<=10,J72*(1-INDEX('入力 Inputs'!$B$71:$B$80,A72)),J72))} | L72: =IF(A72="","",J72) | M72: =IF(A72="","",D72*'入力 Inputs'!$B$64) | N72: =A72 | O72: =IF(A72="","",D72) | P72: =IF(A72="","",G72) | Q72: =IF(A72="","",J72)
A73: =IF(69<='入力 Inputs'!$B$86,69,"") | B73: =IF(A73="","",'入力 Inputs'!$B$55+A73) | C73: =IF(A73="","",0) | D73: =IF(A73="","",(D72-D72*'入力 Inputs'!$B$41-'入力 Inputs'!$B$57*(1+'入力 Inputs'!$B$91)^(69-1))*(1+'入力 Inputs'!$B$83)) | E73: {=IF(A73="","",IF(A73<=10,D73*(1-INDEX('入力 Inputs'!$B$71:$B$80,A73)),D73))} | F73: =IF(A73="","",D73) | G73: =IF(A73="","",(G72-G72*'入力 Inputs'!$B$41-'入力 Inputs'!$B$57*(1+'入力 Inputs'!$B$91)^(69-1))*(1+'入力 Inputs'!$B$84)) | H73: {=IF(A73="","",IF(A73<=10,G73*(1-INDEX('入力 Inputs'!$B$71:$B$80,A73)),G73))} | I73: =IF(A73="","",G73) | J73: =IF(A73="","",(J72-J72*'入力 Inputs'!$B$41-'入力 Inputs'!$B$57*(1+'入力 Inputs'!$B$91)^(69-1))*(1+'入力 Inputs'!$B$85)) | K73: {=IF(A73="","",IF(A73<=10,J73*(1-INDEX('入力 Inputs'!$B$71:$B$80,A73)),J73))} | L73: =IF(A73="","",J73) | M73: =IF(A73="","",D73*'入力 Inputs'!$B$64) | N73: =A73 | O73: =IF(A73="","",D73) | P73: =IF(A73="","",G73) | Q73: =IF(A73="","",J73)
A74: =IF(70<='入力 Inputs'!$B$86,70,"") | B74: =IF(A74="","",'入力 Inputs'!$B$55+A74) | C74: =IF(A74="","",0) | D74: =IF(A74="","",(D73-D73*'入力 Inputs'!$B$41-'入力 Inputs'!$B$57*(1+'入力 Inputs'!$B$91)^(70-1))*(1+'入力 Inputs'!$B$83)) | E74: {=IF(A74="","",IF(A74<=10,D74*(1-INDEX('入力 Inputs'!$B$71:$B$80,A74)),D74))} | F74: =IF(A74="","",D74) | G74: =IF(A74="","",(G73-G73*'入力 Inputs'!$B$41-'入力 Inputs'!$B$57*(1+'入力 Inputs'!$B$91)^(70-1))*(1+'入力 Inputs'!$B$84)) | H74: {=IF(A74="","",IF(A74<=10,G74*(1-INDEX('入力 Inputs'!$B$71:$B$80,A74)),G74))} | I74: =IF(A74="","",G74) | J74: =IF(A74="","",(J73-J73*'入力 Inputs'!$B$41-'入力 Inputs'!$B$57*(1+'入力 Inputs'!$B$91)^(70-1))*(1+'入力 Inputs'!$B$85)) | K74: {=IF(A74="","",IF(A74<=10,J74*(1-INDEX('入力 Inputs'!$B$71:$B$80,A74)),J74))} | L74: =IF(A74="","",J74) | M74: =IF(A74="","",D74*'入力 Inputs'!$B$64) | N74: =A74 | O74: =IF(A74="","",D74) | P74: =IF(A74="","",G74) | Q74: =IF(A74="","",J74)
A75: =IF(71<='入力 Inputs'!$B$86,71,"") | B75: =IF(A75="","",'入力 Inputs'!$B$55+A75) | C75: =IF(A75="","",0) | D75: =IF(A75="","",(D74-D74*'入力 Inputs'!$B$41-'入力 Inputs'!$B$57*(1+'入力 Inputs'!$B$91)^(71-1))*(1+'入力 Inputs'!$B$83)) | E75: {=IF(A75="","",IF(A75<=10,D75*(1-INDEX('入力 Inputs'!$B$71:$B$80,A75)),D75))} | F75: =IF(A75="","",D75) | G75: =IF(A75="","",(G74-G74*'入力 Inputs'!$B$41-'入力 Inputs'!$B$57*(1+'入力 Inputs'!$B$91)^(71-1))*(1+'入力 Inputs'!$B$84)) | H75: {=IF(A75="","",IF(A75<=10,G75*(1-INDEX('入力 Inputs'!$B$71:$B$80,A75)),G75))} | I75: =IF(A75="","",G75) | J75: =IF(A75="","",(J74-J74*'入力 Inputs'!$B$41-'入力 Inputs'!$B$57*(1+'入力 Inputs'!$B$91)^(71-1))*(1+'入力 Inputs'!$B$85)) | K75: {=IF(A75="","",IF(A75<=10,J75*(1-INDEX('入力 Inputs'!$B$71:$B$80,A75)),J75))} | L75: =IF(A75="","",J75) | M75: =IF(A75="","",D75*'入力 Inputs'!$B$64) | N75: =A75 | O75: =IF(A75="","",D75) | P75: =IF(A75="","",G75) | Q75: =IF(A75="","",J75)
A76: =IF(72<='入力 Inputs'!$B$86,72,"") | B76: =IF(A76="","",'入力 Inputs'!$B$55+A76) | C76: =IF(A76="","",0) | D76: =IF(A76="","",(D75-D75*'入力 Inputs'!$B$41-'入力 Inputs'!$B$57*(1+'入力 Inputs'!$B$91)^(72-1))*(1+'入力 Inputs'!$B$83)) | E76: {=IF(A76="","",IF(A76<=10,D76*(1-INDEX('入力 Inputs'!$B$71:$B$80,A76)),D76))} | F76: =IF(A76="","",D76) | G76: =IF(A76="","",(G75-G75*'入力 Inputs'!$B$41-'入力 Inputs'!$B$57*(1+'入力 Inputs'!$B$91)^(72-1))*(1+'入力 Inputs'!$B$84)) | H76: {=IF(A76="","",IF(A76<=10,G76*(1-INDEX('入力 Inputs'!$B$71:$B$80,A76)),G76))} | I76: =IF(A76="","",G76) | J76: =IF(A76="","",(J75-J75*'入力 Inputs'!$B$41-'入力 Inputs'!$B$57*(1+'入力 Inputs'!$B$91)^(72-1))*(1+'入力 Inputs'!$B$85)) | K76: {=IF(A76="","",IF(A76<=10,J76*(1-INDEX('入力 Inputs'!$B$71:$B$80,A76)),J76))} | L76: =IF(A76="","",J76) | M76: =IF(A76="","",D76*'入力 Inputs'!$B$64) | N76: =A76 | O76: =IF(A76="","",D76) | P76: =IF(A76="","",G76) | Q76: =IF(A76="","",J76)
A77: =IF(73<='入力 Inputs'!$B$86,73,"") | B77: =IF(A77="","",'入力 Inputs'!$B$55+A77) | C77: =IF(A77="","",0) | D77: =IF(A77="","",(D76-D76*'入力 Inputs'!$B$41-'入力 Inputs'!$B$57*(1+'入力 Inputs'!$B$91)^(73-1))*(1+'入力 Inputs'!$B$83)) | E77: {=IF(A77="","",IF(A77<=10,D77*(1-INDEX('入力 Inputs'!$B$71:$B$80,A77)),D77))} | F77: =IF(A77="","",D77) | G77: =IF(A77="","",(G76-G76*'入力 Inputs'!$B$41-'入力 Inputs'!$B$57*(1+'入力 Inputs'!$B$91)^(73-1))*(1+'入力 Inputs'!$B$84)) | H77: {=IF(A77="","",IF(A77<=10,G77*(1-INDEX('入力 Inputs'!$B$71:$B$80,A77)),G77))} | I77: =IF(A77="","",G77) | J77: =IF(A77="","",(J76-J76*'入力 Inputs'!$B$41-'入力 Inputs'!$B$57*(1+'入力 Inputs'!$B$91)^(73-1))*(1+'入力 Inputs'!$B$85)) | K77: {=IF(A77="","",IF(A77<=10,J77*(1-INDEX('入力 Inputs'!$B$71:$B$80,A77)),J77))} | L77: =IF(A77="","",J77) | M77: =IF(A77="","",D77*'入力 Inputs'!$B$64) | N77: =A77 | O77: =IF(A77="","",D77) | P77: =IF(A77="","",G77) | Q77: =IF(A77="","",J77)
A78: =IF(74<='入力 Inputs'!$B$86,74,"") | B78: =IF(A78="","",'入力 Inputs'!$B$55+A78) | C78: =IF(A78="","",0) | D78: =IF(A78="","",(D77-D77*'入力 Inputs'!$B$41-'入力 Inputs'!$B$57*(1+'入力 Inputs'!$B$91)^(74-1))*(1+'入力 Inputs'!$B$83)) | E78: {=IF(A78="","",IF(A78<=10,D78*(1-INDEX('入力 Inputs'!$B$71:$B$80,A78)),D78))} | F78: =IF(A78="","",D78) | G78: =IF(A78="","",(G77-G77*'入力 Inputs'!$B$41-'入力 Inputs'!$B$57*(1+'入力 Inputs'!$B$91)^(74-1))*(1+'入力 Inputs'!$B$84)) | H78: {=IF(A78="","",IF(A78<=10,G78*(1-INDEX('入力 Inputs'!$B$71:$B$80,A78)),G78))} | I78: =IF(A78="","",G78) | J78: =IF(A78="","",(J77-J77*'入力 Inputs'!$B$41-'入力 Inputs'!$B$57*(1+'入力 Inputs'!$B$91)^(74-1))*(1+'入力 Inputs'!$B$85)) | K78: {=IF(A78="","",IF(A78<=10,J78*(1-INDEX('入力 Inputs'!$B$71:$B$80,A78)),J78))} | L78: =IF(A78="","",J78) | M78: =IF(A78="","",D78*'入力 Inputs'!$B$64) | N78: =A78 | O78: =IF(A78="","",D78) | P78: =IF(A78="","",G78) | Q78: =IF(A78="","",J78)
A79: =IF(75<='入力 Inputs'!$B$86,75,"") | B79: =IF(A79="","",'入力 Inputs'!$B$55+A79) | C79: =IF(A79="","",0) | D79: =IF(A79="","",(D78-D78*'入力 Inputs'!$B$41-'入力 Inputs'!$B$57*(1+'入力 Inputs'!$B$91)^(75-1))*(1+'入力 Inputs'!$B$83)) | E79: {=IF(A79="","",IF(A79<=10,D79*(1-INDEX('入力 Inputs'!$B$71:$B$80,A79)),D79))} | F79: =IF(A79="","",D79) | G79: =IF(A79="","",(G78-G78*'入力 Inputs'!$B$41-'入力 Inputs'!$B$57*(1+'入力 Inputs'!$B$91)^(75-1))*(1+'入力 Inputs'!$B$84)) | H79: {=IF(A79="","",IF(A79<=10,G79*(1-INDEX('入力 Inputs'!$B$71:$B$80,A79)),G79))} | I79: =IF(A79="","",G79) | J79: =IF(A79="","",(J78-J78*'入力 Inputs'!$B$41-'入力 Inputs'!$B$57*(1+'入力 Inputs'!$B$91)^(75-1))*(1+'入力 Inputs'!$B$85)) | K79: {=IF(A79="","",IF(A79<=10,J79*(1-INDEX('入力 Inputs'!$B$71:$B$80,A79)),J79))} | L79: =IF(A79="","",J79) | M79: =IF(A79="","",D79*'入力 Inputs'!$B$64) | N79: =A79 | O79: =IF(A79="","",D79) | P79: =IF(A79="","",G79) | Q79: =IF(A79="","",J79)
A80: =IF(76<='入力 Inputs'!$B$86,76,"") | B80: =IF(A80="","",'入力 Inputs'!$B$55+A80) | C80: =IF(A80="","",0) | D80: =IF(A80="","",(D79-D79*'入力 Inputs'!$B$41-'入力 Inputs'!$B$57*(1+'入力 Inputs'!$B$91)^(76-1))*(1+'入力 Inputs'!$B$83)) | E80: {=IF(A80="","",IF(A80<=10,D80*(1-INDEX('入力 Inputs'!$B$71:$B$80,A80)),D80))} | F80: =IF(A80="","",D80) | G80: =IF(A80="","",(G79-G79*'入力 Inputs'!$B$41-'入力 Inputs'!$B$57*(1+'入力 Inputs'!$B$91)^(76-1))*(1+'入力 Inputs'!$B$84)) | H80: {=IF(A80="","",IF(A80<=10,G80*(1-INDEX('入力 Inputs'!$B$71:$B$80,A80)),G80))} | I80: =IF(A80="","",G80) | J80: =IF(A80="","",(J79-J79*'入力 Inputs'!$B$41-'入力 Inputs'!$B$57*(1+'入力 Inputs'!$B$91)^(76-1))*(1+'入力 Inputs'!$B$85)) | K80: {=IF(A80="","",IF(A80<=10,J80*(1-INDEX('入力 Inputs'!$B$71:$B$80,A80)),J80))} | L80: =IF(A80="","",J80) | M80: =IF(A80="","",D80*'入力 Inputs'!$B$64) | N80: =A80 | O80: =IF(A80="","",D80) | P80: =IF(A80="","",G80) | Q80: =IF(A80="","",J80)
A81: =IF(77<='入力 Inputs'!$B$86,77,"") | B81: =IF(A81="","",'入力 Inputs'!$B$55+A81) | C81: =IF(A81="","",0) | D81: =IF(A81="","",(D80-D80*'入力 Inputs'!$B$41-'入力 Inputs'!$B$57*(1+'入力 Inputs'!$B$91)^(77-1))*(1+'入力 Inputs'!$B$83)) | E81: {=IF(A81="","",IF(A81<=10,D81*(1-INDEX('入力 Inputs'!$B$71:$B$80,A81)),D81))} | F81: =IF(A81="","",D81) | G81: =IF(A81="","",(G80-G80*'入力 Inputs'!$B$41-'入力 Inputs'!$B$57*(1+'入力 Inputs'!$B$91)^(77-1))*(1+'入力 Inputs'!$B$84)) | H81: {=IF(A81="","",IF(A81<=10,G81*(1-INDEX('入力 Inputs'!$B$71:$B$80,A81)),G81))} | I81: =IF(A81="","",G81) | J81: =IF(A81="","",(J80-J80*'入力 Inputs'!$B$41-'入力 Inputs'!$B$57*(1+'入力 Inputs'!$B$91)^(77-1))*(1+'入力 Inputs'!$B$85)) | K81: {=IF(A81="","",IF(A81<=10,J81*(1-INDEX('入力 Inputs'!$B$71:$B$80,A81)),J81))} | L81: =IF(A81="","",J81) | M81: =IF(A81="","",D81*'入力 Inputs'!$B$64) | N81: =A81 | O81: =IF(A81="","",D81) | P81: =IF(A81="","",G81) | Q81: =IF(A81="","",J81)
A82: =IF(78<='入力 Inputs'!$B$86,78,"") | B82: =IF(A82="","",'入力 Inputs'!$B$55+A82) | C82: =IF(A82="","",0) | D82: =IF(A82="","",(D81-D81*'入力 Inputs'!$B$41-'入力 Inputs'!$B$57*(1+'入力 Inputs'!$B$91)^(78-1))*(1+'入力 Inputs'!$B$83)) | E82: {=IF(A82="","",IF(A82<=10,D82*(1-INDEX('入力 Inputs'!$B$71:$B$80,A82)),D82))} | F82: =IF(A82="","",D82) | G82: =IF(A82="","",(G81-G81*'入力 Inputs'!$B$41-'入力 Inputs'!$B$57*(1+'入力 Inputs'!$B$91)^(78-1))*(1+'入力 Inputs'!$B$84)) | H82: {=IF(A82="","",IF(A82<=10,G82*(1-INDEX('入力 Inputs'!$B$71:$B$80,A82)),G82))} | I82: =IF(A82="","",G82) | J82: =IF(A82="","",(J81-J81*'入力 Inputs'!$B$41-'入力 Inputs'!$B$57*(1+'入力 Inputs'!$B$91)^(78-1))*(1+'入力 Inputs'!$B$85)) | K82: {=IF(A82="","",IF(A82<=10,J82*(1-INDEX('入力 Inputs'!$B$71:$B$80,A82)),J82))} | L82: =IF(A82="","",J82) | M82: =IF(A82="","",D82*'入力 Inputs'!$B$64) | N82: =A82 | O82: =IF(A82="","",D82) | P82: =IF(A82="","",G82) | Q82: =IF(A82="","",J82)
A83: =IF(79<='入力 Inputs'!$B$86,79,"") | B83: =IF(A83="","",'入力 Inputs'!$B$55+A83) | C83: =IF(A83="","",0) | D83: =IF(A83="","",(D82-D82*'入力 Inputs'!$B$41-'入力 Inputs'!$B$57*(1+'入力 Inputs'!$B$91)^(79-1))*(1+'入力 Inputs'!$B$83)) | E83: {=IF(A83="","",IF(A83<=10,D83*(1-INDEX('入力 Inputs'!$B$71:$B$80,A83)),D83))} | F83: =IF(A83="","",D83) | G83: =IF(A83="","",(G82-G82*'入力 Inputs'!$B$41-'入力 Inputs'!$B$57*(1+'入力 Inputs'!$B$91)^(79-1))*(1+'入力 Inputs'!$B$84)) | H83: {=IF(A83="","",IF(A83<=10,G83*(1-INDEX('入力 Inputs'!$B$71:$B$80,A83)),G83))} | I83: =IF(A83="","",G83) | J83: =IF(A83="","",(J82-J82*'入力 Inputs'!$B$41-'入力 Inputs'!$B$57*(1+'入力 Inputs'!$B$91)^(79-1))*(1+'入力 Inputs'!$B$85)) | K83: {=IF(A83="","",IF(A83<=10,J83*(1-INDEX('入力 Inputs'!$B$71:$B$80,A83)),J83))} | L83: =IF(A83="","",J83) | M83: =IF(A83="","",D83*'入力 Inputs'!$B$64) | N83: =A83 | O83: =IF(A83="","",D83) | P83: =IF(A83="","",G83) | Q83: =IF(A83="","",J83)
A84: =IF(80<='入力 Inputs'!$B$86,80,"") | B84: =IF(A84="","",'入力 Inputs'!$B$55+A84) | C84: =IF(A84="","",0) | D84: =IF(A84="","",(D83-D83*'入力 Inputs'!$B$41-'入力 Inputs'!$B$57*(1+'入力 Inputs'!$B$91)^(80-1))*(1+'入力 Inputs'!$B$83)) | E84: {=IF(A84="","",IF(A84<=10,D84*(1-INDEX('入力 Inputs'!$B$71:$B$80,A84)),D84))} | F84: =IF(A84="","",D84) | G84: =IF(A84="","",(G83-G83*'入力 Inputs'!$B$41-'入力 Inputs'!$B$57*(1+'入力 Inputs'!$B$91)^(80-1))*(1+'入力 Inputs'!$B$84)) | H84: {=IF(A84="","",IF(A84<=10,G84*(1-INDEX('入力 Inputs'!$B$71:$B$80,A84)),G84))} | I84: =IF(A84="","",G84) | J84: =IF(A84="","",(J83-J83*'入力 Inputs'!$B$41-'入力 Inputs'!$B$57*(1+'入力 Inputs'!$B$91)^(80-1))*(1+'入力 Inputs'!$B$85)) | K84: {=IF(A84="","",IF(A84<=10,J84*(1-INDEX('入力 Inputs'!$B$71:$B$80,A84)),J84))} | L84: =IF(A84="","",J84) | M84: =IF(A84="","",D84*'入力 Inputs'!$B$64) | N84: =A84 | O84: =IF(A84="","",D84) | P84: =IF(A84="","",G84) | Q84: =IF(A84="","",J84)
A85: =IF(81<='入力 Inputs'!$B$86,81,"") | B85: =IF(A85="","",'入力 Inputs'!$B$55+A85) | C85: =IF(A85="","",0) | D85: =IF(A85="","",(D84-D84*'入力 Inputs'!$B$41-'入力 Inputs'!$B$57*(1+'入力 Inputs'!$B$91)^(81-1))*(1+'入力 Inputs'!$B$83)) | E85: {=IF(A85="","",IF(A85<=10,D85*(1-INDEX('入力 Inputs'!$B$71:$B$80,A85)),D85))} | F85: =IF(A85="","",D85) | G85: =IF(A85="","",(G84-G84*'入力 Inputs'!$B$41-'入力 Inputs'!$B$57*(1+'入力 Inputs'!$B$91)^(81-1))*(1+'入力 Inputs'!$B$84)) | H85: {=IF(A85="","",IF(A85<=10,G85*(1-INDEX('入力 Inputs'!$B$71:$B$80,A85)),G85))} | I85: =IF(A85="","",G85) | J85: =IF(A85="","",(J84-J84*'入力 Inputs'!$B$41-'入力 Inputs'!$B$57*(1+'入力 Inputs'!$B$91)^(81-1))*(1+'入力 Inputs'!$B$85)) | K85: {=IF(A85="","",IF(A85<=10,J85*(1-INDEX('入力 Inputs'!$B$71:$B$80,A85)),J85))} | L85: =IF(A85="","",J85) | M85: =IF(A85="","",D85*'入力 Inputs'!$B$64) | N85: =A85 | O85: =IF(A85="","",D85) | P85: =IF(A85="","",G85) | Q85: =IF(A85="","",J85)
A86: =IF(82<='入力 Inputs'!$B$86,82,"") | B86: =IF(A86="","",'入力 Inputs'!$B$55+A86) | C86: =IF(A86="","",0) | D86: =IF(A86="","",(D85-D85*'入力 Inputs'!$B$41-'入力 Inputs'!$B$57*(1+'入力 Inputs'!$B$91)^(82-1))*(1+'入力 Inputs'!$B$83)) | E86: {=IF(A86="","",IF(A86<=10,D86*(1-INDEX('入力 Inputs'!$B$71:$B$80,A86)),D86))} | F86: =IF(A86="","",D86) | G86: =IF(A86="","",(G85-G85*'入力 Inputs'!$B$41-'入力 Inputs'!$B$57*(1+'入力 Inputs'!$B$91)^(82-1))*(1+'入力 Inputs'!$B$84)) | H86: {=IF(A86="","",IF(A86<=10,G86*(1-INDEX('入力 Inputs'!$B$71:$B$80,A86)),G86))} | I86: =IF(A86="","",G86) | J86: =IF(A86="","",(J85-J85*'入力 Inputs'!$B$41-'入力 Inputs'!$B$57*(1+'入力 Inputs'!$B$91)^(82-1))*(1+'入力 Inputs'!$B$85)) | K86: {=IF(A86="","",IF(A86<=10,J86*(1-INDEX('入力 Inputs'!$B$71:$B$80,A86)),J86))} | L86: =IF(A86="","",J86) | M86: =IF(A86="","",D86*'入力 Inputs'!$B$64) | N86: =A86 | O86: =IF(A86="","",D86) | P86: =IF(A86="","",G86) | Q86: =IF(A86="","",J86)
A87: =IF(83<='入力 Inputs'!$B$86,83,"") | B87: =IF(A87="","",'入力 Inputs'!$B$55+A87) | C87: =IF(A87="","",0) | D87: =IF(A87="","",(D86-D86*'入力 Inputs'!$B$41-'入力 Inputs'!$B$57*(1+'入力 Inputs'!$B$91)^(83-1))*(1+'入力 Inputs'!$B$83)) | E87: {=IF(A87="","",IF(A87<=10,D87*(1-INDEX('入力 Inputs'!$B$71:$B$80,A87)),D87))} | F87: =IF(A87="","",D87) | G87: =IF(A87="","",(G86-G86*'入力 Inputs'!$B$41-'入力 Inputs'!$B$57*(1+'入力 Inputs'!$B$91)^(83-1))*(1+'入力 Inputs'!$B$84)) | H87: {=IF(A87="","",IF(A87<=10,G87*(1-INDEX('入力 Inputs'!$B$71:$B$80,A87)),G87))} | I87: =IF(A87="","",G87) | J87: =IF(A87="","",(J86-J86*'入力 Inputs'!$B$41-'入力 Inputs'!$B$57*(1+'入力 Inputs'!$B$91)^(83-1))*(1+'入力 Inputs'!$B$85)) | K87: {=IF(A87="","",IF(A87<=10,J87*(1-INDEX('入力 Inputs'!$B$71:$B$80,A87)),J87))} | L87: =IF(A87="","",J87) | M87: =IF(A87="","",D87*'入力 Inputs'!$B$64) | N87: =A87 | O87: =IF(A87="","",D87) | P87: =IF(A87="","",G87) | Q87: =IF(A87="","",J87)
A88: =IF(84<='入力 Inputs'!$B$86,84,"") | B88: =IF(A88="","",'入力 Inputs'!$B$55+A88) | C88: =IF(A88="","",0) | D88: =IF(A88="","",(D87-D87*'入力 Inputs'!$B$41-'入力 Inputs'!$B$57*(1+'入力 Inputs'!$B$91)^(84-1))*(1+'入力 Inputs'!$B$83)) | E88: {=IF(A88="","",IF(A88<=10,D88*(1-INDEX('入力 Inputs'!$B$71:$B$80,A88)),D88))} | F88: =IF(A88="","",D88) | G88: =IF(A88="","",(G87-G87*'入力 Inputs'!$B$41-'入力 Inputs'!$B$57*(1+'入力 Inputs'!$B$91)^(84-1))*(1+'入力 Inputs'!$B$84)) | H88: {=IF(A88="","",IF(A88<=10,G88*(1-INDEX('入力 Inputs'!$B$71:$B$80,A88)),G88))} | I88: =IF(A88="","",G88) | J88: =IF(A88="","",(J87-J87*'入力 Inputs'!$B$41-'入力 Inputs'!$B$57*(1+'入力 Inputs'!$B$91)^(84-1))*(1+'入力 Inputs'!$B$85)) | K88: {=IF(A88="","",IF(A88<=10,J88*(1-INDEX('入力 Inputs'!$B$71:$B$80,A88)),J88))} | L88: =IF(A88="","",J88) | M88: =IF(A88="","",D88*'入力 Inputs'!$B$64) | N88: =A88 | O88: =IF(A88="","",D88) | P88: =IF(A88="","",G88) | Q88: =IF(A88="","",J88)
A89: =IF(85<='入力 Inputs'!$B$86,85,"") | B89: =IF(A89="","",'入力 Inputs'!$B$55+A89) | C89: =IF(A89="","",0) | D89: =IF(A89="","",(D88-D88*'入力 Inputs'!$B$41-'入力 Inputs'!$B$57*(1+'入力 Inputs'!$B$91)^(85-1))*(1+'入力 Inputs'!$B$83)) | E89: {=IF(A89="","",IF(A89<=10,D89*(1-INDEX('入力 Inputs'!$B$71:$B$80,A89)),D89))} | F89: =IF(A89="","",D89) | G89: =IF(A89="","",(G88-G88*'入力 Inputs'!$B$41-'入力 Inputs'!$B$57*(1+'入力 Inputs'!$B$91)^(85-1))*(1+'入力 Inputs'!$B$84)) | H89: {=IF(A89="","",IF(A89<=10,G89*(1-INDEX('入力 Inputs'!$B$71:$B$80,A89)),G89))} | I89: =IF(A89="","",G89) | J89: =IF(A89="","",(J88-J88*'入力 Inputs'!$B$41-'入力 Inputs'!$B$57*(1+'入力 Inputs'!$B$91)^(85-1))*(1+'入力 Inputs'!$B$85)) | K89: {=IF(A89="","",IF(A89<=10,J89*(1-INDEX('入力 Inputs'!$B$71:$B$80,A89)),J89))} | L89: =IF(A89="","",J89) | M89: =IF(A89="","",D89*'入力 Inputs'!$B$64) | N89: =A89 | O89: =IF(A89="","",D89) | P89: =IF(A89="","",G89) | Q89: =IF(A89="","",J89)
A90: =IF(86<='入力 Inputs'!$B$86,86,"") | B90: =IF(A90="","",'入力 Inputs'!$B$55+A90) | C90: =IF(A90="","",0) | D90: =IF(A90="","",(D89-D89*'入力 Inputs'!$B$41-'入力 Inputs'!$B$57*(1+'入力 Inputs'!$B$91)^(86-1))*(1+'入力 Inputs'!$B$83)) | E90: {=IF(A90="","",IF(A90<=10,D90*(1-INDEX('入力 Inputs'!$B$71:$B$80,A90)),D90))} | F90: =IF(A90="","",D90) | G90: =IF(A90="","",(G89-G89*'入力 Inputs'!$B$41-'入力 Inputs'!$B$57*(1+'入力 Inputs'!$B$91)^(86-1))*(1+'入力 Inputs'!$B$84)) | H90: {=IF(A90="","",IF(A90<=10,G90*(1-INDEX('入力 Inputs'!$B$71:$B$80,A90)),G90))} | I90: =IF(A90="","",G90) | J90: =IF(A90="","",(J89-J89*'入力 Inputs'!$B$41-'入力 Inputs'!$B$57*(1+'入力 Inputs'!$B$91)^(86-1))*(1+'入力 Inputs'!$B$85)) | K90: {=IF(A90="","",IF(A90<=10,J90*(1-INDEX('入力 Inputs'!$B$71:$B$80,A90)),J90))} | L90: =IF(A90="","",J90) | M90: =IF(A90="","",D90*'入力 Inputs'!$B$64) | N90: =A90 | O90: =IF(A90="","",D90) | P90: =IF(A90="","",G90) | Q90: =IF(A90="","",J90)
A91: =IF(87<='入力 Inputs'!$B$86,87,"") | B91: =IF(A91="","",'入力 Inputs'!$B$55+A91) | C91: =IF(A91="","",0) | D91: =IF(A91="","",(D90-D90*'入力 Inputs'!$B$41-'入力 Inputs'!$B$57*(1+'入力 Inputs'!$B$91)^(87-1))*(1+'入力 Inputs'!$B$83)) | E91: {=IF(A91="","",IF(A91<=10,D91*(1-INDEX('入力 Inputs'!$B$71:$B$80,A91)),D91))} | F91: =IF(A91="","",D91) | G91: =IF(A91="","",(G90-G90*'入力 Inputs'!$B$41-'入力 Inputs'!$B$57*(1+'入力 Inputs'!$B$91)^(87-1))*(1+'入力 Inputs'!$B$84)) | H91: {=IF(A91="","",IF(A91<=10,G91*(1-INDEX('入力 Inputs'!$B$71:$B$80,A91)),G91))} | I91: =IF(A91="","",G91) | J91: =IF(A91="","",(J90-J90*'入力 Inputs'!$B$41-'入力 Inputs'!$B$57*(1+'入力 Inputs'!$B$91)^(87-1))*(1+'入力 Inputs'!$B$85)) | K91: {=IF(A91="","",IF(A91<=10,J91*(1-INDEX('入力 Inputs'!$B$71:$B$80,A91)),J91))} | L91: =IF(A91="","",J91) | M91: =IF(A91="","",D91*'入力 Inputs'!$B$64) | N91: =A91 | O91: =IF(A91="","",D91) | P91: =IF(A91="","",G91) | Q91: =IF(A91="","",J91)
A92: =IF(88<='入力 Inputs'!$B$86,88,"") | B92: =IF(A92="","",'入力 Inputs'!$B$55+A92) | C92: =IF(A92="","",0) | D92: =IF(A92="","",(D91-D91*'入力 Inputs'!$B$41-'入力 Inputs'!$B$57*(1+'入力 Inputs'!$B$91)^(88-1))*(1+'入力 Inputs'!$B$83)) | E92: {=IF(A92="","",IF(A92<=10,D92*(1-INDEX('入力 Inputs'!$B$71:$B$80,A92)),D92))} | F92: =IF(A92="","",D92) | G92: =IF(A92="","",(G91-G91*'入力 Inputs'!$B$41-'入力 Inputs'!$B$57*(1+'入力 Inputs'!$B$91)^(88-1))*(1+'入力 Inputs'!$B$84)) | H92: {=IF(A92="","",IF(A92<=10,G92*(1-INDEX('入力 Inputs'!$B$71:$B$80,A92)),G92))} | I92: =IF(A92="","",G92) | J92: =IF(A92="","",(J91-J91*'入力 Inputs'!$B$41-'入力 Inputs'!$B$57*(1+'入力 Inputs'!$B$91)^(88-1))*(1+'入力 Inputs'!$B$85)) | K92: {=IF(A92="","",IF(A92<=10,J92*(1-INDEX('入力 Inputs'!$B$71:$B$80,A92)),J92))} | L92: =IF(A92="","",J92) | M92: =IF(A92="","",D92*'入力 Inputs'!$B$64) | N92: =A92 | O92: =IF(A92="","",D92) | P92: =IF(A92="","",G92) | Q92: =IF(A92="","",J92)
A93: =IF(89<='入力 Inputs'!$B$86,89,"") | B93: =IF(A93="","",'入力 Inputs'!$B$55+A93) | C93: =IF(A93="","",0) | D93: =IF(A93="","",(D92-D92*'入力 Inputs'!$B$41-'入力 Inputs'!$B$57*(1+'入力 Inputs'!$B$91)^(89-1))*(1+'入力 Inputs'!$B$83)) | E93: {=IF(A93="","",IF(A93<=10,D93*(1-INDEX('入力 Inputs'!$B$71:$B$80,A93)),D93))} | F93: =IF(A93="","",D93) | G93: =IF(A93="","",(G92-G92*'入力 Inputs'!$B$41-'入力 Inputs'!$B$57*(1+'入力 Inputs'!$B$91)^(89-1))*(1+'入力 Inputs'!$B$84)) | H93: {=IF(A93="","",IF(A93<=10,G93*(1-INDEX('入力 Inputs'!$B$71:$B$80,A93)),G93))} | I93: =IF(A93="","",G93) | J93: =IF(A93="","",(J92-J92*'入力 Inputs'!$B$41-'入力 Inputs'!$B$57*(1+'入力 Inputs'!$B$91)^(89-1))*(1+'入力 Inputs'!$B$85)) | K93: {=IF(A93="","",IF(A93<=10,J93*(1-INDEX('入力 Inputs'!$B$71:$B$80,A93)),J93))} | L93: =IF(A93="","",J93) | M93: =IF(A93="","",D93*'入力 Inputs'!$B$64) | N93: =A93 | O93: =IF(A93="","",D93) | P93: =IF(A93="","",G93) | Q93: =IF(A93="","",J93)
A94: =IF(90<='入力 Inputs'!$B$86,90,"") | B94: =IF(A94="","",'入力 Inputs'!$B$55+A94) | C94: =IF(A94="","",0) | D94: =IF(A94="","",(D93-D93*'入力 Inputs'!$B$41-'入力 Inputs'!$B$57*(1+'入力 Inputs'!$B$91)^(90-1))*(1+'入力 Inputs'!$B$83)) | E94: {=IF(A94="","",IF(A94<=10,D94*(1-INDEX('入力 Inputs'!$B$71:$B$80,A94)),D94))} | F94: =IF(A94="","",D94) | G94: =IF(A94="","",(G93-G93*'入力 Inputs'!$B$41-'入力 Inputs'!$B$57*(1+'入力 Inputs'!$B$91)^(90-1))*(1+'入力 Inputs'!$B$84)) | H94: {=IF(A94="","",IF(A94<=10,G94*(1-INDEX('入力 Inputs'!$B$71:$B$80,A94)),G94))} | I94: =IF(A94="","",G94) | J94: =IF(A94="","",(J93-J93*'入力 Inputs'!$B$41-'入力 Inputs'!$B$57*(1+'入力 Inputs'!$B$91)^(90-1))*(1+'入力 Inputs'!$B$85)) | K94: {=IF(A94="","",IF(A94<=10,J94*(1-INDEX('入力 Inputs'!$B$71:$B$80,A94)),J94))} | L94: =IF(A94="","",J94) | M94: =IF(A94="","",D94*'入力 Inputs'!$B$64) | N94: =A94 | O94: =IF(A94="","",D94) | P94: =IF(A94="","",G94) | Q94: =IF(A94="","",J94)
A95: =IF(91<='入力 Inputs'!$B$86,91,"") | B95: =IF(A95="","",'入力 Inputs'!$B$55+A95) | C95: =IF(A95="","",0) | D95: =IF(A95="","",(D94-D94*'入力 Inputs'!$B$41-'入力 Inputs'!$B$57*(1+'入力 Inputs'!$B$91)^(91-1))*(1+'入力 Inputs'!$B$83)) | E95: {=IF(A95="","",IF(A95<=10,D95*(1-INDEX('入力 Inputs'!$B$71:$B$80,A95)),D95))} | F95: =IF(A95="","",D95) | G95: =IF(A95="","",(G94-G94*'入力 Inputs'!$B$41-'入力 Inputs'!$B$57*(1+'入力 Inputs'!$B$91)^(91-1))*(1+'入力 Inputs'!$B$84)) | H95: {=IF(A95="","",IF(A95<=10,G95*(1-INDEX('入力 Inputs'!$B$71:$B$80,A95)),G95))} | I95: =IF(A95="","",G95) | J95: =IF(A95="","",(J94-J94*'入力 Inputs'!$B$41-'入力 Inputs'!$B$57*(1+'入力 Inputs'!$B$91)^(91-1))*(1+'入力 Inputs'!$B$85)) | K95: {=IF(A95="","",IF(A95<=10,J95*(1-INDEX('入力 Inputs'!$B$71:$B$80,A95)),J95))} | L95: =IF(A95="","",J95) | M95: =IF(A95="","",D95*'入力 Inputs'!$B$64) | N95: =A95 | O95: =IF(A95="","",D95) | P95: =IF(A95="","",G95) | Q95: =IF(A95="","",J95)
A96: =IF(92<='入力 Inputs'!$B$86,92,"") | B96: =IF(A96="","",'入力 Inputs'!$B$55+A96) | C96: =IF(A96="","",0) | D96: =IF(A96="","",(D95-D95*'入力 Inputs'!$B$41-'入力 Inputs'!$B$57*(1+'入力 Inputs'!$B$91)^(92-1))*(1+'入力 Inputs'!$B$83)) | E96: {=IF(A96="","",IF(A96<=10,D96*(1-INDEX('入力 Inputs'!$B$71:$B$80,A96)),D96))} | F96: =IF(A96="","",D96) | G96: =IF(A96="","",(G95-G95*'入力 Inputs'!$B$41-'入力 Inputs'!$B$57*(1+'入力 Inputs'!$B$91)^(92-1))*(1+'入力 Inputs'!$B$84)) | H96: {=IF(A96="","",IF(A96<=10,G96*(1-INDEX('入力 Inputs'!$B$71:$B$80,A96)),G96))} | I96: =IF(A96="","",G96) | J96: =IF(A96="","",(J95-J95*'入力 Inputs'!$B$41-'入力 Inputs'!$B$57*(1+'入力 Inputs'!$B$91)^(92-1))*(1+'入力 Inputs'!$B$85)) | K96: {=IF(A96="","",IF(A96<=10,J96*(1-INDEX('入力 Inputs'!$B$71:$B$80,A96)),J96))} | L96: =IF(A96="","",J96) | M96: =IF(A96="","",D96*'入力 Inputs'!$B$64) | N96: =A96 | O96: =IF(A96="","",D96) | P96: =IF(A96="","",G96) | Q96: =IF(A96="","",J96)
A97: =IF(93<='入力 Inputs'!$B$86,93,"") | B97: =IF(A97="","",'入力 Inputs'!$B$55+A97) | C97: =IF(A97="","",0) | D97: =IF(A97="","",(D96-D96*'入力 Inputs'!$B$41-'入力 Inputs'!$B$57*(1+'入力 Inputs'!$B$91)^(93-1))*(1+'入力 Inputs'!$B$83)) | E97: {=IF(A97="","",IF(A97<=10,D97*(1-INDEX('入力 Inputs'!$B$71:$B$80,A97)),D97))} | F97: =IF(A97="","",D97) | G97: =IF(A97="","",(G96-G96*'入力 Inputs'!$B$41-'入力 Inputs'!$B$57*(1+'入力 Inputs'!$B$91)^(93-1))*(1+'入力 Inputs'!$B$84)) | H97: {=IF(A97="","",IF(A97<=10,G97*(1-INDEX('入力 Inputs'!$B$71:$B$80,A97)),G97))} | I97: =IF(A97="","",G97) | J97: =IF(A97="","",(J96-J96*'入力 Inputs'!$B$41-'入力 Inputs'!$B$57*(1+'入力 Inputs'!$B$91)^(93-1))*(1+'入力 Inputs'!$B$85)) | K97: {=IF(A97="","",IF(A97<=10,J97*(1-INDEX('入力 Inputs'!$B$71:$B$80,A97)),J97))} | L97: =IF(A97="","",J97) | M97: =IF(A97="","",D97*'入力 Inputs'!$B$64) | N97: =A97 | O97: =IF(A97="","",D97) | P97: =IF(A97="","",G97) | Q97: =IF(A97="","",J97)
A98: =IF(94<='入力 Inputs'!$B$86,94,"") | B98: =IF(A98="","",'入力 Inputs'!$B$55+A98) | C98: =IF(A98="","",0) | D98: =IF(A98="","",(D97-D97*'入力 Inputs'!$B$41-'入力 Inputs'!$B$57*(1+'入力 Inputs'!$B$91)^(94-1))*(1+'入力 Inputs'!$B$83)) | E98: {=IF(A98="","",IF(A98<=10,D98*(1-INDEX('入力 Inputs'!$B$71:$B$80,A98)),D98))} | F98: =IF(A98="","",D98) | G98: =IF(A98="","",(G97-G97*'入力 Inputs'!$B$41-'入力 Inputs'!$B$57*(1+'入力 Inputs'!$B$91)^(94-1))*(1+'入力 Inputs'!$B$84)) | H98: {=IF(A98="","",IF(A98<=10,G98*(1-INDEX('入力 Inputs'!$B$71:$B$80,A98)),G98))} | I98: =IF(A98="","",G98) | J98: =IF(A98="","",(J97-J97*'入力 Inputs'!$B$41-'入力 Inputs'!$B$57*(1+'入力 Inputs'!$B$91)^(94-1))*(1+'入力 Inputs'!$B$85)) | K98: {=IF(A98="","",IF(A98<=10,J98*(1-INDEX('入力 Inputs'!$B$71:$B$80,A98)),J98))} | L98: =IF(A98="","",J98) | M98: =IF(A98="","",D98*'入力 Inputs'!$B$64) | N98: =A98 | O98: =IF(A98="","",D98) | P98: =IF(A98="","",G98) | Q98: =IF(A98="","",J98)
A99: =IF(95<='入力 Inputs'!$B$86,95,"") | B99: =IF(A99="","",'入力 Inputs'!$B$55+A99) | C99: =IF(A99="","",0) | D99: =IF(A99="","",(D98-D98*'入力 Inputs'!$B$41-'入力 Inputs'!$B$57*(1+'入力 Inputs'!$B$91)^(95-1))*(1+'入力 Inputs'!$B$83)) | E99: {=IF(A99="","",IF(A99<=10,D99*(1-INDEX('入力 Inputs'!$B$71:$B$80,A99)),D99))} | F99: =IF(A99="","",D99) | G99: =IF(A99="","",(G98-G98*'入力 Inputs'!$B$41-'入力 Inputs'!$B$57*(1+'入力 Inputs'!$B$91)^(95-1))*(1+'入力 Inputs'!$B$84)) | H99: {=IF(A99="","",IF(A99<=10,G99*(1-INDEX('入力 Inputs'!$B$71:$B$80,A99)),G99))} | I99: =IF(A99="","",G99) | J99: =IF(A99="","",(J98-J98*'入力 Inputs'!$B$41-'入力 Inputs'!$B$57*(1+'入力 Inputs'!$B$91)^(95-1))*(1+'入力 Inputs'!$B$85)) | K99: {=IF(A99="","",IF(A99<=10,J99*(1-INDEX('入力 Inputs'!$B$71:$B$80,A99)),J99))} | L99: =IF(A99="","",J99) | M99: =IF(A99="","",D99*'入力 Inputs'!$B$64) | N99: =A99 | O99: =IF(A99="","",D99) | P99: =IF(A99="","",G99) | Q99: =IF(A99="","",J99)
A100: =IF(96<='入力 Inputs'!$B$86,96,"") | B100: =IF(A100="","",'入力 Inputs'!$B$55+A100) | C100: =IF(A100="","",0) | D100: =IF(A100="","",(D99-D99*'入力 Inputs'!$B$41-'入力 Inputs'!$B$57*(1+'入力 Inputs'!$B$91)^(96-1))*(1+'入力 Inputs'!$B$83)) | E100: {=IF(A100="","",IF(A100<=10,D100*(1-INDEX('入力 Inputs'!$B$71:$B$80,A100)),D100))} | F100: =IF(A100="","",D100) | G100: =IF(A100="","",(G99-G99*'入力 Inputs'!$B$41-'入力 Inputs'!$B$57*(1+'入力 Inputs'!$B$91)^(96-1))*(1+'入力 Inputs'!$B$84)) | H100: {=IF(A100="","",IF(A100<=10,G100*(1-INDEX('入力 Inputs'!$B$71:$B$80,A100)),G100))} | I100: =IF(A100="","",G100) | J100: =IF(A100="","",(J99-J99*'入力 Inputs'!$B$41-'入力 Inputs'!$B$57*(1+'入力 Inputs'!$B$91)^(96-1))*(1+'入力 Inputs'!$B$85)) | K100: {=IF(A100="","",IF(A100<=10,J100*(1-INDEX('入力 Inputs'!$B$71:$B$80,A100)),J100))} | L100: =IF(A100="","",J100) | M100: =IF(A100="","",D100*'入力 Inputs'!$B$64) | N100: =A100 | O100: =IF(A100="","",D100) | P100: =IF(A100="","",G100) | Q100: =IF(A100="","",J100)
A101: =IF(97<='入力 Inputs'!$B$86,97,"") | B101: =IF(A101="","",'入力 Inputs'!$B$55+A101) | C101: =IF(A101="","",0) | D101: =IF(A101="","",(D100-D100*'入力 Inputs'!$B$41-'入力 Inputs'!$B$57*(1+'入力 Inputs'!$B$91)^(97-1))*(1+'入力 Inputs'!$B$83)) | E101: {=IF(A101="","",IF(A101<=10,D101*(1-INDEX('入力 Inputs'!$B$71:$B$80,A101)),D101))} | F101: =IF(A101="","",D101) | G101: =IF(A101="","",(G100-G100*'入力 Inputs'!$B$41-'入力 Inputs'!$B$57*(1+'入力 Inputs'!$B$91)^(97-1))*(1+'入力 Inputs'!$B$84)) | H101: {=IF(A101="","",IF(A101<=10,G101*(1-INDEX('入力 Inputs'!$B$71:$B$80,A101)),G101))} | I101: =IF(A101="","",G101) | J101: =IF(A101="","",(J100-J100*'入力 Inputs'!$B$41-'入力 Inputs'!$B$57*(1+'入力 Inputs'!$B$91)^(97-1))*(1+'入力 Inputs'!$B$85)) | K101: {=IF(A101="","",IF(A101<=10,J101*(1-INDEX('入力 Inputs'!$B$71:$B$80,A101)),J101))} | L101: =IF(A101="","",J101) | M101: =IF(A101="","",D101*'入力 Inputs'!$B$64) | N101: =A101 | O101: =IF(A101="","",D101) | P101: =IF(A101="","",G101) | Q101: =IF(A101="","",J101)
...

Sheet 税金 Tax Impact
A1: =IF('入力 Inputs'!$F$1="English","PPVA TAX IMPACT ANALYSIS",IF('入力 Inputs'!$F$1="日本語","PPVA税金への影響分析","PPVA税金への影響分析 / PPVA TAX IMPACT ANALYSIS")) -> PPVA TAX IMPACT ANALYSIS | B1: Make second for US | C1: Combined CSV to include USD as well
A2: =IF('入力 Inputs'!$F$1="English","All values pull from Inputs. Current portfolio vs. new PPVA tax impact.",IF('入力 Inputs'!$F$1="日本語","全ての値は入力シートから取得。現行ポートフォリオとPPVAの税金影響を比較","全ての値は入力シートから取得。現行ポートフォリオとPPVAの税金影響を比較 / All values pull from Inputs. Current portfolio vs. new PPVA tax impact.")) -> All values pull from Inputs. Current portfolio vs. new PPVA tax impact.
A4: =IF('入力 Inputs'!$F$1="English","CURRENT POSITION (Without New PPVA)",IF('入力 Inputs'!$F$1="日本語","現在のポジション（新規PPVAなし）","現在のポジション（新規PPVAなし） / CURRENT POSITION (Without New PPVA)")) -> CURRENT POSITION (Without New PPVA)
A5: =IF('入力 Inputs'!$F$1="English","Current CSV (USD)",IF('入力 Inputs'!$F$1="日本語","現行解約返戻金（米ドル）","現行解約返戻金（米ドル） / Current CSV (USD)")) -> Current CSV (USD) | B5: ='入力 Inputs'!B60 -> 18963106 | D5: =IF('入力 Inputs'!$F$1="English","Current CSV (JPY)",IF('入力 Inputs'!$F$1="日本語","現行解約返戻金（円）","現行解約返戻金（円） / Current CSV (JPY)")) -> Current CSV (JPY) | E5: =B5*'入力 Inputs'!B63 -> 2844465900
A6: =IF('入力 Inputs'!$F$1="English","Basis (USD)",IF('入力 Inputs'!$F$1="日本語","基準額（米ドル）","基準額（米ドル） / Basis (USD)")) -> Basis (USD) | B6: ='入力 Inputs'!B61 -> 16195676 | D6: =IF('入力 Inputs'!$F$1="English","Basis (JPY)",IF('入力 Inputs'!$F$1="日本語","基準額（円）","基準額（円） / Basis (JPY)")) -> Basis (JPY) | E6: ='入力 Inputs'!B67 -> 1781524360
A7: =IF('入力 Inputs'!$F$1="English","Gain (USD)",IF('入力 Inputs'!$F$1="日本語","利益（米ドル）","利益（米ドル） / Gain (USD)")) -> Gain (USD) | B7: =B5-B6 -> 2767430 | D7: =IF('入力 Inputs'!$F$1="English","Gain (JPY)",IF('入力 Inputs'!$F$1="日本語","利益（円）","利益（円） / Gain (JPY)")) -> Gain (JPY) | E7: =E5-E6 -> 1062941540
A8: =IF('入力 Inputs'!$F$1="English","Tax Impact (USD)",IF('入力 Inputs'!$F$1="日本語","税金への影響（米ドル）","税金への影響（米ドル） / Tax Impact (USD)")) -> Tax Impact (USD) | B8: =B7*'入力 Inputs'!B66 -> 1522086.5 | D8: =IF('入力 Inputs'!$F$1="English","Tax Impact (JPY)",IF('入力 Inputs'!$F$1="日本語","税金への影響（円）","税金への影響（円） / Tax Impact (JPY)")) -> Tax Impact (JPY) | E8: =E7*'入力 Inputs'!B66 -> 584617847
A12: =IF('入力 Inputs'!$F$1="English","10-YEAR TAX IMPACT: WITHOUT vs. WITH PPVA",IF('入力 Inputs'!$F$1="日本語","10年間税金への影響比較","10年間税金への影響比較 / 10-YEAR TAX IMPACT: WITHOUT vs. WITH PPVA")) -> 10-YEAR TAX IMPACT: WITHOUT vs. WITH PPVA
A13: =IF('入力 Inputs'!$F$1="English","Year",IF('入力 Inputs'!$F$1="日本語","年","年 / Year")) -> Year | B13: =IF('入力 Inputs'!$F$1="English","Existing CSV (USD)",IF('入力 Inputs'!$F$1="日本語","既存CSV（米ドル）","既存CSV（米ドル） / Existing CSV (USD)")) -> Existing CSV (USD) | C13: =IF('入力 Inputs'!$F$1="English","Existing Gain (USD)",IF('入力 Inputs'!$F$1="日本語","既存利益（米ドル）","既存利益（米ドル） / Existing Gain (USD)")) -> Existing Gain (USD) | D13: =IF('入力 Inputs'!$F$1="English","Tax w/o PPVA (USD)",IF('入力 Inputs'!$F$1="日本語","PPVAなし税金（米ドル）","PPVAなし税金（米ドル） / Tax w/o PPVA (USD)")) -> Tax w/o PPVA (USD) | E13: =IF('入力 Inputs'!$F$1="English","PPVA Fund Value",IF('入力 Inputs'!$F$1="日本語","PPVAファンド価値","PPVAファンド価値 / PPVA Fund Value")) -> PPVA Fund Value | F13: =IF('入力 Inputs'!$F$1="English","PPVA Surrender Value",IF('入力 Inputs'!$F$1="日本語","PPVA解約返戻金","PPVA解約返戻金 / PPVA Surrender Value")) -> PPVA Surrender Value | G13: =IF('入力 Inputs'!$F$1="English","Combined CSV (JPY)",IF('入力 Inputs'!$F$1="日本語","合算CSV（円）","合算CSV（円） / Combined CSV (JPY)")) -> Combined CSV (JPY) | H13: =IF('入力 Inputs'!$F$1="English","Combined Gain (JPY)",IF('入力 Inputs'!$F$1="日本語","合算利益（円）","合算利益（円） / Combined Gain (JPY)")) -> Combined Gain (JPY) | I13: =IF('入力 Inputs'!$F$1="English","Tax w/ PPVA (USD)",IF('入力 Inputs'!$F$1="日本語","PPVAあり税金（米ドル）","PPVAあり税金（米ドル） / Tax w/ PPVA (USD)")) -> Tax w/ PPVA (USD) | J13: =IF('入力 Inputs'!$F$1="English","Design B Fund Value",IF('入力 Inputs'!$F$1="日本語","デザインBファンド価値","デザインBファンド価値 / Design B Fund Value")) -> Design B Fund Value | K13: =IF('入力 Inputs'!$F$1="English","Design B Surrender Value",IF('入力 Inputs'!$F$1="日本語","デザインB解約返戻金","デザインB解約返戻金 / Design B Surrender Value")) -> Design B Surrender Value | L13: =IF('入力 Inputs'!$F$1="English","Tax w/ Design B (USD)",IF('入力 Inputs'!$F$1="日本語","デザインB税金（米ドル）","デザインB税金（米ドル） / Tax w/ Design B (USD)")) -> Tax w/ Design B (USD)
A14: 1 | B14: ='入力 Inputs'!$B$60*(1+'入力 Inputs'!$B$65)^A14 -> 20100892 | C14: =B14-'入力 Inputs'!$B$61 -> 3905216.4 | D14: =MAX(C14,0)*'入力 Inputs'!$B$66 -> 2147869 | E14: ='キャリア Carrier Illust.'!D5 -> 12826532 | F14: ='キャリア Carrier Illust.'!E5 -> 641326.62 | G14: =B14*'入力 Inputs'!$B$64+F14*'入力 Inputs'!$B$64 -> 3.318755e+09 | H14: =G14-('入力 Inputs'!$B$67+'入力 Inputs'!$B$7*'入力 Inputs'!$B$64) -> -5.4276932e+08 | I14: =MAX(H14,0)*'入力 Inputs'!$B$66/'入力 Inputs'!$B$64 -> 0 | J14: =('入力 Inputs'!B87-'入力 Inputs'!B87*'入力 Inputs'!$B$41-'入力 Inputs'!$B$57)*(1+'入力 Inputs'!$B$95) -> 12735692 | K14: {=IF(A14<=10,J14*(1-INDEX('入力 Inputs'!$B$97:$B$106,A14)),J14)} -> 0 | L14: =MAX((B14*'入力 Inputs'!$B$64+K14*'入力 Inputs'!$B$64)-('入力 Inputs'!$B$67+'入力 Inputs'!$B$7*'入力 Inputs'!$B$64),0)*'入力 Inputs'!$B$66/'入力 Inputs'!$B$64 -> 0
A15: 2 | B15: ='入力 Inputs'!$B$60*(1+'入力 Inputs'!$B$65)^A15 -> 21306946 | C15: =B15-'入力 Inputs'!$B$61 -> 5111269.9 | D15: =MAX(C15,0)*'入力 Inputs'!$B$66 -> 2811198.4 | E15: ='キャリア Carrier Illust.'!D6 -> 13607939 | F15: ='キャリア Carrier Illust.'!E6 -> 1360793.9 | G15: =B15*'入力 Inputs'!$B$64+F15*'入力 Inputs'!$B$64 -> 3.6268384e+09 | H15: =G15-('入力 Inputs'!$B$67+'入力 Inputs'!$B$7*'入力 Inputs'!$B$64) -> -2.34686e+08 | I15: =MAX(H15,0)*'入力 Inputs'!$B$66/'入力 Inputs'!$B$64 -> 0 | J15: =(J14-J14*'入力 Inputs'!$B$41)*(1+'入力 Inputs'!$B$95) -> 13416001 | K15: {=IF(A15<=10,J15*(1-INDEX('入力 Inputs'!$B$97:$B$106,A15)),J15)} -> 8049600.8 | L15: =MAX((B15*'入力 Inputs'!$B$64+K15*'入力 Inputs'!$B$64)-('入力 Inputs'!$B$67+'入力 Inputs'!$B$7*'入力 Inputs'!$B$64),0)*'入力 Inputs'!$B$66/'入力 Inputs'!$B$64 -> 2872110.7
A16: 3 | B16: ='入力 Inputs'!$B$60*(1+'入力 Inputs'!$B$65)^A16 -> 22585363 | C16: =B16-'入力 Inputs'!$B$61 -> 6389686.7 | D16: =MAX(C16,0)*'入力 Inputs'!$B$66 -> 3514327.7 | E16: ='キャリア Carrier Illust.'!D7 -> 14436953 | F16: ='キャリア Carrier Illust.'!E7 -> 2887390.7 | G16: =B16*'入力 Inputs'!$B$64+F16*'入力 Inputs'!$B$64 -> 4.0756405e+09 | H16: =G16-('入力 Inputs'!$B$67+'入力 Inputs'!$B$7*'入力 Inputs'!$B$64) -> 2.1411617e+08 | I16: =MAX(H16,0)*'入力 Inputs'!$B$66/'入力 Inputs'!$B$64 -> 736024.34 | J16: =(J15-J15*'入力 Inputs'!$B$41)*(1+'入力 Inputs'!$B$95) -> 14132651 | K16: {=IF(A16<=10,J16*(1-INDEX('入力 Inputs'!$B$97:$B$106,A16)),J16)} -> 11306120 | L16: =MAX((B16*'入力 Inputs'!$B$64+K16*'入力 Inputs'!$B$64)-('入力 Inputs'!$B$67+'入力 Inputs'!$B$7*'入力 Inputs'!$B$64),0)*'入力 Inputs'!$B$66/'入力 Inputs'!$B$64 -> 5366325.7
A17: 4 | B17: ='入力 Inputs'!$B$60*(1+'入力 Inputs'!$B$65)^A17 -> 23940484 | C17: =B17-'入力 Inputs'!$B$61 -> 7744808.4 | D17: =MAX(C17,0)*'入力 Inputs'!$B$66 -> 4259644.6 | E17: ='キャリア Carrier Illust.'!D8 -> 15316477 | F17: ='キャリア Carrier Illust.'!E8 -> 4594943 | G17: =B17*'入力 Inputs'!$B$64+F17*'入力 Inputs'!$B$64 -> 4.5656684e+09 | H17: =G17-('入力 Inputs'!$B$67+'入力 Inputs'!$B$7*'入力 Inputs'!$B$64) -> 7.0414403e+08 | I17: =MAX(H17,0)*'入力 Inputs'!$B$66/'入力 Inputs'!$B$64 -> 2420495.1 | J17: =(J16-J16*'入力 Inputs'!$B$41)*(1+'入力 Inputs'!$B$95) -> 14887581 | K17: {=IF(A17<=10,J17*(1-INDEX('入力 Inputs'!$B$97:$B$106,A17)),J17)} -> 13398823 | L17: =MAX((B17*'入力 Inputs'!$B$64+K17*'入力 Inputs'!$B$64)-('入力 Inputs'!$B$67+'入力 Inputs'!$B$7*'入力 Inputs'!$B$64),0)*'入力 Inputs'!$B$66/'入力 Inputs'!$B$64 -> 7262629.3
A18: 5 | B18: ='入力 Inputs'!$B$60*(1+'入力 Inputs'!$B$65)^A18 -> 25376913 | C18: =B18-'入力 Inputs'!$B$61 -> 9181237.5 | D18: =MAX(C18,0)*'入力 Inputs'!$B$66 -> 5049680.6 | E18: ='キャリア Carrier Illust.'!D9 -> 16249586 | F18: ='キャリア Carrier Illust.'!E9 -> 6499834.6 | G18: =B18*'入力 Inputs'!$B$64+F18*'入力 Inputs'!$B$64 -> 5.1002797e+09 | H18: =G18-('入力 Inputs'!$B$67+'入力 Inputs'!$B$7*'入力 Inputs'!$B$64) -> 1.2387553e+09 | I18: =MAX(H18,0)*'入力 Inputs'!$B$66/'入力 Inputs'!$B$64 -> 4258221.4 | J18: =(J17-J17*'入力 Inputs'!$B$41)*(1+'入力 Inputs'!$B$95) -> 15682839 | K18: {=IF(A18<=10,J18*(1-INDEX('入力 Inputs'!$B$97:$B$106,A18)),J18)} -> 14898697 | L18: =MAX((B18*'入力 Inputs'!$B$64+K18*'入力 Inputs'!$B$64)-('入力 Inputs'!$B$67+'入力 Inputs'!$B$7*'入力 Inputs'!$B$64),0)*'入力 Inputs'!$B$66/'入力 Inputs'!$B$64 -> 8877595.7
A19: 6 | B19: ='入力 Inputs'!$B$60*(1+'入力 Inputs'!$B$65)^A19 -> 26899528 | C19: =B19-'入力 Inputs'!$B$61 -> 10703852 | D19: =MAX(C19,0)*'入力 Inputs'!$B$66 -> 5887118.8 | E19: ='キャリア Carrier Illust.'!D10 -> 17239547 | F19: ='キャリア Carrier Illust.'!E10 -> 17239547 | G19: =B19*'入力 Inputs'!$B$64+F19*'入力 Inputs'!$B$64 -> 7.0622521e+09 | H19: =G19-('入力 Inputs'!$B$67+'入力 Inputs'!$B$7*'入力 Inputs'!$B$64) -> 3.2007278e+09 | I19: =MAX(H19,0)*'入力 Inputs'!$B$66/'入力 Inputs'!$B$64 -> 11002502 | J19: =(J18-J18*'入力 Inputs'!$B$41)*(1+'入力 Inputs'!$B$95) -> 16520577 | K19: {=IF(A19<=10,J19*(1-INDEX('入力 Inputs'!$B$97:$B$106,A19)),J19)} -> 16520577 | L19: =MAX((B19*'入力 Inputs'!$B$64+K19*'入力 Inputs'!$B$64)-('入力 Inputs'!$B$67+'入力 Inputs'!$B$7*'入力 Inputs'!$B$64),0)*'入力 Inputs'!$B$66/'入力 Inputs'!$B$64 -> 10607068
A20: 7 | B20: ='入力 Inputs'!$B$60*(1+'入力 Inputs'!$B$65)^A20 -> 28513500 | C20: =B20-'入力 Inputs'!$B$61 -> 12317824 | D20: =MAX(C20,0)*'入力 Inputs'!$B$66 -> 6774803.2 | E20: ='キャリア Carrier Illust.'!D11 -> 18289823 | F20: ='キャリア Carrier Illust.'!E11 -> 18289823 | G20: =B20*'入力 Inputs'!$B$64+F20*'入力 Inputs'!$B$64 -> 7.4885318e+09 | H20: =G20-('入力 Inputs'!$B$67+'入力 Inputs'!$B$7*'入力 Inputs'!$B$64) -> 3.6270074e+09 | I20: =MAX(H20,0)*'入力 Inputs'!$B$66/'入力 Inputs'!$B$64 -> 12467838 | J20: =(J19-J19*'入力 Inputs'!$B$41)*(1+'入力 Inputs'!$B$95) -> 17403065 | K20: {=IF(A20<=10,J20*(1-INDEX('入力 Inputs'!$B$97:$B$106,A20)),J20)} -> 17403065 | L20: =MAX((B20*'入力 Inputs'!$B$64+K20*'入力 Inputs'!$B$64)-('入力 Inputs'!$B$67+'入力 Inputs'!$B$7*'入力 Inputs'!$B$64),0)*'入力 Inputs'!$B$66/'入力 Inputs'!$B$64 -> 11980121
A21: 8 | B21: ='入力 Inputs'!$B$60*(1+'入力 Inputs'!$B$65)^A21 -> 30224310 | C21: =B21-'入力 Inputs'!$B$61 -> 14028634 | D21: =MAX(C21,0)*'入力 Inputs'!$B$66 -> 7715748.7 | E21: ='キャリア Carrier Illust.'!D12 -> 19404090 | F21: ='キャリア Carrier Illust.'!E12 -> 19404090 | G21: =B21*'入力 Inputs'!$B$64+F21*'入力 Inputs'!$B$64 -> 7.9405439e+09 | H21: =G21-('入力 Inputs'!$B$67+'入力 Inputs'!$B$7*'入力 Inputs'!$B$64) -> 4.0790196e+09 | I21: =MAX(H21,0)*'入力 Inputs'!$B$66/'入力 Inputs'!$B$64 -> 14021630 | J21: =(J20-J20*'入力 Inputs'!$B$41)*(1+'入力 Inputs'!$B$95) -> 18332693 | K21: {=IF(A21<=10,J21*(1-INDEX('入力 Inputs'!$B$97:$B$106,A21)),J21)} -> 18332693 | L21: =MAX((B21*'入力 Inputs'!$B$64+K21*'入力 Inputs'!$B$64)-('入力 Inputs'!$B$67+'入力 Inputs'!$B$7*'入力 Inputs'!$B$64),0)*'入力 Inputs'!$B$66/'入力 Inputs'!$B$64 -> 13432362
A22: 9 | B22: ='入力 Inputs'!$B$60*(1+'入力 Inputs'!$B$65)^A22 -> 32037769 | C22: =B22-'入力 Inputs'!$B$61 -> 15842093 | D22: =MAX(C22,0)*'入力 Inputs'!$B$66 -> 8713150.9 | E22: ='キャリア Carrier Illust.'!D13 -> 20586245 | F22: ='キャリア Carrier Illust.'!E13 -> 20586245 | G22: =B22*'入力 Inputs'!$B$64+F22*'入力 Inputs'!$B$64 -> 8.4198421e+09 | H22: =G22-('入力 Inputs'!$B$67+'入力 Inputs'!$B$7*'入力 Inputs'!$B$64) -> 4.5583178e+09 | I22: =MAX(H22,0)*'入力 Inputs'!$B$66/'入力 Inputs'!$B$64 -> 15669217 | J22: =(J21-J21*'入力 Inputs'!$B$41)*(1+'入力 Inputs'!$B$95) -> 19311980 | K22: {=IF(A22<=10,J22*(1-INDEX('入力 Inputs'!$B$97:$B$106,A22)),J22)} -> 19311980 | L22: =MAX((B22*'入力 Inputs'!$B$64+K22*'入力 Inputs'!$B$64)-('入力 Inputs'!$B$67+'入力 Inputs'!$B$7*'入力 Inputs'!$B$64),0)*'入力 Inputs'!$B$66/'入力 Inputs'!$B$64 -> 14968372
A23: 10 | B23: ='入力 Inputs'!$B$60*(1+'入力 Inputs'!$B$65)^A23 -> 33960035 | C23: =B23-'入力 Inputs'!$B$61 -> 17764359 | D23: =MAX(C23,0)*'入力 Inputs'!$B$66 -> 9770397.3 | E23: ='キャリア Carrier Illust.'!D14 -> 21840425 | F23: ='キャリア Carrier Illust.'!E14 -> 21840425 | G23: =B23*'入力 Inputs'!$B$64+F23*'入力 Inputs'!$B$64 -> 8.9280736e+09 | H23: =G23-('入力 Inputs'!$B$67+'入力 Inputs'!$B$7*'入力 Inputs'!$B$64) -> 5.0665492e+09 | I23: =MAX(H23,0)*'入力 Inputs'!$B$66/'入力 Inputs'!$B$64 -> 17416263 | J23: =(J22-J22*'入力 Inputs'!$B$41)*(1+'入力 Inputs'!$B$95) -> 20343577 | K23: {=IF(A23<=10,J23*(1-INDEX('入力 Inputs'!$B$97:$B$106,A23)),J23)} -> 20343577 | L23: =MAX((B23*'入力 Inputs'!$B$64+K23*'入力 Inputs'!$B$64)-('入力 Inputs'!$B$67+'入力 Inputs'!$B$7*'入力 Inputs'!$B$64),0)*'入力 Inputs'!$B$66/'入力 Inputs'!$B$64 -> 16592997
A25: =IF('入力 Inputs'!$F$1="English","TAX SAVINGS SUMMARY",IF('入力 Inputs'!$F$1="日本語","税金節約概要","税金節約概要 / TAX SAVINGS SUMMARY")) -> TAX SAVINGS SUMMARY
B26: =IF('入力 Inputs'!$F$1="English","Without PPVA",IF('入力 Inputs'!$F$1="日本語","PPVAなし","PPVAなし / Without PPVA")) -> Without PPVA | C26: =IF('入力 Inputs'!$F$1="English","With PPVA",IF('入力 Inputs'!$F$1="日本語","PPVAあり","PPVAあり / With PPVA")) -> With PPVA | D26: =IF('入力 Inputs'!$F$1="English","Tax Savings",IF('入力 Inputs'!$F$1="日本語","税金節約額","税金節約額 / Tax Savings")) -> Tax Savings | E26: =IF('入力 Inputs'!$F$1="English","Tax w/ Design B",IF('入力 Inputs'!$F$1="日本語","デザインB税金","デザインB税金 / Tax w/ Design B")) -> Tax w/ Design B
A27: =IF('入力 Inputs'!$F$1="English","Year 1 Tax Impact",IF('入力 Inputs'!$F$1="日本語","1年目税金への影響","1年目税金への影響 / Year 1 Tax Impact")) -> Year 1 Tax Impact | B27: =D14 -> 2147869 | C27: =I14 -> 0 | D27: =B27-C27 -> 2147869 | E27: =L14 -> 0
A28: =IF('入力 Inputs'!$F$1="English","Year 3 Tax Impact",IF('入力 Inputs'!$F$1="日本語","3年目税金への影響","3年目税金への影響 / Year 3 Tax Impact")) -> Year 3 Tax Impact | B28: =D16 -> 3514327.7 | C28: =I16 -> 736024.34 | D28: =B28-C28 -> 2778303.3 | E28: =L16 -> 5366325.7
A29: =IF('入力 Inputs'!$F$1="English","Year 5 Tax Impact",IF('入力 Inputs'!$F$1="日本語","5年目税金への影響","5年目税金への影響 / Year 5 Tax Impact")) -> Year 5 Tax Impact | B29: =D18 -> 5049680.6 | C29: =I18 -> 4258221.4 | D29: =B29-C29 -> 791459.17 | E29: =L18 -> 8877595.7
A30: =IF('入力 Inputs'!$F$1="English","Year 10 Tax Impact",IF('入力 Inputs'!$F$1="日本語","10年目税金への影響","10年目税金への影響 / Year 10 Tax Impact")) -> Year 10 Tax Impact | B30: =D23 -> 9770397.3 | C30: =I23 -> 17416263 | D30: =B30-C30 -> -7645865.7 | E30: =L23 -> 16592997
A32: =IF('入力 Inputs'!$F$1="English","Year",IF('入力 Inputs'!$F$1="日本語","年","年 / Year")) -> Year | B32: =IF('入力 Inputs'!$F$1="English","Tax w/o PPVA",IF('入力 Inputs'!$F$1="日本語","PPVAなし税金","PPVAなし税金 / Tax w/o PPVA")) -> Tax w/o PPVA | C32: =IF('入力 Inputs'!$F$1="English","Tax w/ PPVA",IF('入力 Inputs'!$F$1="日本語","PPVAあり税金","PPVAあり税金 / Tax w/ PPVA")) -> Tax w/ PPVA | D32: =IF('入力 Inputs'!$F$1="English","Tax w/ Design B",IF('入力 Inputs'!$F$1="日本語","デザインB税金","デザインB税金 / Tax w/ Design B")) -> Tax w/ Design B
A33: =A14 -> 1 | B33: =D14 -> 2147869 | C33: =I14 -> 0 | D33: =L14 -> 0
A34: =A15 -> 2 | B34: =D15 -> 2811198.4 | C34: =I15 -> 0 | D34: =L15 -> 2872110.7
A35: =A16 -> 3 | B35: =D16 -> 3514327.7 | C35: =I16 -> 736024.34 | D35: =L16 -> 5366325.7
A36: =A17 -> 4 | B36: =D17 -> 4259644.6 | C36: =I17 -> 2420495.1 | D36: =L17 -> 7262629.3
A37: =A18 -> 5 | B37: =D18 -> 5049680.6 | C37: =I18 -> 4258221.4 | D37: =L18 -> 8877595.7
A38: =A19 -> 6 | B38: =D19 -> 5887118.8 | C38: =I19 -> 11002502 | D38: =L19 -> 10607068
A39: =A20 -> 7 | B39: =D20 -> 6774803.2 | C39: =I20 -> 12467838 | D39: =L20 -> 11980121
A40: =A21 -> 8 | B40: =D21 -> 7715748.7 | C40: =I21 -> 14021630 | D40: =L21 -> 13432362
A41: =A22 -> 9 | B41: =D22 -> 8713150.9 | C41: =I22 -> 15669217 | D41: =L22 -> 14968372
A42: =A23 -> 10 | B42: =D23 -> 9770397.3 | C42: =I23 -> 17416263 | D42: =L23 -> 16592997
A45: =IF('入力 Inputs'!$F$1="English","SENSITIVITY: Year 5 Tax Savings (USD)",IF('入力 Inputs'!$F$1="日本語","感度分析：5年目税金節約額（米ドル）","感度分析：5年目税金節約額（米ドル） / SENSITIVITY: Year 5 Tax Savings (USD)")) -> SENSITIVITY: Year 5 Tax Savings (USD)
A46: =IF('入力 Inputs'!$F$1="English","FX Dissolution / CSV Growth",IF('入力 Inputs'!$F$1="日本語","FX解散率 / CSV成長率","FX解散率 / CSV成長率 / FX Dissolution / CSV Growth")) -> FX Dissolution / CSV Growth | B46: 0.04 | C46: 0.05 | D46: 0.06 | E46: 0.07 | F46: 0.08
A47: 130 | B47: =MAX('入力 Inputs'!B60*(1+B$46)^5-'入力 Inputs'!B61,0)*'入力 Inputs'!B66-MAX(('入力 Inputs'!B60*(1+B$46)^5*$A47+'キャリア Carrier Illust.'!E9*$A47)-('入力 Inputs'!B67+'入力 Inputs'!B7*$A47),0)*'入力 Inputs'!B66/$A47 -> 2204687.6 | C47: =MAX('入力 Inputs'!B60*(1+C$46)^5-'入力 Inputs'!B61,0)*'入力 Inputs'!B66-MAX(('入力 Inputs'!B60*(1+C$46)^5*$A47+'キャリア Carrier Illust.'!E9*$A47)-('入力 Inputs'!B67+'入力 Inputs'!B7*$A47),0)*'入力 Inputs'!B66/$A47 -> 2204687.6 | D47: =MAX('入力 Inputs'!B60*(1+D$46)^5-'入力 Inputs'!B61,0)*'入力 Inputs'!B66-MAX(('入力 Inputs'!B60*(1+D$46)^5*$A47+'キャリア Carrier Illust.'!E9*$A47)-('入力 Inputs'!B67+'入力 Inputs'!B7*$A47),0)*'入力 Inputs'!B66/$A47 -> 2204687.6 | E47: =MAX('入力 Inputs'!B60*(1+E$46)^5-'入力 Inputs'!B61,0)*'入力 Inputs'!B66-MAX(('入力 Inputs'!B60*(1+E$46)^5*$A47+'キャリア Carrier Illust.'!E9*$A47)-('入力 Inputs'!B67+'入力 Inputs'!B7*$A47),0)*'入力 Inputs'!B66/$A47 -> 2204687.6 | F47: =MAX('入力 Inputs'!B60*(1+F$46)^5-'入力 Inputs'!B61,0)*'入力 Inputs'!B66-MAX(('入力 Inputs'!B60*(1+F$46)^5*$A47+'キャリア Carrier Illust.'!E9*$A47)-('入力 Inputs'!B67+'入力 Inputs'!B7*$A47),0)*'入力 Inputs'!B66/$A47 -> 2204687.6
A48: 140 | B48: =MAX('入力 Inputs'!B60*(1+B$46)^5-'入力 Inputs'!B61,0)*'入力 Inputs'!B66-MAX(('入力 Inputs'!B60*(1+B$46)^5*$A48+'キャリア Carrier Illust.'!E9*$A48)-('入力 Inputs'!B67+'入力 Inputs'!B7*$A48),0)*'入力 Inputs'!B66/$A48 -> 1666314.9 | C48: =MAX('入力 Inputs'!B60*(1+C$46)^5-'入力 Inputs'!B61,0)*'入力 Inputs'!B66-MAX(('入力 Inputs'!B60*(1+C$46)^5*$A48+'キャリア Carrier Illust.'!E9*$A48)-('入力 Inputs'!B67+'入力 Inputs'!B7*$A48),0)*'入力 Inputs'!B66/$A48 -> 1666314.9 | D48: =MAX('入力 Inputs'!B60*(1+D$46)^5-'入力 Inputs'!B61,0)*'入力 Inputs'!B66-MAX(('入力 Inputs'!B60*(1+D$46)^5*$A48+'キャリア Carrier Illust.'!E9*$A48)-('入力 Inputs'!B67+'入力 Inputs'!B7*$A48),0)*'入力 Inputs'!B66/$A48 -> 1666314.9 | E48: =MAX('入力 Inputs'!B60*(1+E$46)^5-'入力 Inputs'!B61,0)*'入力 Inputs'!B66-MAX(('入力 Inputs'!B60*(1+E$46)^5*$A48+'キャリア Carrier Illust.'!E9*$A48)-('入力 Inputs'!B67+'入力 Inputs'!B7*$A48),0)*'入力 Inputs'!B66/$A48 -> 1666314.9 | F48: =MAX('入力 Inputs'!B60*(1+F$46)^5-'入力 Inputs'!B61,0)*'入力 Inputs'!B66-MAX(('入力 Inputs'!B60*(1+F$46)^5*$A48+'キャリア Carrier Illust.'!E9*$A48)-('入力 Inputs'!B67+'入力 Inputs'!B7*$A48),0)*'入力 Inputs'!B66/$A48 -> 1666314.9
A49: 150 | B49: =MAX('入力 Inputs'!B60*(1+B$46)^5-'入力 Inputs'!B61,0)*'入力 Inputs'!B66-MAX(('入力 Inputs'!B60*(1+B$46)^5*$A49+'キャリア Carrier Illust.'!E9*$A49)-('入力 Inputs'!B67+'入力 Inputs'!B7*$A49),0)*'入力 Inputs'!B66/$A49 -> 1199725.2 | C49: =MAX('入力 Inputs'!B60*(1+C$46)^5-'入力 Inputs'!B61,0)*'入力 Inputs'!B66-MAX(('入力 Inputs'!B60*(1+C$46)^5*$A49+'キャリア Carrier Illust.'!E9*$A49)-('入力 Inputs'!B67+'入力 Inputs'!B7*$A49),0)*'入力 Inputs'!B66/$A49 -> 1199725.2 | D49: =MAX('入力 Inputs'!B60*(1+D$46)^5-'入力 Inputs'!B61,0)*'入力 Inputs'!B66-MAX(('入力 Inputs'!B60*(1+D$46)^5*$A49+'キャリア Carrier Illust.'!E9*$A49)-('入力 Inputs'!B67+'入力 Inputs'!B7*$A49),0)*'入力 Inputs'!B66/$A49 -> 1199725.2 | E49: =MAX('入力 Inputs'!B60*(1+E$46)^5-'入力 Inputs'!B61,0)*'入力 Inputs'!B66-MAX(('入力 Inputs'!B60*(1+E$46)^5*$A49+'キャリア Carrier Illust.'!E9*$A49)-('入力 Inputs'!B67+'入力 Inputs'!B7*$A49),0)*'入力 Inputs'!B66/$A49 -> 1199725.2 | F49: =MAX('入力 Inputs'!B60*(1+F$46)^5-'入力 Inputs'!B61,0)*'入力 Inputs'!B66-MAX(('入力 Inputs'!B60*(1+F$46)^5*$A49+'キャリア Carrier Illust.'!E9*$A49)-('入力 Inputs'!B67+'入力 Inputs'!B7*$A49),0)*'入力 Inputs'!B66/$A49 -> 1199725.2
A50: 160 | B50: =MAX('入力 Inputs'!B60*(1+B$46)^5-'入力 Inputs'!B61,0)*'入力 Inputs'!B66-MAX(('入力 Inputs'!B60*(1+B$46)^5*$A50+'キャリア Carrier Illust.'!E9*$A50)-('入力 Inputs'!B67+'入力 Inputs'!B7*$A50),0)*'入力 Inputs'!B66/$A50 -> 791459.17 | C50: =MAX('入力 Inputs'!B60*(1+C$46)^5-'入力 Inputs'!B61,0)*'入力 Inputs'!B66-MAX(('入力 Inputs'!B60*(1+C$46)^5*$A50+'キャリア Carrier Illust.'!E9*$A50)-('入力 Inputs'!B67+'入力 Inputs'!B7*$A50),0)*'入力 Inputs'!B66/$A50 -> 791459.17 | D50: =MAX('入力 Inputs'!B60*(1+D$46)^5-'入力 Inputs'!B61,0)*'入力 Inputs'!B66-MAX(('入力 Inputs'!B60*(1+D$46)^5*$A50+'キャリア Carrier Illust.'!E9*$A50)-('入力 Inputs'!B67+'入力 Inputs'!B7*$A50),0)*'入力 Inputs'!B66/$A50 -> 791459.17 | E50: =MAX('入力 Inputs'!B60*(1+E$46)^5-'入力 Inputs'!B61,0)*'入力 Inputs'!B66-MAX(('入力 Inputs'!B60*(1+E$46)^5*$A50+'キャリア Carrier Illust.'!E9*$A50)-('入力 Inputs'!B67+'入力 Inputs'!B7*$A50),0)*'入力 Inputs'!B66/$A50 -> 791459.17 | F50: =MAX('入力 Inputs'!B60*(1+F$46)^5-'入力 Inputs'!B61,0)*'入力 Inputs'!B66-MAX(('入力 Inputs'!B60*(1+F$46)^5*$A50+'キャリア Carrier Illust.'!E9*$A50)-('入力 Inputs'!B67+'入力 Inputs'!B7*$A50),0)*'入力 Inputs'!B66/$A50 -> 791459.17
A51: 170 | B51: =MAX('入力 Inputs'!B60*(1+B$46)^5-'入力 Inputs'!B61,0)*'入力 Inputs'!B66-MAX(('入力 Inputs'!B60*(1+B$46)^5*$A51+'キャリア Carrier Illust.'!E9*$A51)-('入力 Inputs'!B67+'入力 Inputs'!B7*$A51),0)*'入力 Inputs'!B66/$A51 -> 431224.46 | C51: =MAX('入力 Inputs'!B60*(1+C$46)^5-'入力 Inputs'!B61,0)*'入力 Inputs'!B66-MAX(('入力 Inputs'!B60*(1+C$46)^5*$A51+'キャリア Carrier Illust.'!E9*$A51)-('入力 Inputs'!B67+'入力 Inputs'!B7*$A51),0)*'入力 Inputs'!B66/$A51 -> 431224.46 | D51: =MAX('入力 Inputs'!B60*(1+D$46)^5-'入力 Inputs'!B61,0)*'入力 Inputs'!B66-MAX(('入力 Inputs'!B60*(1+D$46)^5*$A51+'キャリア Carrier Illust.'!E9*$A51)-('入力 Inputs'!B67+'入力 Inputs'!B7*$A51),0)*'入力 Inputs'!B66/$A51 -> 431224.46 | E51: =MAX('入力 Inputs'!B60*(1+E$46)^5-'入力 Inputs'!B61,0)*'入力 Inputs'!B66-MAX(('入力 Inputs'!B60*(1+E$46)^5*$A51+'キャリア Carrier Illust.'!E9*$A51)-('入力 Inputs'!B67+'入力 Inputs'!B7*$A51),0)*'入力 Inputs'!B66/$A51 -> 431224.46 | F51: =MAX('入力 Inputs'!B60*(1+F$46)^5-'入力 Inputs'!B61,0)*'入力 Inputs'!B66-MAX(('入力 Inputs'!B60*(1+F$46)^5*$A51+'キャリア Carrier Illust.'!E9*$A51)-('入力 Inputs'!B67+'入力 Inputs'!B7*$A51),0)*'入力 Inputs'!B66/$A51 -> 431224.46

Sheet 既存ポートフォリオ Existing
A1: =IF('入力 Inputs'!$F$1="English","EXISTING INSURANCE PORTFOLIO SUMMARY",IF('入力 Inputs'!$F$1="日本語","既存保険ポートフォリオ概要","既存保険ポートフォリオ概要 / EXISTING INSURANCE PORTFOLIO SUMMARY")) -> EXISTING INSURANCE PORTFOLIO SUMMARY
A2: =IF('入力 Inputs'!$F$1="English","Takata family existing policies — for reference",IF('入力 Inputs'!$F$1="日本語","高田家の現行保険証券 — 参照用","高田家の現行保険証券 — 参照用 / Takata family existing policies — for reference")) -> Takata family existing policies — for reference
A4: =IF('入力 Inputs'!$F$1="English","Carrier",IF('入力 Inputs'!$F$1="日本語","キャリア","キャリア / Carrier")) -> Carrier | B4: =IF('入力 Inputs'!$F$1="English","Policy Number",IF('入力 Inputs'!$F$1="日本語","証券番号","証券番号 / Policy Number")) -> Policy Number | C4: =IF('入力 Inputs'!$F$1="English","Issue Date",IF('入力 Inputs'!$F$1="日本語","発行日","発行日 / Issue Date")) -> Issue Date | D4: =IF('入力 Inputs'!$F$1="English","Death Benefit",IF('入力 Inputs'!$F$1="日本語","死亡保険金","死亡保険金 / Death Benefit")) -> Death Benefit | E4: =IF('入力 Inputs'!$F$1="English","Total Premium",IF('入力 Inputs'!$F$1="日本語","支払保険料合計","支払保険料合計 / Total Premium")) -> Total Premium | F4: =IF('入力 Inputs'!$F$1="English","Type",IF('入力 Inputs'!$F$1="日本語","種類","種類 / Type")) -> Type
A5: Pan American | B5: 9201157340 | C5: 43166 | D5: 10000000 | E5: 3320000 | F5: PPLI/PPVA
A6: Pacific Life | B6: VF53293100 | C6: 43293 | D6: 33500000 | E6: 7000000 | F6: VUL
A7: Global Atlantic / Accordia | B7: UL00035275 | C7: 43350 | D7: 10000000 | E7: 1350000 | F7: UL
A8: Lincoln | B8: VUL1035292 | C8: 44813 | D8: 20000000 | E8: 3889368 | F8: VUL
A9: Lincoln | B9: 4922053 | C9: 43587 | D9: 10000000 | E9: 1300308 | F9: VUL
A10: =IF('入力 Inputs'!$F$1="English","TOTAL",IF('入力 Inputs'!$F$1="日本語","合計","合計 / TOTAL")) -> TOTAL | D10: =SUM(D5:D9) -> 83500000 | E10: =SUM(E5:E9) -> 16859676
A12: =IF('入力 Inputs'!$F$1="English","KEY METRICS",IF('入力 Inputs'!$F$1="日本語","主要指標","主要指標 / KEY METRICS")) -> KEY METRICS
A13: =IF('入力 Inputs'!$F$1="English","Total Death Benefit",IF('入力 Inputs'!$F$1="日本語","死亡保険金合計","死亡保険金合計 / Total Death Benefit")) -> Total Death Benefit | B13: =D10 -> 83500000
A14: =IF('入力 Inputs'!$F$1="English","Total Premiums Paid",IF('入力 Inputs'!$F$1="日本語","保険料合計","保険料合計 / Total Premiums Paid")) -> Total Premiums Paid | B14: =E10 -> 16859676
A15: =IF('入力 Inputs'!$F$1="English","Premium-to-DB Ratio",IF('入力 Inputs'!$F$1="日本語","保険料対DB比率","保険料対DB比率 / Premium-to-DB Ratio")) -> Premium-to-DB Ratio | B15: =D10/E10 -> 4.9526456
A16: =IF('入力 Inputs'!$F$1="English","Current CSV (USD)",IF('入力 Inputs'!$F$1="日本語","現行CSV（米ドル）","現行CSV（米ドル） / Current CSV (USD)")) -> Current CSV (USD) | B16: ='入力 Inputs'!B60 -> 18963106
A17: =IF('入力 Inputs'!$F$1="English","Basis (USD)",IF('入力 Inputs'!$F$1="日本語","基準額（米ドル）","基準額（米ドル） / Basis (USD)")) -> Basis (USD) | B17: ='入力 Inputs'!B61 -> 16195676
A18: =IF('入力 Inputs'!$F$1="English","Unrealized Gain",IF('入力 Inputs'!$F$1="日本語","未実現利益","未実現利益 / Unrealized Gain")) -> Unrealized Gain | B18: =B16-B17 -> 2767430
A19: =IF('入力 Inputs'!$F$1="English","Number of Policies (4 are MECs)",IF('入力 Inputs'!$F$1="日本語","証券数（4つはMEC）","証券数（4つはMEC） / Number of Policies (4 are MECs)")) -> Number of Policies (4 are MECs) | B19: 5 (4 MECs)
A21: =IF('入力 Inputs'!$F$1="English","LLC Dissolution Date",IF('入力 Inputs'!$F$1="日本語","LLC解散日","LLC解散日 / LLC Dissolution Date")) -> LLC Dissolution Date | B21: 46023
A22: =IF('入力 Inputs'!$F$1="English","Trust Creation Date",IF('入力 Inputs'!$F$1="日本語","信託設立日","信託設立日 / Trust Creation Date")) -> Trust Creation Date | B22: 46030

Sheet サマリー Summary
A1: =IF('入力 Inputs'!$F$1="English","EXECUTIVE SUMMARY",IF('入力 Inputs'!$F$1="日本語","エグゼクティブサマリー","エグゼクティブサマリー / EXECUTIVE SUMMARY")) -> EXECUTIVE SUMMARY
A2: =IF('入力 Inputs'!$F$1="English","PPVA Master Tool — Key figures at a glance (print-ready)",IF('入力 Inputs'!$F$1="日本語","PPVAマスターツール — 主要数値の概要（1ページ印刷用）","PPVAマスターツール — 主要数値の概要（1ページ印刷用） / PPVA Master Tool — Key figures at a glance (print-ready)")) -> PPVA Master Tool — Key figures at a glance (print-ready)
A4: =IF('入力 Inputs'!$F$1="English","DEAL STRUCTURE",IF('入力 Inputs'!$F$1="日本語","取引構造","取引構造 / DEAL STRUCTURE")) -> DEAL STRUCTURE
A5: =IF('入力 Inputs'!$F$1="English","Total Deposit",IF('入力 Inputs'!$F$1="日本語","預入総額","預入総額 / Total Deposit")) -> Total Deposit | B5: ='入力 Inputs'!B7 -> 13000000
A6: =IF('入力 Inputs'!$F$1="English","Net to Policy",IF('入力 Inputs'!$F$1="日本語","正味保険料","正味保険料 / Net to Policy")) -> Net to Policy | B6: ='入力 Inputs'!B87 -> 12090000
A7: =IF('入力 Inputs'!$F$1="English","Guaranteed Allocation",IF('入力 Inputs'!$F$1="日本語","保証配分率","保証配分率 / Guaranteed Allocation")) -> Guaranteed Allocation | B7: =SUM('入力 Inputs'!B25:'入力 Inputs'!B27) -> 0.75
A8: =IF('入力 Inputs'!$F$1="English","Gross Weighted Return",IF('入力 Inputs'!$F$1="日本語","加重グロスリターン","加重グロスリターン / Gross Weighted Return")) -> Gross Weighted Return | B8: ='入力 Inputs'!E32 -> 0.062525
A10: =IF('入力 Inputs'!$F$1="English","PROJECTED FUND VALUE (Base Rate)",IF('入力 Inputs'!$F$1="日本語","予測ファンド価値（基準率）","予測ファンド価値（基準率） / PROJECTED FUND VALUE (Base Rate)")) -> PROJECTED FUND VALUE (Base Rate)
A11: =IF('入力 Inputs'!$F$1="English","Year 10 Fund Value",IF('入力 Inputs'!$F$1="日本語","10年目ファンド価値","10年目ファンド価値 / Year 10 Fund Value")) -> Year 10 Fund Value | B11: ='キャリア Carrier Illust.'!D14 -> 21840425
A12: =IF('入力 Inputs'!$F$1="English","Year 10 Surrender Value",IF('入力 Inputs'!$F$1="日本語","10年目解約返戻金","10年目解約返戻金 / Year 10 Surrender Value")) -> Year 10 Surrender Value | B12: ='キャリア Carrier Illust.'!E14 -> 21840425
A13: =IF('入力 Inputs'!$F$1="English","Year 30 Fund Value",IF('入力 Inputs'!$F$1="日本語","30年目ファンド価値","30年目ファンド価値 / Year 30 Fund Value")) -> Year 30 Fund Value | B13: ='キャリア Carrier Illust.'!D34 -> 71278246
A15: =IF('入力 Inputs'!$F$1="English","TAX IMPACT",IF('入力 Inputs'!$F$1="日本語","税金への影響","税金への影響 / TAX IMPACT")) -> TAX IMPACT
A16: =IF('入力 Inputs'!$F$1="English","Year 1 Tax Savings",IF('入力 Inputs'!$F$1="日本語","1年目税金節約額","1年目税金節約額 / Year 1 Tax Savings")) -> Year 1 Tax Savings | B16: ='税金 Tax Impact'!D27 -> 2147869
A17: =IF('入力 Inputs'!$F$1="English","Year 5 Tax Savings",IF('入力 Inputs'!$F$1="日本語","5年目税金節約額","5年目税金節約額 / Year 5 Tax Savings")) -> Year 5 Tax Savings | B17: ='税金 Tax Impact'!D29 -> 791459.17
A18: =IF('入力 Inputs'!$F$1="English","Estimated Tax Event (without PPVA)",IF('入力 Inputs'!$F$1="日本語","推定税事象（PPVAなし）","推定税事象（PPVAなし） / Estimated Tax Event (without PPVA)")) -> Estimated Tax Event (without PPVA) | B18: ='税金 Tax Impact'!B8 -> 1522086.5
A20: =IF('入力 Inputs'!$F$1="English","INCOME BY PARTY",IF('入力 Inputs'!$F$1="日本語","当事者別収入","当事者別収入 / INCOME BY PARTY")) -> INCOME BY PARTY
A21: =IF('入力 Inputs'!$F$1="English","Ohana Firm (upfront)",IF('入力 Inputs'!$F$1="日本語","Ohana事務所（前払い）","Ohana事務所（前払い） / Ohana Firm (upfront)")) -> Ohana Firm (upfront) | B21: ='マスター Master'!B18 -> 351000
A22: =IF('入力 Inputs'!$F$1="English","PBWR (upfront)",IF('入力 Inputs'!$F$1="日本語","PBWR（前払い）","PBWR（前払い） / PBWR (upfront)")) -> PBWR (upfront) | B22: ='マスター Master'!B17 -> 351000
A23: =IF('入力 Inputs'!$F$1="English","RIA Year 1 Fee",IF('入力 Inputs'!$F$1="日本語","RIA 1年目手数料","RIA 1年目手数料 / RIA Year 1 Fee")) -> RIA Year 1 Fee | B23: ='マスター Master'!C21 -> 18103.5
A24: =IF('入力 Inputs'!$F$1="English","Money Manager Year 1 Fee",IF('入力 Inputs'!$F$1="日本語","マネーマネージャー1年目手数料","マネーマネージャー1年目手数料 / Money Manager Year 1 Fee")) -> Money Manager Year 1 Fee | B24: ='計算 Calculations'!D49 -> 0
A26: =IF('入力 Inputs'!$F$1="English","NET RETURN TO CLIENT",IF('入力 Inputs'!$F$1="日本語","顧客への正味リターン","顧客への正味リターン / NET RETURN TO CLIENT")) -> NET RETURN TO CLIENT
A27: =IF('入力 Inputs'!$F$1="English","Net Return (after all fees)",IF('入力 Inputs'!$F$1="日本語","正味リターン（手数料控除後）","正味リターン（手数料控除後） / Net Return (after all fees)")) -> Net Return (after all fees) | B27: ='マスター Master'!B56 -> 0.059015193
A28: =IF('入力 Inputs'!$F$1="English","Break-Even Year (Surrender Value > Deposit)",IF('入力 Inputs'!$F$1="日本語","損益分岐年（解約返戻金 > 預入額）","損益分岐年（解約返戻金 > 預入額） / Break-Even Year (Surrender Value > Deposit)")) -> Break-Even Year (Surrender Value > Deposit) | B28: ='キャリア Carrier Illust.'!B129 -> 6

Sheet マスター Master
A1: =IF('入力 Inputs'!$F$1="English","PPVA DEAL MODEL — INCOME DASHBOARD",IF('入力 Inputs'!$F$1="日本語","PPVA取引モデル — 収益ダッシュボード","PPVA取引モデル — 収益ダッシュボード / PPVA DEAL MODEL — INCOME DASHBOARD")) -> PPVA DEAL MODEL — INCOME DASHBOARD
A2: =IF('入力 Inputs'!$F$1="English","Change inputs on the Inputs tab to update all numbers and charts automatically",IF('入力 Inputs'!$F$1="日本語","インタラクティブ計算 — 入力タブで変更すると自動更新","インタラクティブ計算 — 入力タブで変更すると自動更新 / Change inputs on the Inputs tab to update all numbers and charts automatically")) -> Change inputs on the Inputs tab to update all numbers and charts automatically
A4: =IF('入力 Inputs'!$F$1="English","DEAL OVERVIEW",IF('入力 Inputs'!$F$1="日本語","取引概要","取引概要 / DEAL OVERVIEW")) -> DEAL OVERVIEW
A5: =IF('入力 Inputs'!$F$1="English","Total Deposit",IF('入力 Inputs'!$F$1="日本語","預入総額","預入総額 / Total Deposit")) -> Total Deposit | B5: ='入力 Inputs'!B7 -> 13000000
A6: =IF('入力 Inputs'!$F$1="English","Less: Premium Load (7%)",IF('入力 Inputs'!$F$1="日本語","差引：プレミアムロード（7%）","差引：プレミアムロード（7%） / Less: Premium Load (7%)")) -> Less: Premium Load (7%) | B6: =-'計算 Calculations'!B8 -> -910000
A7: =IF('入力 Inputs'!$F$1="English","Less: Admin & Bank Fees",IF('入力 Inputs'!$F$1="日本語","差引：管理・銀行手数料","差引：管理・銀行手数料 / Less: Admin & Bank Fees")) -> Less: Admin & Bank Fees | B7: =-'計算 Calculations'!B21 -> -21000
A8: =IF('入力 Inputs'!$F$1="English","Net to Inspira",IF('入力 Inputs'!$F$1="日本語","インスピラへの正味送金額","インスピラへの正味送金額 / Net to Inspira")) -> Net to Inspira | B8: ='計算 Calculations'!B23 -> 12069000
A9: =IF('入力 Inputs'!$F$1="English","Guaranteed Allocation (75%)",IF('入力 Inputs'!$F$1="日本語","保証配分（75%）","保証配分（75%） / Guaranteed Allocation (75%)")) -> Guaranteed Allocation (75%) | B9: ='計算 Calculations'!C31 -> 9051750
A10: =IF('入力 Inputs'!$F$1="English","Non-Guaranteed Allocation (25%)",IF('入力 Inputs'!$F$1="日本語","非保証配分（25%）","非保証配分（25%） / Non-Guaranteed Allocation (25%)")) -> Non-Guaranteed Allocation (25%) | B10: ='計算 Calculations'!C37 -> 3017250
A11: =IF('入力 Inputs'!$F$1="English","Gross Weighted Return",IF('入力 Inputs'!$F$1="日本語","加重グロスリターン","加重グロスリターン / Gross Weighted Return")) -> Gross Weighted Return | B11: ='計算 Calculations'!E39 -> 0.062525
A13: =IF('入力 Inputs'!$F$1="English","INCOME BY PARTY — WHO EARNS WHAT BY WHEN",IF('入力 Inputs'!$F$1="日本語","各当事者の収入","各当事者の収入 / INCOME BY PARTY — WHO EARNS WHAT BY WHEN")) -> INCOME BY PARTY — WHO EARNS WHAT BY WHEN
A14: =IF('入力 Inputs'!$F$1="English","Party",IF('入力 Inputs'!$F$1="日本語","当事者","当事者 / Party")) -> Party | B14: Upfront ($) | C14: Annual Recurring ($) | D14: 5-Year Total ($) | E14: 10-Year Total ($) | F14: Notes
A15: =IF('入力 Inputs'!$F$1="English","Syndicated Capital",IF('入力 Inputs'!$F$1="日本語","Syndicated Capital","Syndicated Capital")) -> Syndicated Capital | B15: ='計算 Calculations'!B11 -> 39000 | C15: — | D15: =B15 -> 39000 | E15: =B15 -> 39000 | F15: 5% holdback on premium load
A16: =IF('入力 Inputs'!$F$1="English","PB Investment Services",IF('入力 Inputs'!$F$1="日本語","PB Investment Services","PB Investment Services")) -> PB Investment Services | B16: ='計算 Calculations'!B13 -> 39000 | C16: — | D16: =B16 -> 39000 | E16: =B16 -> 39000 | F16: 5% holdback on premium load
A17: =IF('入力 Inputs'!$F$1="English","PBWR",IF('入力 Inputs'!$F$1="日本語","PBWR","PBWR")) -> PBWR | B17: ='計算 Calculations'!B15 -> 351000 | C17: — | D17: =B17 -> 351000 | E17: =B17 -> 351000 | F17: 50% of net after both holdbacks
A18: =IF('入力 Inputs'!$F$1="English","Ohana Firm",IF('入力 Inputs'!$F$1="日本語","Ohana事務所","Ohana事務所 / Ohana Firm")) -> Ohana Firm | B18: ='計算 Calculations'!B16 -> 351000 | C18: — | D18: =B18 -> 351000 | E18: =B18 -> 351000 | F18: 50% of net load — upfront program income
A19: =IF('入力 Inputs'!$F$1="English","3cStructures",IF('入力 Inputs'!$F$1="日本語","3cStructures","3cStructures / 3cStructures")) -> 3cStructures | B19: ='計算 Calculations'!B7 -> 130000 | C19: — | D19: =B19 -> 130000 | E19: =B19 -> 130000 | F19: 1% structuring fee
A20: =IF('入力 Inputs'!$F$1="English","Marketing Allowance (Regional)",IF('入力 Inputs'!$F$1="日本語","マーケティング手当（リージョナル）","マーケティング手当（リージョナル） / Marketing Allowance (Regional)")) -> Marketing Allowance (Regional) | B20: ='計算 Calculations'!I39 -> 388320.08 | C20: — | D20: =B20 -> 388320.08 | E20: =B20 -> 388320.08 | F20: Commission on annuity products at Regional rate
A21: =IF('入力 Inputs'!$F$1="English","RIA / Investment Advisor",IF('入力 Inputs'!$F$1="日本語","RIA / 投資アドバイザー","RIA / 投資アドバイザー / RIA / Investment Advisor")) -> RIA / Investment Advisor | B21: — | C21: ='計算 Calculations'!D47 -> 18103.5 | D21: =C83 -> 102566.85 | E21: =C88 -> 241467.03 | F21: 0.15% annual advisory fee on net assets — RECURRING
A22: =IF('入力 Inputs'!$F$1="English","Advantage (M&E)",IF('入力 Inputs'!$F$1="日本語","Advantage（M&E）","Advantage（M&E） / Advantage (M&E)")) -> Advantage (M&E) | B22: — | C22: ='計算 Calculations'!D46 -> 18103.5 | D22: =SUM('計算 Calculations'!D54:D58) -> 102566.85 | E22: =SUM('計算 Calculations'!D54:D63) -> 241467.03 | F22: 0.15% M&E annual charge
A23: =IF('入力 Inputs'!$F$1="English","Inspira (Custodian)",IF('入力 Inputs'!$F$1="日本語","インスピラ（保管料）","インスピラ（保管料） / Inspira (Custodian)")) -> Inspira (Custodian) | B23: — | C23: ='計算 Calculations'!D48 -> 6034.5 | D23: =SUM('計算 Calculations'!F54:F58) -> 34188.95 | E23: =SUM('計算 Calculations'!F54:F63) -> 80489.009 | F23: 0.05% custodian fee
A24: =IF('入力 Inputs'!$F$1="English","Money Manager",IF('入力 Inputs'!$F$1="日本語","マネーマネージャー","マネーマネージャー / Money Manager")) -> Money Manager | B24: — | C24: ='計算 Calculations'!D49 -> 0 | D24: =SUM('計算 Calculations'!G54:G58) -> 0 | E24: =SUM('計算 Calculations'!G54:G63) -> 0 | F24: Money Manager fee — default 0%
A26: =IF('入力 Inputs'!$F$1="English","TOTAL DEAL ECONOMICS",IF('入力 Inputs'!$F$1="日本語","取引経済合計","取引経済合計 / TOTAL DEAL ECONOMICS")) -> TOTAL DEAL ECONOMICS | B26: =B15+B16+B17+B18+B19+B20 -> 1298320.1 | C26: =C21+C22+C23+C24 -> 42241.5 | D26: =SUM(D15:D24) -> 1537642.7 | E26: =SUM(E15:E24) -> 1861743.1
A28: =IF('入力 Inputs'!$F$1="English","WHY AN RIA WANTS TO WORK WITH YOU",IF('入力 Inputs'!$F$1="日本語","RIAがあなたと仕事をしたい理由","RIAがあなたと仕事をしたい理由 / WHY AN RIA WANTS TO WORK WITH YOU")) -> WHY AN RIA WANTS TO WORK WITH YOU
A29: =IF('入力 Inputs'!$F$1="English","Annual Advisory Revenue (0.15%)",IF('入力 Inputs'!$F$1="日本語","年間アドバイザリー収入（0.15%）","年間アドバイザリー収入（0.15%） / Annual Advisory Revenue (0.15%)")) -> Annual Advisory Revenue (0.15%) | B29: =C21 -> 18103.5
A30: =IF('入力 Inputs'!$F$1="English","5-Year Cumulative Revenue",IF('入力 Inputs'!$F$1="日本語","5年累積収入","5年累積収入 / 5-Year Cumulative Revenue")) -> 5-Year Cumulative Revenue | B30: =D21 -> 102566.85
A31: =IF('入力 Inputs'!$F$1="English","10-Year Cumulative Revenue",IF('入力 Inputs'!$F$1="日本語","10年累積収入","10年累積収入 / 10-Year Cumulative Revenue")) -> 10-Year Cumulative Revenue | B31: =E21 -> 241467.03
A32: =IF('入力 Inputs'!$F$1="English","AUM Added to Practice",IF('入力 Inputs'!$F$1="日本語","プラクティスへのAUM追加","プラクティスへのAUM追加 / AUM Added to Practice")) -> AUM Added to Practice | B32: ='計算 Calculations'!B23 -> 12069000
A33: Gross Weighted Return for Client | B33: ='計算 Calculations'!E39 -> 0.062525
A35: ✔ パッシブ・リカーリング収入 — アクティブ取引不要 / Passive, recurring income — no active trading required
A36: ✔ 顧客は75%を保証商品に投資し6.25%のブレンドリターンを取得 / Client gets 6.25% blended return with 75% guaranteed
A38: =IF('入力 Inputs'!$F$1="English","WHY AN OHANA FIRM WANTS TO INTRODUCE THEIR CLIENT",IF('入力 Inputs'!$F$1="日本語","Ohana事務所が顧客を紹介したい理由","Ohana事務所が顧客を紹介したい理由 / WHY AN OHANA FIRM WANTS TO INTRODUCE THEIR CLIENT")) -> WHY AN OHANA FIRM WANTS TO INTRODUCE THEIR CLIENT
A39: =IF('入力 Inputs'!$F$1="English","Upfront Program Income (50% of net after holdbacks)",IF('入力 Inputs'!$F$1="日本語","前払いプログラム収入（ホールドバック後のネットの50%）","前払いプログラム収入（ホールドバック後のネットの50%） / Upfront Program Income (50% of net after holdbacks)")) -> Upfront Program Income (50% of net after holdbacks) | B39: =B18 -> 351000
A40: =IF('入力 Inputs'!$F$1="English","As % of Client Deposit",IF('入力 Inputs'!$F$1="日本語","顧客預入額に対する割合","顧客預入額に対する割合 / As % of Client Deposit")) -> As % of Client Deposit | B40: =B18/'入力 Inputs'!B7 -> 0.027
A41: =IF('入力 Inputs'!$F$1="English","Ohana Share % (of net load)",IF('入力 Inputs'!$F$1="日本語","Ohana分配率（ネットロードの%）","Ohana分配率（ネットロードの%） / Ohana Share % (of net load)")) -> Ohana Share % (of net load) | B41: ='入力 Inputs'!B16 -> 0.5
A42: =IF('入力 Inputs'!$F$1="English","Client Net Assets Working",IF('入力 Inputs'!$F$1="日本語","顧客の正味運用資産","顧客の正味運用資産 / Client Net Assets Working")) -> Client Net Assets Working | B42: ='計算 Calculations'!B23 -> 12069000
A44: ✔ $13M預入に対する紹介で$351,000の前払い / $351,000 upfront for a single introduction on $13M deposit
A45: ✔ 顧客は$12M以上を多様な商品に投資 / Client retains $12M+ invested in diversified products
A46: ✔ 75%が保証商品 — 顧客のための安全第一 / 75% in guaranteed products — safety-first positioning
A48: =IF('入力 Inputs'!$F$1="English","NET-TO-CLIENT RETURN WATERFALL",IF('入力 Inputs'!$F$1="日本語","顧客への正味リターンウォーターフォール","顧客への正味リターンウォーターフォール / NET-TO-CLIENT RETURN WATERFALL")) -> NET-TO-CLIENT RETURN WATERFALL
A49: =IF('入力 Inputs'!$F$1="English","Item",IF('入力 Inputs'!$F$1="日本語","項目","項目 / Item")) -> Item | B49: =IF('入力 Inputs'!$F$1="English","Rate",IF('入力 Inputs'!$F$1="日本語","率","率 / Rate")) -> Rate | C49: =IF('入力 Inputs'!$F$1="English","Notes",IF('入力 Inputs'!$F$1="日本語","備考","備考 / Notes")) -> Notes
A50: =IF('入力 Inputs'!$F$1="English","Gross Weighted Return",IF('入力 Inputs'!$F$1="日本語","加重グロスリターン","加重グロスリターン / Gross Weighted Return")) -> Gross Weighted Return | B50: ='入力 Inputs'!E32 -> 0.062525 | C50: =IF('入力 Inputs'!$F$1="English","Weighted avg of fund allocations",IF('入力 Inputs'!$F$1="日本語","ファンド配分の加重平均","ファンド配分の加重平均 / Weighted avg of fund allocations")) -> Weighted avg of fund allocations
A51: =IF('入力 Inputs'!$F$1="English","Less: Advantage M&E",IF('入力 Inputs'!$F$1="日本語","差引：Advantage M&E","差引：Advantage M&E / Less: Advantage M&E")) -> Less: Advantage M&E | B51: =-'入力 Inputs'!B41 -> -0.0015
A52: =IF('入力 Inputs'!$F$1="English","Less: RIA Advisory Fee",IF('入力 Inputs'!$F$1="日本語","差引：RIAアドバイザリー手数料","差引：RIAアドバイザリー手数料 / Less: RIA Advisory Fee")) -> Less: RIA Advisory Fee | B52: =-'入力 Inputs'!B42 -> -0.0015
A53: =IF('入力 Inputs'!$F$1="English","Less: Inspira Custodian",IF('入力 Inputs'!$F$1="日本語","差引：インスピラ保管料","差引：インスピラ保管料 / Less: Inspira Custodian")) -> Less: Inspira Custodian | B53: =-'入力 Inputs'!B43 -> -0.0005
A54: =IF('入力 Inputs'!$F$1="English","Less: Money Manager (non-guaranteed only)",IF('入力 Inputs'!$F$1="日本語","差引：マネーマネージャー手数料（非保証分のみ）","差引：マネーマネージャー手数料（非保証分のみ） / Less: Money Manager (non-guaranteed only)")) -> Less: Money Manager (non-guaranteed only) | B54: =-'入力 Inputs'!B44*('入力 Inputs'!B29+'入力 Inputs'!B30+'入力 Inputs'!B31) -> 0 | C54: =IF('入力 Inputs'!$F$1="English","Applied to non-guaranteed allocation only",IF('入力 Inputs'!$F$1="日本語","非保証配分のみに適用","非保証配分のみに適用 / Applied to non-guaranteed allocation only")) -> Applied to non-guaranteed allocation only
A55: =IF('入力 Inputs'!$F$1="English","Less: Est. COI (Year 1 equivalent)",IF('入力 Inputs'!$F$1="日本語","差引：推定COI（初年度相当）","差引：推定COI（初年度相当） / Less: Est. COI (Year 1 equivalent)")) -> Less: Est. COI (Year 1 equivalent) | B55: =-'入力 Inputs'!B57/'入力 Inputs'!B87 -> -9.8072787e-06
A56: =IF('入力 Inputs'!$F$1="English","NET RETURN TO CLIENT (Est.)",IF('入力 Inputs'!$F$1="日本語","顧客への正味リターン（推定）","顧客への正味リターン（推定） / NET RETURN TO CLIENT (Est.)")) -> NET RETURN TO CLIENT (Est.) | B56: =B50+B51+B52+B53+B54+B55 -> 0.059015193
A60: =IF('入力 Inputs'!$F$1="English","CHART DATA",IF('入力 Inputs'!$F$1="日本語","チャートデータ","チャートデータ / CHART DATA")) -> CHART DATA
A61: =IF('入力 Inputs'!$F$1="English","Fund Allocation",IF('入力 Inputs'!$F$1="日本語","ファンド配分","ファンド配分 / Fund Allocation")) -> Fund Allocation | B61: Amount ($)
A62: Intl Fixed Rate Plan Plus | B62: ='計算 Calculations'!C28 -> 4224150
A63: Intl Fixed Rate Plan | B63: ='計算 Calculations'!C29 -> 3017250
A64: US 5-Year FIA | B64: ='計算 Calculations'!C30 -> 1810350
A65: AAIDX (Alt Income) | B65: ='計算 Calculations'!C34 -> 1206900
A66: ACRE III (CRE Fund) | B66: ='計算 Calculations'!C35 -> 1206900
A67: Cash (Liquidity) | B67: ='計算 Calculations'!C36 -> 603450
A69: =IF('入力 Inputs'!$F$1="English","Upfront Income",IF('入力 Inputs'!$F$1="日本語","前払い収入","前払い収入 / Upfront Income")) -> Upfront Income | B69: Upfront ($) | C69: Annual Recurring ($)
A70: Syndicated Capital Broker Dealer | B70: =B15 -> 39000 | C70: 0
A71: PB Investment Services | B71: =B16 -> 39000 | C71: 0
A72: PBWR | B72: =B17 -> 351000 | C72: 0
A73: Ohana Firm | B73: =B18 -> 351000 | C73: 0
A74: 3cStructures | B74: =B19 -> 130000 | C74: 0
A75: RIA / Advisor | B75: 0 | C75: =C21 -> 18103.5
A76: Money Manager | B76: 0 | C76: =C24 -> 0
A78: =IF('入力 Inputs'!$F$1="English","Year",IF('入力 Inputs'!$F$1="日本語","年","年 / Year")) -> Year | B78: RIA Annual ($) | C78: RIA Cumulative ($)
A79: Year 1 | B79: =C21 -> 18103.5 | C79: =B79 -> 18103.5
A80: Year 2 | B80: =B79*(1+'入力 Inputs'!$B$51) -> 19235.421 | C80: =C79+B80 -> 37338.921
A81: Year 3 | B81: =B80*(1+'入力 Inputs'!$B$51) -> 20438.116 | C81: =C80+B81 -> 57777.037
A82: Year 4 | B82: =B81*(1+'入力 Inputs'!$B$51) -> 21716.009 | C82: =C81+B82 -> 79493.047
A83: Year 5 | B83: =B82*(1+'入力 Inputs'!$B$51) -> 23073.803 | C83: =C82+B83 -> 102566.85
A84: Year 6 | B84: =B83*(1+'入力 Inputs'!$B$51) -> 24516.492 | C84: =C83+B84 -> 127083.34
A85: Year 7 | B85: =B84*(1+'入力 Inputs'!$B$51) -> 26049.386 | C85: =C84+B85 -> 153132.73
A86: Year 8 | B86: =B85*(1+'入力 Inputs'!$B$51) -> 27678.124 | C86: =C85+B86 -> 180810.85
A87: Year 9 | B87: =B86*(1+'入力 Inputs'!$B$51) -> 29408.698 | C87: =C86+B87 -> 210219.55
A88: Year 10 | B88: =B87*(1+'入力 Inputs'!$B$51) -> 31247.477 | C88: =C87+B88 -> 241467.03
A90: =IF('入力 Inputs'!$F$1="English","Key Party Comparison",IF('入力 Inputs'!$F$1="日本語","主要当事者比較","主要当事者比較 / Key Party Comparison")) -> Key Party Comparison | B90: Upfront ($) | C90: 10-Year Total ($)
A91: Ohana Firm | B91: =B18 -> 351000 | C91: =E18 -> 351000
A92: RIA / Advisor | B92: 0 | C92: =E21 -> 241467.03
A94: =IF('入力 Inputs'!$F$1="English","Commission Tier",IF('入力 Inputs'!$F$1="日本語","コミッション階層","コミッション階層 / Commission Tier")) -> Commission Tier | B94: OGA ($) | C94: Processor ($) | D94: Regional ($)
A95: Intl Fixed Rate Plan Plus | B95: ='計算 Calculations'!F28 -> 211207.5 | C95: ='計算 Calculations'!H28 -> 200647.12 | D95: ='計算 Calculations'!I28 -> 190086.75
A96: Intl Fixed Rate Plan | B96: ='計算 Calculations'!F29 -> 129741.75 | C96: ='計算 Calculations'!H29 -> 123254.66 | D96: ='計算 Calculations'!I29 -> 116767.57
A97: US 5-Year FIA | B97: ='計算 Calculations'!F30 -> 140302.12 | C97: N/A | D97: ='計算 Calculations'!I30 -> 81465.75

Sheet Ohanaピッチ
A1: =IF('入力 Inputs'!$F$1="English","OHANA FIRM — YOUR DEAL INCOME",IF('入力 Inputs'!$F$1="日本語","Ohana事務所 — あなたの取引収入","Ohana事務所 — あなたの取引収入 / OHANA FIRM — YOUR DEAL INCOME")) -> OHANA FIRM — YOUR DEAL INCOME | E1: Party | F1: Amount
A2: =IF('入力 Inputs'!$F$1="English","Private Placement Variable Annuity — Program Income Opportunity",IF('入力 Inputs'!$F$1="日本語","プライベートプレースメント変額年金 — プログラム収入機会","プライベートプレースメント変額年金 — プログラム収入機会 / Private Placement Variable Annuity — Program Income Opportunity")) -> Private Placement Variable Annuity — Program Income Opportunity | E2: Syndicated Capital | F2: ='計算 Calculations'!B11 -> 39000
E3: 3cStructures | F3: ='計算 Calculations'!B7 -> 130000
A4: =IF('入力 Inputs'!$F$1="English","DEAL SIZE",IF('入力 Inputs'!$F$1="日本語","取引規模","取引規模 / DEAL SIZE")) -> DEAL SIZE | E4: PB Investment Services | F4: ='計算 Calculations'!B13 -> 39000
A5: =IF('入力 Inputs'!$F$1="English","Client Deposit",IF('入力 Inputs'!$F$1="日本語","顧客預入額","顧客預入額 / Client Deposit")) -> Client Deposit | B5: ='入力 Inputs'!B7 -> 13000000 | E5: Ohana Firm | F5: =B8 -> 351000
E6: Split | F6: Amount
A7: =IF('入力 Inputs'!$F$1="English","YOUR PROGRAM INCOME",IF('入力 Inputs'!$F$1="日本語","あなたのプログラム収入","あなたのプログラム収入 / YOUR PROGRAM INCOME")) -> YOUR PROGRAM INCOME | B7: Amount | E7: Guaranteed (75%) | F7: =B13 -> 9051750
A8: =IF('入力 Inputs'!$F$1="English","Upfront Program Income",IF('入力 Inputs'!$F$1="日本語","前払いプログラム収入","前払いプログラム収入 / Upfront Program Income")) -> Upfront Program Income | B8: ='計算 Calculations'!B16 -> 351000 | C8: 50% of net load — paid upfront | E8: Non-Guaranteed (25%) | F8: ='計算 Calculations'!C37 -> 3017250
A9: =IF('入力 Inputs'!$F$1="English","As % of Client Deposit",IF('入力 Inputs'!$F$1="日本語","顧客預入額に対する割合","顧客預入額に対する割合 / As % of Client Deposit")) -> As % of Client Deposit | B9: =B8/B5 -> 0.027
A11: =IF('入力 Inputs'!$F$1="English","CLIENT OUTCOME",IF('入力 Inputs'!$F$1="日本語","顧客の成果","顧客の成果 / CLIENT OUTCOME")) -> CLIENT OUTCOME
A12: =IF('入力 Inputs'!$F$1="English","Net Invested for Client",IF('入力 Inputs'!$F$1="日本語","顧客の正味投資額","顧客の正味投資額 / Net Invested for Client")) -> Net Invested for Client | B12: ='計算 Calculations'!B23 -> 12069000
A13: =IF('入力 Inputs'!$F$1="English","In Guaranteed Products (75%)",IF('入力 Inputs'!$F$1="日本語","保証商品に投資（75%）","保証商品に投資（75%） / In Guaranteed Products (75%)")) -> In Guaranteed Products (75%) | B13: ='計算 Calculations'!C31 -> 9051750
A14: =IF('入力 Inputs'!$F$1="English","Gross Weighted Return",IF('入力 Inputs'!$F$1="日本語","加重グロスリターン","加重グロスリターン / Gross Weighted Return")) -> Gross Weighted Return | B14: ='入力 Inputs'!B51 -> 0.062525
A15: =IF('入力 Inputs'!$F$1="English","Net Return to Client (est.)",IF('入力 Inputs'!$F$1="日本語","顧客への正味リターン（推定）","顧客への正味リターン（推定） / Net Return to Client (est.)")) -> Net Return to Client (est.) | B15: =B14-'計算 Calculations'!B50 -> 0.059025
A17: =IF('入力 Inputs'!$F$1="English","SCALE: INCOME BY DEPOSIT SIZE",IF('入力 Inputs'!$F$1="日本語","規模別収入一覧","規模別収入一覧 / SCALE: INCOME BY DEPOSIT SIZE")) -> SCALE: INCOME BY DEPOSIT SIZE
A18: =IF('入力 Inputs'!$F$1="English","Deposit Size",IF('入力 Inputs'!$F$1="日本語","預入額","預入額 / Deposit Size")) -> Deposit Size | B18: Program Income
A19: 5000000 | B19: =5000000*'入力 Inputs'!B11*(1-'入力 Inputs'!B13-'入力 Inputs'!B14)*'入力 Inputs'!B16 -> 135000
A20: 10000000 | B20: =10000000*'入力 Inputs'!B11*(1-'入力 Inputs'!B13-'入力 Inputs'!B14)*'入力 Inputs'!B16 -> 270000
A21: ='入力 Inputs'!B7 -> 13000000 | B21: =B8 -> 351000
A22: 20000000 | B22: =20000000*'入力 Inputs'!B11*(1-'入力 Inputs'!B13-'入力 Inputs'!B14)*'入力 Inputs'!B16 -> 540000
A23: 50000000 | B23: =50000000*'入力 Inputs'!B11*(1-'入力 Inputs'!B13-'入力 Inputs'!B14)*'入力 Inputs'!B16 -> 1350000

Sheet PBWRピッチ
A1: =IF('入力 Inputs'!$F$1="English","PBWR — YOUR DEAL INCOME",IF('入力 Inputs'!$F$1="日本語","PBWR — あなたの取引収入","PBWR — あなたの取引収入 / PBWR — YOUR DEAL INCOME")) -> PBWR — YOUR DEAL INCOME | F1: Source | G1: Amount
A2: =IF('入力 Inputs'!$F$1="English","Private Placement Variable Annuity — What You Earn",IF('入力 Inputs'!$F$1="日本語","プライベートプレースメント変額年金 — 収入内容","プライベートプレースメント変額年金 — 収入内容 / Private Placement Variable Annuity — What You Earn")) -> Private Placement Variable Annuity — What You Earn | F2: Premium Load Share | G2: =B8 -> 351000
F3: Marketing Allowance | G3: =B9 -> 481251.38
A4: =IF('入力 Inputs'!$F$1="English","DEAL SIZE",IF('入力 Inputs'!$F$1="日本語","取引規模","取引規模 / DEAL SIZE")) -> DEAL SIZE
A5: =IF('入力 Inputs'!$F$1="English","Client Deposit",IF('入力 Inputs'!$F$1="日本語","顧客預入額","顧客預入額 / Client Deposit")) -> Client Deposit | B5: ='入力 Inputs'!B7 -> 13000000 | F5: Product | G5: OGA | H5: Commission ($)
F6: Intl Fixed Rate Plan Plus | G6: =D15 -> 211207.5
A7: =IF('入力 Inputs'!$F$1="English","YOUR INCOME",IF('入力 Inputs'!$F$1="日本語","あなたの収入","あなたの収入 / YOUR INCOME")) -> YOUR INCOME | B7: Amount | F7: Intl Fixed Rate Plan | G7: =D16 -> 129741.75
A8: =IF('入力 Inputs'!$F$1="English","Premium Load Income",IF('入力 Inputs'!$F$1="日本語","プレミアムロード収入","プレミアムロード収入 / Premium Load Income")) -> Premium Load Income | B8: ='計算 Calculations'!B15 -> 351000 | C8: Your share of the upfront premium load | F8: US 5-Year FIA | G8: =D17 -> 140302.12
A9: =IF('入力 Inputs'!$F$1="English","Marketing Allowance",IF('入力 Inputs'!$F$1="日本語","マーケティング手当","マーケティング手当 / Marketing Allowance")) -> Marketing Allowance | B9: ='計算 Calculations'!F39 -> 481251.38 | C9: Annuity product commissions (OGA rate)
A11: =IF('入力 Inputs'!$F$1="English","TOTAL INCOME FROM THIS DEAL",IF('入力 Inputs'!$F$1="日本語","この取引からの合計収入","この取引からの合計収入 / TOTAL INCOME FROM THIS DEAL")) -> TOTAL INCOME FROM THIS DEAL | B11: =B8+B9 -> 832251.38
A13: =IF('入力 Inputs'!$F$1="English","COMMISSION BREAKDOWN BY PRODUCT",IF('入力 Inputs'!$F$1="日本語","商品別コミッション内訳","商品別コミッション内訳 / COMMISSION BREAKDOWN BY PRODUCT")) -> COMMISSION BREAKDOWN BY PRODUCT
A14: =IF('入力 Inputs'!$F$1="English","Annuity Product",IF('入力 Inputs'!$F$1="日本語","年金商品","年金商品 / Annuity Product")) -> Annuity Product | B14: Premium ($) | C14: Rate | D14: Commission ($)
A15: =IF('入力 Inputs'!$F$1="English","Intl Fixed Rate Plan Plus",IF('入力 Inputs'!$F$1="日本語","国際固定金利プランプラス","国際固定金利プランプラス / Intl Fixed Rate Plan Plus")) -> Intl Fixed Rate Plan Plus | B15: ='計算 Calculations'!C28 -> 4224150 | C15: ='入力 Inputs'!B36 -> 0.05 | D15: ='計算 Calculations'!F28 -> 211207.5
A16: =IF('入力 Inputs'!$F$1="English","Intl Fixed Rate Plan",IF('入力 Inputs'!$F$1="日本語","国際固定金利プラン","国際固定金利プラン / Intl Fixed Rate Plan")) -> Intl Fixed Rate Plan | B16: ='計算 Calculations'!C29 -> 3017250 | C16: ='入力 Inputs'!B37 -> 0.043 | D16: ='計算 Calculations'!F29 -> 129741.75
A17: =IF('入力 Inputs'!$F$1="English","US 5-Year FIA",IF('入力 Inputs'!$F$1="日本語","米国5年FIA","米国5年FIA / US 5-Year FIA")) -> US 5-Year FIA | B17: ='計算 Calculations'!C30 -> 1810350 | C17: ='入力 Inputs'!B38 -> 0.0775 | D17: ='計算 Calculations'!F30 -> 140302.12
A19: =IF('入力 Inputs'!$F$1="English","Total Marketing Allowance",IF('入力 Inputs'!$F$1="日本語","マーケティング手当合計","マーケティング手当合計 / Total Marketing Allowance")) -> Total Marketing Allowance | D19: ='計算 Calculations'!F39 -> 481251.38

Sheet アドバイザーピッチ
A1: =IF('入力 Inputs'!$F$1="English","RIA / INVESTMENT ADVISOR — YOUR INCOME",IF('入力 Inputs'!$F$1="日本語","RIA / 投資アドバイザー — あなたの収入","RIA / 投資アドバイザー — あなたの収入 / RIA / INVESTMENT ADVISOR — YOUR INCOME")) -> RIA / INVESTMENT ADVISOR — YOUR INCOME
A2: =IF('入力 Inputs'!$F$1="English","PPVA — Recurring Advisory Revenue",IF('入力 Inputs'!$F$1="日本語","プライベートプレースメント変額年金 — リカーリングアドバイザリー収入","プライベートプレースメント変額年金 — リカーリングアドバイザリー収入 / PPVA — Recurring Advisory Revenue")) -> PPVA — Recurring Advisory Revenue
A4: =IF('入力 Inputs'!$F$1="English","DEAL SIZE & FEE",IF('入力 Inputs'!$F$1="日本語","取引規模と手数料","取引規模と手数料 / DEAL SIZE & FEE")) -> DEAL SIZE & FEE
A5: =IF('入力 Inputs'!$F$1="English","Net AUM (from deal)",IF('入力 Inputs'!$F$1="日本語","正味AUM（取引から）","正味AUM（取引から） / Net AUM (from deal)")) -> Net AUM (from deal) | B5: ='計算 Calculations'!B23 -> 12069000
A6: =IF('入力 Inputs'!$F$1="English","Your Advisory Fee Rate",IF('入力 Inputs'!$F$1="日本語","アドバイザリー手数料率","アドバイザリー手数料率 / Your Advisory Fee Rate")) -> Your Advisory Fee Rate | B6: ='入力 Inputs'!B42 -> 0.0015 | C6: Pulls from Inputs → Syndicated / Stephen RIA %
A7: =IF('入力 Inputs'!$F$1="English","Assumed Annual Growth Rate",IF('入力 Inputs'!$F$1="日本語","想定年間成長率","想定年間成長率 / Assumed Annual Growth Rate")) -> Assumed Annual Growth Rate | B7: ='入力 Inputs'!B51 -> 0.062525 | C7: Pulls from Inputs → Growth Assumptions
A9: =IF('入力 Inputs'!$F$1="English","YOUR INCOME SUMMARY",IF('入力 Inputs'!$F$1="日本語","収入概要","収入概要 / YOUR INCOME SUMMARY")) -> YOUR INCOME SUMMARY
A10: =IF('入力 Inputs'!$F$1="English","Year 1 Advisory Fee",IF('入力 Inputs'!$F$1="日本語","1年目アドバイザリー手数料","1年目アドバイザリー手数料 / Year 1 Advisory Fee")) -> Year 1 Advisory Fee | B10: =B5*B6 -> 18103.5
A11: =IF('入力 Inputs'!$F$1="English","5-Year Cumulative",IF('入力 Inputs'!$F$1="日本語","5年累積","5年累積 / 5-Year Cumulative")) -> 5-Year Cumulative | B11: =D26 -> 102566.85
A12: =IF('入力 Inputs'!$F$1="English","10-Year Cumulative",IF('入力 Inputs'!$F$1="日本語","10年累積","10年累積 / 10-Year Cumulative")) -> 10-Year Cumulative | B12: =D31 -> 241467.03
A14: =IF('入力 Inputs'!$F$1="English","CLIENT OUTCOME",IF('入力 Inputs'!$F$1="日本語","顧客の成果","顧客の成果 / CLIENT OUTCOME")) -> CLIENT OUTCOME
A15: =IF('入力 Inputs'!$F$1="English","Gross Weighted Return",IF('入力 Inputs'!$F$1="日本語","加重グロスリターン","加重グロスリターン / Gross Weighted Return")) -> Gross Weighted Return | B15: ='入力 Inputs'!B51 -> 0.062525
A16: =IF('入力 Inputs'!$F$1="English","Less: Advisory Fee",IF('入力 Inputs'!$F$1="日本語","差引：アドバイザリー手数料","差引：アドバイザリー手数料 / Less: Advisory Fee")) -> Less: Advisory Fee | B16: =-B6 -> -0.0015
A17: =IF('入力 Inputs'!$F$1="English","Less: Other Fund Charges (M&E + Custodian + MM)",IF('入力 Inputs'!$F$1="日本語","差引：その他ファンド手数料（M&E+保管料+MM）","差引：その他ファンド手数料（M&E+保管料+MM） / Less: Other Fund Charges (M&E + Custodian + MM)")) -> Less: Other Fund Charges (M&E + Custodian + MM) | B17: =-('入力 Inputs'!B41+'入力 Inputs'!B43+'入力 Inputs'!B44) -> -0.002
A18: =IF('入力 Inputs'!$F$1="English","Net Return to Client",IF('入力 Inputs'!$F$1="日本語","顧客への正味リターン","顧客への正味リターン / Net Return to Client")) -> Net Return to Client | B18: =B15+B16+B17 -> 0.059025
A20: =IF('入力 Inputs'!$F$1="English","10-YEAR INCOME PROJECTION",IF('入力 Inputs'!$F$1="日本語","10年間収入予測","10年間収入予測 / 10-YEAR INCOME PROJECTION")) -> 10-YEAR INCOME PROJECTION
A21: =IF('入力 Inputs'!$F$1="English","Year",IF('入力 Inputs'!$F$1="日本語","年","年 / Year")) -> Year | B21: AUM ($) | C21: Annual Fee ($) | D21: Cumulative ($) | F21: Year | G21: Annual Fee ($) | H21: Cumulative ($)
A22: Year 1 | B22: =$B$5 -> 12069000 | C22: =B22*$B$6 -> 18103.5 | D22: =C22 -> 18103.5 | F22: =A22 -> Year 1 | G22: =C22 -> 18103.5 | H22: =D22 -> 18103.5
A23: Year 2 | B23: =B22*(1+$B$7) -> 12823614 | C23: =B23*$B$6 -> 19235.421 | D23: =D22+C23 -> 37338.921 | F23: =A23 -> Year 2 | G23: =C23 -> 19235.421 | H23: =D23 -> 37338.921
A24: Year 3 | B24: =B23*(1+$B$7) -> 13625411 | C24: =B24*$B$6 -> 20438.116 | D24: =D23+C24 -> 57777.037 | F24: =A24 -> Year 3 | G24: =C24 -> 20438.116 | H24: =D24 -> 57777.037
A25: Year 4 | B25: =B24*(1+$B$7) -> 14477340 | C25: =B25*$B$6 -> 21716.009 | D25: =D24+C25 -> 79493.047 | F25: =A25 -> Year 4 | G25: =C25 -> 21716.009 | H25: =D25 -> 79493.047
A26: Year 5 | B26: =B25*(1+$B$7) -> 15382535 | C26: =B26*$B$6 -> 23073.803 | D26: =D25+C26 -> 102566.85 | F26: =A26 -> Year 5 | G26: =C26 -> 23073.803 | H26: =D26 -> 102566.85
A27: Year 6 | B27: =B26*(1+$B$7) -> 16344328 | C27: =B27*$B$6 -> 24516.492 | D27: =D26+C27 -> 127083.34 | F27: =A27 -> Year 6 | G27: =C27 -> 24516.492 | H27: =D27 -> 127083.34
A28: Year 7 | B28: =B27*(1+$B$7) -> 17366257 | C28: =B28*$B$6 -> 26049.386 | D28: =D27+C28 -> 153132.73 | F28: =A28 -> Year 7 | G28: =C28 -> 26049.386 | H28: =D28 -> 153132.73
A29: Year 8 | B29: =B28*(1+$B$7) -> 18452083 | C29: =B29*$B$6 -> 27678.124 | D29: =D28+C29 -> 180810.85 | F29: =A29 -> Year 8 | G29: =C29 -> 27678.124 | H29: =D29 -> 180810.85
A30: Year 9 | B30: =B29*(1+$B$7) -> 19605799 | C30: =B30*$B$6 -> 29408.698 | D30: =D29+C30 -> 210219.55 | F30: =A30 -> Year 9 | G30: =C30 -> 29408.698 | H30: =D30 -> 210219.55
A31: Year 10 | B31: =B30*(1+$B$7) -> 20831652 | C31: =B31*$B$6 -> 31247.477 | D31: =D30+C31 -> 241467.03 | F31: =A31 -> Year 10 | G31: =C31 -> 31247.477 | H31: =D31 -> 241467.03

Sheet MMピッチ MM Pitch
A1: =IF('入力 Inputs'!$F$1="English","MONEY MANAGER — YOUR SUB-ADVISORY INCOME",IF('入力 Inputs'!$F$1="日本語","マネーマネージャー — あなたのサブアドバイザリー収入","マネーマネージャー — あなたのサブアドバイザリー収入 / MONEY MANAGER — YOUR SUB-ADVISORY INCOME")) -> MONEY MANAGER — YOUR SUB-ADVISORY INCOME
A2: =IF('入力 Inputs'!$F$1="English","Private Placement Variable Annuity — Institutional Sub-Advisory Mandate",IF('入力 Inputs'!$F$1="日本語","プライベートプレースメント変額年金 — 機関投資家マンデート","プライベートプレースメント変額年金 — 機関投資家マンデート / Private Placement Variable Annuity — Institutional Sub-Advisory Mandate")) -> Private Placement Variable Annuity — Institutional Sub-Advisory Mandate
A4: =IF('入力 Inputs'!$F$1="English","MANDATE SIZE",IF('入力 Inputs'!$F$1="日本語","マンデート規模","マンデート規模 / MANDATE SIZE")) -> MANDATE SIZE
A5: =IF('入力 Inputs'!$F$1="English","AUM Sub-Advised",IF('入力 Inputs'!$F$1="日本語","サブアドバイズAUM","サブアドバイズAUM / AUM Sub-Advised")) -> AUM Sub-Advised | B5: ='入力 Inputs'!C29+'入力 Inputs'!C30 -> 2413800
A6: =IF('入力 Inputs'!$F$1="English","Management Fee Rate",IF('入力 Inputs'!$F$1="日本語","管理報酬率","管理報酬率 / Management Fee Rate")) -> Management Fee Rate | B6: ='入力 Inputs'!B44 -> 0
A7: =IF('入力 Inputs'!$F$1="English","Assumed Annual Growth Rate",IF('入力 Inputs'!$F$1="日本語","想定年間成長率","想定年間成長率 / Assumed Annual Growth Rate")) -> Assumed Annual Growth Rate | B7: ='入力 Inputs'!B51 -> 0.062525
A9: =IF('入力 Inputs'!$F$1="English","YOUR INCOME SUMMARY",IF('入力 Inputs'!$F$1="日本語","収入概要","収入概要 / YOUR INCOME SUMMARY")) -> YOUR INCOME SUMMARY
A10: =IF('入力 Inputs'!$F$1="English","Year 1 Management Fee",IF('入力 Inputs'!$F$1="日本語","1年目管理報酬","1年目管理報酬 / Year 1 Management Fee")) -> Year 1 Management Fee | B10: =B5*B6 -> 0
A11: =IF('入力 Inputs'!$F$1="English","5-Year Cumulative",IF('入力 Inputs'!$F$1="日本語","5年累積","5年累積 / 5-Year Cumulative")) -> 5-Year Cumulative | B11: {=SUMPRODUCT(B5*(1+'入力 Inputs'!B51)^{0,1,2,3,4})*B6} -> 0
A12: =IF('入力 Inputs'!$F$1="English","10-Year Cumulative",IF('入力 Inputs'!$F$1="日本語","10年累積","10年累積 / 10-Year Cumulative")) -> 10-Year Cumulative | B12: {=SUMPRODUCT(B5*(1+'入力 Inputs'!B51)^{0,1,2,3,4,5,6,7,8,9})*B6} -> 0
A14: =IF('入力 Inputs'!$F$1="English","VALUE PROPOSITION",IF('入力 Inputs'!$F$1="日本語","価値提案","価値提案 / VALUE PROPOSITION")) -> VALUE PROPOSITION
A15: =IF('入力 Inputs'!$F$1="English","✔ Zero client acquisition cost — sticky institutional AUM",IF('入力 Inputs'!$F$1="日本語","✔ 顧客獲得コストなし — スティッキーな機関AUM","✔ 顧客獲得コストなし — スティッキーな機関AUM / ✔ Zero client acquisition cost — sticky institutional AUM")) -> ✔ Zero client acquisition cost — sticky institutional AUM
A16: =IF('入力 Inputs'!$F$1="English","✔ Locked assets during surrender charge period",IF('入力 Inputs'!$F$1="日本語","✔ 解約手数料期間中はロックされた資産","✔ 解約手数料期間中はロックされた資産 / ✔ Locked assets during surrender charge period")) -> ✔ Locked assets during surrender charge period
A17: =IF('入力 Inputs'!$F$1="English","✔ Long-duration mandate — minimum 5-year horizon",IF('入力 Inputs'!$F$1="日本語","✔ 長期マンデート — 最低5年のホライズン","✔ 長期マンデート — 最低5年のホライズン / ✔ Long-duration mandate — minimum 5-year horizon")) -> ✔ Long-duration mandate — minimum 5-year horizon
A18: =IF('入力 Inputs'!$F$1="English","✔ Pipeline potential for additional mandates",IF('入力 Inputs'!$F$1="日本語","✔ 追加マンデートのパイプライン可能性","✔ 追加マンデートのパイプライン可能性 / ✔ Pipeline potential for additional mandates")) -> ✔ Pipeline potential for additional mandates
